Workbook

Sheet Cover
B3: APPLE INC.
B6: Equity Research & Financial Projection Model
B10: Ticker: | C10: AAPL (NASDAQ)
B11: Sector: | C11: Technology
B12: Sub-Industry: | C12: Technology Hardware & Equipment
B13: Model Version: | C13: v1.0
B14: Prepared By: | C14: Equity Research
B15: Date: | C15: 14 March 2026
B16: Fiscal Year End: | C16: Last Saturday of September
B17: Currency: | C17: USD ($millions)
B18: Hist. Period: | C18: FY2021 – FY2025
B19: Proj. Period: | C19: FY2026E – FY2030E
B20: DISCLAIMER: This financial model is prepared for analytical and informational purposes only. It does not constitute investment advice. Projections are based on publicly available data and reasonable assumptions; actual results may differ materially.
B25: MODEL STRUCTURE
B26: =HYPERLINK("#'Assumptions & Drivers'!A5","Assumptions & Drivers") -> Assumptions & Drivers | C26: =HYPERLINK("#'Assumptions & Drivers'!B65","READ ME") -> READ ME
B27: =HYPERLINK("#'Income Statement'!A5","Income Statement") -> Income Statement | C27: Historical P&L (FY2021–FY2025) with 5 year forward projections
B28: =HYPERLINK("#'Cash Flow Statement'!A5","Cash Flow Statement") -> Cash Flow Statement | C28: Historical cash flows (FY2021–FY2025) with 5 year forward projections
B29: =HYPERLINK("#'Balance Sheet'!A5","Balance Sheet") -> Balance Sheet | C29: Historical balance sheet (FY2021–FY2025) with 5 year forward projections
B30: =HYPERLINK("#'Financial Summary'!A5","Financial Summary") -> Financial Summary | C30: Includes key ratios for comparable analysis
B31: =HYPERLINK("#'DCF'!A5","DCF") -> DCF | C31: Implied Share Price
B32: =HYPERLINK("#'Sensitivity Analysis'!A5","Sensitivity Analysis") -> Sensitivity Analysis | C32: Currently based on Implied Share Price and Year 5 EBITDA
B33: =HYPERLINK("#'Scenario Analysis'!A5","Scenario Analysis") -> Scenario Analysis | C33: Figure projections for potential scenarios

Sheet Assumptions & Drivers
B1: ASSUMPTIONS & DRIVERS
B2: Model Version 1.0 | All projections in USD ($millions) | Blue = editable input
B4: Assumption / Driver | C4: Notes / Source | D4: FY2025A | E4: FY2026E | F4: FY2027E | G4: FY2028E | H4: FY2029E | I4: FY2030E
B6: 1. REVENUE GROWTH ASSUMPTIONS | M6: Metric Tweaks | N6: CHECK
B7: Product Revenue Growth (YoY %) | C7: iPhone, Mac, iPad, Wearables | D7: ='Income Statement'!G7/'Income Statement'!F7-1 -> 0.04116107 | E7: 0.04116107 | F7: 0.04116107 | G7: 0.04116107 | H7: 0.04116107 | I7: 0.04116107 | M7: =HYPERLINK("#D44","Theoretical WACC?") -> Theoretical WACC? | N7: =_xlfn.ISFORMULA(D45) -> TRUE
B8: Services Revenue Growth (YoY %) | C8: App Store, AppleCare, iCloud, etc. | D8: ='Income Statement'!G8/'Income Statement'!F8-1 -> 0.13506431 | E8: 0.13506431 | F8: 0.13506431 | G8: 0.13506431 | H8: 0.13506431 | I8: 0.13506431 | M8: =HYPERLINK("#E7","Normal Revenue Growth?") -> Normal Revenue Growth? | N8: =AND(ABS(E7-D7)/D7<0.1,ABS(E8-D8)/D8<0.1) -> TRUE
B10: 2. MARGIN ASSUMPTIONS | M10: =HYPERLINK("#D52","Normal Terminal Growth?") -> Normal Terminal Growth? | N10: =D53 -> 0.025
B11: Product Gross Margin (%) | C11: Hardware margin; modest expansion from mix | D11: =('Income Statement'!G7-'Income Statement'!G14)/'Income Statement'!G7 -> 0.3677065 | E11: 0.367 | F11: 0.372 | G11: 0.377 | H11: 0.37 | I11: 0.37 | M11: =HYPERLINK("#D53","Normal Exit Multiple?") -> Normal Exit Multiple? | N11: =D54 -> 15
B12: Services Gross Margin (%) | C12: High-margin software/services segment | D12: =('Income Statement'!G8-'Income Statement'!G15)/'Income Statement'!G8 -> 0.75408124 | E12: 0.757 | F12: 0.762 | G12: 0.767 | H12: 0.75 | I12: 0.75
B13: R&D as % of Revenue | C13: Sustained investment in silicon, AI, XR | D13: ='Income Statement'!G25/'Income Statement'!G10 -> 0.083020754 | E13: 0.084 | F13: 0.083 | G13: 0.082 | H13: 0.081 | I13: 0.08
B14: SG&A as % of Revenue | C14: Operating leverage on fixed cost base | D14: ='Income Statement'!G28/'Income Statement'!G10 -> 0.066322889 | E14: 0.065 | F14: 0.064 | G14: 0.063 | H14: 0.062 | I14: 0.061
B16: 3. DEPRECIATION, AMORTIZATION & CAPEX
B17: D&A as % of Revenue | C17: Stable asset base; modest PP&E growth | D17: ='Cash Flow Statement'!G9/'Income Statement'!G10 -> 0.028109313 | E17: 0.028 | F17: 0.028 | G17: 0.027 | H17: 0.027 | I17: 0.027
B18: CapEx Intensity (CapEx / Revenue) | C18: Data centre, retail, R&D facilities | D18: =-'Cash Flow Statement'!G25/'Income Statement'!G10 -> 0.030553079 | E18: 0.031 | F18: 0.03 | G18: 0.029 | H18: 0.029 | I18: 0.028
B19: SBC as % of Revenue | C19: Sustains talent via RSU/option programmes | D19: ='Cash Flow Statement'!G10/'Income Statement'!G10 -> 0.030908711 | E19: 0.031 | F19: 0.031 | G19: 0.03 | H19: 0.03 | I19: 0.029
B21: 4. WORKING CAPITAL DAYS
B22: Days Sales Outstanding (DSO) | C22: AR / Revenue × 365 | D22: ='Balance Sheet'!G10/'Income Statement'!G10*365 -> 34.886991
B23: Days Inventory Outstanding (DIO) | C23: Inventory / COGS × 365 | D23: ='Balance Sheet'!G12/'Income Statement'!G18*365 -> 9.4454652
B24: Days Payable Outstanding (DPO) | C24: AP / COGS × 365 | D24: ='Balance Sheet'!G31/'Income Statement'!G18*365 -> 115.40052
B26: 5. TAX RATE & INTEREST
B27: Effective Tax Rate (%) | C27: Blended rate; elevated FY24 normalises | D27: ='Income Statement'!G47/'Income Statement'!G44 -> 0.15610002 | E27: 0.21 | F27: 0.21 | G27: 0.21 | H27: 0.21 | I27: 0.21
B28: Interest Income Rate (% on avg. cash) | C28: Short-term yields modestly declining | E28: 0.042 | F28: 0.04 | G28: 0.038 | H28: 0.037 | I28: 0.036
B29: Interest Expense Rate (% on avg. debt) | C29: Average coupon on long-term debt | E29: 0.03 | F29: 0.029 | G29: 0.028 | H29: 0.028 | I29: 0.027
B31: 6. CAPITAL RETURN ASSUMPTIONS
B32: Annual Share Buyback ($mm) | C32: Assumes sustained ~$90bn programme | E32: 90000 | F32: 85000 | G32: 80000 | H32: 75000 | I32: 70000
B33: Annual Dividend per Share ($) | C33: ~5% annual growth in DPS | D33: 1.0277448 | E33: =MID($C$33,2,1)/100+D33 -> 1.0777448 | F33: =MID($C$33,2,1)/100+E33 -> 1.1277448 | G33: =MID($C$33,2,1)/100+F33 -> 1.1777448 | H33: =MID($C$33,2,1)/100+G33 -> 1.2277448 | I33: =MID($C$33,2,1)/100+H33 -> 1.2777448
B35: 7. WACC COMPONENTS (for reference)
B36: Risk-Free Rate (10Y UST Yield, %) | C36: 4.30% | D36: 0.043
B37: Equity Risk Premium (%) | C37: Damodaran Jan-2025 | D37: 0.048
B38: Beta (5Y Monthly, vs. S&P 500) | C38: Bloomberg | D38: 1.25
B39: Cost of Equity – CAPM (%) | C39: Rf + β × ERP (CAPM) | D39: =D36+D38*D37 -> 0.103 | E39: * Suggested 9%
B40: Pre-Tax Cost of Debt (%) | C40: Weighted avg. coupon | D40: 0.03
B41: Marginal Tax Rate (%) | C41: Federal + state blended | D41: 0.21
B42: After-Tax Cost of Debt (%) | C42: kd × (1 – tax rate) | D42: =D40*(1-D41) -> 0.0237 | E42: * Suggested 5%
B43: Equity Weight (%) | C43: Market cap / EV | D43: 0.94
B44: Debt Weight (%) | C44: Net debt / EV | D44: 0.06
B45: WACC (%) | C45: ke×We + kd×Wd×(1-t) | D45: =D39*D43+D42*D44 -> 0.098242 | E45: *Suggested 8% for APPL's massive cash moat, low bankruptcy risk and consistent stock buybacks
B47: 8. DILUTED SHARE COUNT
B48: Beginning Diluted Shares | C48: End of prior year count | D48: ='Income Statement'!G53 -> 15004697000
B49: Net Shares Retired via Buybacks | C49: Assumed avg. price for retirement | E49: 550000000 | F49: 500000000 | G49: 460000000 | H49: 420000000 | I49: 390000000
B50: SBC Dilution | C50: Options + RSU vesting | E50: 100000000 | F50: 95000000 | G50: 90000000 | H50: 85000000 | I50: 80000000
B52: 9. TERMINAL VALUE
B53: Terminal Growth Rate (Gordon Growth) | C53: Long-run perpetuity nominal growth rate | D53: 0.025
B54: Exit EV/EBITDA Multiple | C54: Peer group median terminal exit multiple | D54: 15
B56: 10. STOCK MARKET VALUES
B57: Stock Price | D57: 250
B58: Shares Outstanding | D58: =D48 -> 15004697000
B59: Market Capitalization | D59: =D57*D58 -> 3751174250000
B60: Cash | D60: ='Balance Sheet'!G8 -> 35934000000
B61: Debt | D61: ='Balance Sheet'!G39 -> 78328000000
B62: EV | D62: =D59+D61-D60 -> 3793568250000
B65: COLOUR LEGEND
B66: Blue text | C66: Hardcoded inputs — edit these cells for intended analysis
B67: Green text | C67: Formula linked from another sheet in this workbook
B68: Black text | C68: Calculated formula — do not overwrite

Sheet Raw (Income Statement)
A1: RAW | I1: ADJUSTED
A2: AAPL_income-statement_Annual_As_Originally_Reported | B2: 2021 | C2: 2022 | D2: 2023 | E2: 2024 | F2: 2025 | G2: TTM | I2: =A2 -> AAPL_income-statement_Annual_As_Originally_Reported | J2: =B2 -> 2021 | K2: =C2 -> 2022 | L2: =D2 -> 2023 | M2: =E2 -> 2024 | N2: =F2 -> 2025 | O2: =G2 -> TTM
A3: Gross Profit | B3: 152836000000 | C3: 170782000000 | D3: 169148000000 | E3: 180683000000 | F3: 195201000000 | G3: 206157000000 | I3: =A3 -> Gross Profit | J3: =B3 -> 152836000000 | K3: =C3 -> 170782000000 | L3: =D3 -> 169148000000 | M3: =E3 -> 180683000000 | N3: =F3 -> 195201000000 | O3: =G3 -> 206157000000
A4: Total Revenue | B4: 365817000000 | C4: 394328000000 | D4: 383285000000 | E4: 391035000000 | F4: 416161000000 | G4: 435617000000 | I4: =A4 -> Total Revenue | J4: =B4 -> 365817000000 | K4: =C4 -> 394328000000 | L4: =D4 -> 383285000000 | M4: =E4 -> 391035000000 | N4: =F4 -> 416161000000 | O4: =G4 -> 435617000000
A5: Business Revenue | B5: 365817000000 | C5: 394328000000 | D5: 383285000000 | E5: 391035000000 | F5: 416161000000 | G5: 435617000000 | I5: -Products | J5: 297392000000 | K5: 316199000000 | L5: 298085000000 | M5: 294866000000 | N5: 307003000000
A6: Cost of Revenue | B6: -212981000000 | C6: -223546000000 | D6: -214137000000 | E6: -210352000000 | F6: -220960000000 | G6: -229460000000 | I6: -Services | J6: 68425000000 | K6: 78129000000 | L6: 85200000000 | M6: 96169000000 | N6: 109158000000
A7: Cost of Goods and Services | B7: -212981000000 | C7: -223546000000 | D7: -214137000000 | E7: -210352000000 | F7: -220960000000 | G7: -229460000000 | I7: Reconcialiation Check | J7: =ABS(SUM(J5:J6))=ABS(J4) -> TRUE | K7: =ABS(SUM(K5:K6))=ABS(K4) -> TRUE | L7: =ABS(SUM(L5:L6))=ABS(L4) -> TRUE | M7: =ABS(SUM(M5:M6))=ABS(M4) -> TRUE | N7: =ABS(SUM(N5:N6))=ABS(N4) -> TRUE | P7: =AND(J7:O7) -> TRUE
A8: Operating Income/Expenses | B8: -43887000000 | C8: -51345000000 | D8: -54847000000 | E8: -57467000000 | F8: -62151000000 | G8: -65087000000 | I8: =A5 -> Business Revenue | J8: =B5 -> 365817000000 | K8: =C5 -> 394328000000 | L8: =D5 -> 383285000000 | M8: =E5 -> 391035000000 | N8: =F5 -> 416161000000 | O8: =G5 -> 435617000000
A9: Selling, General and Administrative Expenses | B9: -21973000000 | C9: -25094000000 | D9: -24932000000 | E9: -26097000000 | F9: -27601000000 | G9: -27918000000 | I9: =A6 -> Cost of Revenue | J9: =B6 -> -212981000000 | K9: =C6 -> -223546000000 | L9: =D6 -> -214137000000 | M9: =E6 -> -210352000000 | N9: =F6 -> -220960000000 | O9: =G6 -> -229460000000
A10: Research and Development Expenses | B10: -21914000000 | C10: -26251000000 | D10: -29915000000 | E10: -31370000000 | F10: -34550000000 | G10: -37169000000 | I10: =A7 -> Cost of Goods and Services | J10: =B7 -> -212981000000 | K10: =C7 -> -223546000000 | L10: =D7 -> -214137000000 | M10: =E7 -> -210352000000 | N10: =F7 -> -220960000000
A11: Total Operating Profit/Loss | B11: 108949000000 | C11: 119437000000 | D11: 114301000000 | E11: 123216000000 | F11: 133050000000 | G11: 141070000000 | I11: -Products | J11: 192266000000 | K11: 201471000000 | L11: 189282000000 | M11: 185233000000 | N11: 194116000000
A12: Non-Operating Income/Expense, Total | B12: 258000000 | C12: -334000000 | D12: -565000000 | E12: 269000000 | F12: -321000000 | G12: 77000000 | I12: -Services | J12: 20715000000 | K12: 22075000000 | L12: 24855000000 | M12: 25119000000 | N12: 26844000000
A13: Other Income/Expense, Non-Operating | B13: 60000000 | C13: -228000000 | D13: -382000000 | E13: 269000000 | F13: -321000000 | G13: 77000000 | I13: Reconcialiation Check | J13: =ABS(SUM(J11:J12))=ABS(J10) -> TRUE | K13: =ABS(SUM(K11:K12))=ABS(K10) -> TRUE | L13: =ABS(SUM(L11:L12))=ABS(L10) -> TRUE | M13: =ABS(SUM(M11:M12))=ABS(M10) -> TRUE | N13: =ABS(SUM(N11:N12))=ABS(N10) -> TRUE | P13: =AND(J13:O13) -> TRUE
A14: Total Net Finance Income/Expense | B14: 198000000 | C14: -106000000 | D14: -183000000 | I14: =A8 -> Operating Income/Expenses | J14: =B8 -> -43887000000 | K14: =C8 -> -51345000000 | L14: =D8 -> -54847000000 | M14: =E8 -> -57467000000 | N14: =F8 -> -62151000000 | O14: =G8 -> -65087000000
A15: Net Interest Income/Expense | B15: 198000000 | C15: -106000000 | D15: -183000000 | I15: =A9 -> Selling, General and Administrative Expenses | J15: =B9 -> -21973000000 | K15: =C9 -> -25094000000 | L15: =D9 -> -24932000000 | M15: =E9 -> -26097000000 | N15: =F9 -> -27601000000 | O15: =G9 -> -27918000000
A16: Interest Expense Net of Capitalized Interest | B16: -2645000000 | C16: -2931000000 | D16: -3933000000 | I16: =A10 -> Research and Development Expenses | J16: =B10 -> -21914000000 | K16: =C10 -> -26251000000 | L16: =D10 -> -29915000000 | M16: =E10 -> -31370000000 | N16: =F10 -> -34550000000 | O16: =G10 -> -37169000000
A17: Interest Income | B17: 2843000000 | C17: 2825000000 | D17: 3750000000 | I17: =A11 -> Total Operating Profit/Loss | J17: =B11 -> 108949000000 | K17: =C11 -> 119437000000 | L17: =D11 -> 114301000000 | M17: =E11 -> 123216000000 | N17: =F11 -> 133050000000 | O17: =G11 -> 141070000000
A18: Pretax Income | B18: 109207000000 | C18: 119103000000 | D18: 113736000000 | E18: 123485000000 | F18: 132729000000 | G18: 141147000000 | I18: =A12 -> Non-Operating Income/Expense, Total | J18: =B12 -> 258000000 | K18: =C12 -> -334000000 | L18: =D12 -> -565000000 | M18: =E12 -> 269000000 | N18: =F12 -> -321000000 | O18: =G12 -> 77000000
A19: Provision for Income Tax | B19: -14527000000 | C19: -19300000000 | D19: -16741000000 | E19: -29749000000 | F19: -20719000000 | G19: -23370000000 | I19: =A13 -> Other Income/Expense, Non-Operating | J19: =B13 -> 60000000 | K19: =C13 -> -228000000 | L19: =D13 -> -382000000 | M19: =E13 -> 269000000 | N19: =F13 -> -321000000 | O19: =G13 -> 77000000
A20: Net Income before Extraordinary Items and Discontinued Operations | B20: 94680000000 | C20: 99803000000 | D20: 96995000000 | E20: 93736000000 | F20: 112010000000 | G20: 117777000000 | I20: =A14 -> Total Net Finance Income/Expense | J20: =B14 -> 198000000 | K20: =C14 -> -106000000 | L20: =D14 -> -183000000 | M20: =E14 | N20: =F14 | O20: =G14
A21: Net Income after Extraordinary Items and Discontinued Operations | B21: 94680000000 | C21: 99803000000 | D21: 96995000000 | E21: 93736000000 | F21: 112010000000 | G21: 117777000000 | I21: =A15 -> Net Interest Income/Expense | J21: =B15 -> 198000000 | K21: =C15 -> -106000000 | L21: =D15 -> -183000000 | M21: =E15 | N21: =F15 | O21: =G15
A22: Net Income after Non-Controlling/Minority Interests | B22: 94680000000 | C22: 99803000000 | D22: 96995000000 | E22: 93736000000 | F22: 112010000000 | G22: 117777000000 | I22: =A16 -> Interest Expense Net of Capitalized Interest | J22: =B16 -> -2645000000 | K22: =C16 -> -2931000000 | L22: =D16 -> -3933000000 | M22: =E16 | N22: =F16 | O22: =G16
A23: Net Income Available to Common Stockholders | B23: 94680000000 | C23: 99803000000 | D23: 96995000000 | E23: 93736000000 | F23: 112010000000 | G23: 117777000000 | I23: =A17 -> Interest Income | J23: =B17 -> 2843000000 | K23: =C17 -> 2825000000 | L23: =D17 -> 3750000000 | M23: =E17 | N23: =F17 | O23: =G17
A24: Diluted Net Income Available to Common Stockholders | B24: 94680000000 | C24: 99803000000 | D24: 96995000000 | E24: 93736000000 | F24: 112010000000 | G24: 117777000000 | I24: =A18 -> Pretax Income | J24: =B18 -> 109207000000 | K24: =C18 -> 119103000000 | L24: =D18 -> 113736000000 | M24: =E18 -> 123485000000 | N24: =F18 -> 132729000000 | O24: =G18 -> 141147000000
A25: Income Statement Supplemental Section | I25: =A19 -> Provision for Income Tax | J25: =B19 -> -14527000000 | K25: =C19 -> -19300000000 | L25: =D19 -> -16741000000 | M25: =E19 -> -29749000000 | N25: =F19 -> -20719000000 | O25: =G19 -> -23370000000
A26: Reported Normalized and Operating Income/Expense Supplemental Section | I26: =A20 -> Net Income before Extraordinary Items and Discontinued Operations | J26: =B20 -> 94680000000 | K26: =C20 -> 99803000000 | L26: =D20 -> 96995000000 | M26: =E20 -> 93736000000 | N26: =F20 -> 112010000000 | O26: =G20 -> 117777000000
A27: Total Revenue as Reported, Supplemental | B27: 365817000000 | C27: 394328000000 | D27: 383285000000 | E27: 391035000000 | F27: 416161000000 | G27: 435617000000 | I27: =A21 -> Net Income after Extraordinary Items and Discontinued Operations | J27: =B21 -> 94680000000 | K27: =C21 -> 99803000000 | L27: =D21 -> 96995000000 | M27: =E21 -> 93736000000 | N27: =F21 -> 112010000000 | O27: =G21 -> 117777000000
A28: Reported Operating Expense | B28: -43887000000 | C28: -51345000000 | D28: -54847000000 | E28: -57467000000 | F28: -62151000000 | G28: -65087000000 | I28: =A22 -> Net Income after Non-Controlling/Minority Interests | J28: =B22 -> 94680000000 | K28: =C22 -> 99803000000 | L28: =D22 -> 96995000000 | M28: =E22 -> 93736000000 | N28: =F22 -> 112010000000 | O28: =G22 -> 117777000000
A29: Reported Total Operating Profit/Loss | B29: 108949000000 | C29: 119437000000 | D29: 114301000000 | E29: 123216000000 | F29: 133050000000 | G29: 141070000000 | I29: =A23 -> Net Income Available to Common Stockholders | J29: =B23 -> 94680000000 | K29: =C23 -> 99803000000 | L29: =D23 -> 96995000000 | M29: =E23 -> 93736000000 | N29: =F23 -> 112010000000 | O29: =G23 -> 117777000000
A30: Reported Effective Tax Rate | B30: 0.133 | C30: 0.162 | D30: 0.147 | E30: 0.241 | F30: 0.156 | I30: =A24 -> Diluted Net Income Available to Common Stockholders | J30: =B24 -> 94680000000 | K30: =C24 -> 99803000000 | L30: =D24 -> 96995000000 | M30: =E24 -> 93736000000 | N30: =F24 -> 112010000000 | O30: =G24 -> 117777000000
A31: Reported Normalized Income | E31: 103982000000 | I31: =A25 -> Income Statement Supplemental Section | J31: =B25 | K31: =C25 | L31: =D25 | M31: =E25 | N31: =F25 | O31: =G25
A32: Basic EPS | B32: 5.67 | C32: 6.15 | D32: 6.16 | E32: 6.11 | F32: 7.49 | G32: 7.92 | I32: =A26 -> Reported Normalized and Operating Income/Expense Supplemental Section | J32: =B26 | K32: =C26 | L32: =D26 | M32: =E26 | N32: =F26 | O32: =G26
A33: Basic EPS from Continuing Operations | B33: 5.67 | C33: 6.15 | D33: 6.16 | E33: 6.11 | F33: 7.49 | G33: 7.92 | I33: =A27 -> Total Revenue as Reported, Supplemental | J33: =B27 -> 365817000000 | K33: =C27 -> 394328000000 | L33: =D27 -> 383285000000 | M33: =E27 -> 391035000000 | N33: =F27 -> 416161000000 | O33: =G27 -> 435617000000
A34: Diluted EPS | B34: 5.61 | C34: 6.11 | D34: 6.13 | E34: 6.08 | F34: 7.46 | G34: 7.91 | I34: =A28 -> Reported Operating Expense | J34: =B28 -> -43887000000 | K34: =C28 -> -51345000000 | L34: =D28 -> -54847000000 | M34: =E28 -> -57467000000 | N34: =F28 -> -62151000000 | O34: =G28 -> -65087000000
A35: Diluted EPS from Continuing Operations | B35: 5.61 | C35: 6.11 | D35: 6.13 | E35: 6.08 | F35: 7.46 | G35: 7.9 | I35: =A29 -> Reported Total Operating Profit/Loss | J35: =B29 -> 108949000000 | K35: =C29 -> 119437000000 | L35: =D29 -> 114301000000 | M35: =E29 -> 123216000000 | N35: =F29 -> 133050000000 | O35: =G29 -> 141070000000
A36: Basic Weighted Average Shares Outstanding | B36: 16701272000 | C36: 16215963000 | D36: 15744231000 | E36: 15343783000 | F36: 14948500000 | G36: 14865108500 | I36: =A30 -> Reported Effective Tax Rate | J36: =B30 -> 0.133 | K36: =C30 -> 0.162 | L36: =D30 -> 0.147 | M36: =E30 -> 0.241 | N36: =F30 -> 0.156 | O36: =G30
A37: Diluted Weighted Average Shares Outstanding | B37: 16864919000 | C37: 16325819000 | D37: 15812547000 | E37: 15408095000 | F37: 15004697000 | G37: 14919569750 | I37: =A31 -> Reported Normalized Income | J37: =B31 | K37: =C31 | L37: =D31 | M37: =E31 -> 103982000000 | N37: =F31 | O37: =G31
A38: Total Dividend Per Share | B38: 0.85 | C38: 0.9 | D38: 0.94 | E38: 0.98 | F38: 1.02 | G38: 1.03 | I38: =A32 -> Basic EPS | J38: =B32 -> 5.67 | K38: =C32 -> 6.15 | L38: =D32 -> 6.16 | M38: =E32 -> 6.11 | N38: =F32 -> 7.49 | O38: =G32 -> 7.92
A39: Regular Dividend Per Share Calc | B39: 0.85 | C39: 0.9 | D39: 0.94 | E39: 0.98 | F39: 1.02 | G39: 1.03 | I39: =A33 -> Basic EPS from Continuing Operations | J39: =B33 -> 5.67 | K39: =C33 -> 6.15 | L39: =D33 -> 6.16 | M39: =E33 -> 6.11 | N39: =F33 -> 7.49 | O39: =G33 -> 7.92
A40: Reported Normalized Diluted EPS | E40: 6.75 | I40: =A34 -> Diluted EPS | J40: =B34 -> 5.61 | K40: =C34 -> 6.11 | L40: =D34 -> 6.13 | M40: =E34 -> 6.08 | N40: =F34 -> 7.46 | O40: =G34 -> 7.91
A41: Basic EPS | B41: 5.67 | C41: 6.15 | D41: 6.16 | E41: 6.11 | F41: 7.49 | G41: 7.93 | I41: =A35 -> Diluted EPS from Continuing Operations | J41: =B35 -> 5.61 | K41: =C35 -> 6.11 | L41: =D35 -> 6.13 | M41: =E35 -> 6.08 | N41: =F35 -> 7.46 | O41: =G35 -> 7.9
A42: Diluted EPS | B42: 5.61 | C42: 6.11 | D42: 6.13 | E42: 6.08 | F42: 7.46 | G42: 7.9 | I42: =A36 -> Basic Weighted Average Shares Outstanding | J42: =B36 -> 16701272000 | K42: =C36 -> 16215963000 | L42: =D36 -> 15744231000 | M42: =E36 -> 15343783000 | N42: =F36 -> 14948500000 | O42: =G36 -> 14865108500
A43: Basic WASO | B43: 16701272000 | C43: 16215963000 | D43: 15744231000 | E43: 15343783000 | F43: 14948500000 | G43: 14865108500 | I43: =A37 -> Diluted Weighted Average Shares Outstanding | J43: =B37 -> 16864919000 | K43: =C37 -> 16325819000 | L43: =D37 -> 15812547000 | M43: =E37 -> 15408095000 | N43: =F37 -> 15004697000 | O43: =G37 -> 14919569750
A44: Diluted WASO | B44: 16864919000 | C44: 16325819000 | D44: 15812547000 | E44: 15408095000 | F44: 15004697000 | G44: 14919569750 | I44: =A38 -> Total Dividend Per Share | J44: =B38 -> 0.85 | K44: =C38 -> 0.9 | L44: =D38 -> 0.94 | M44: =E38 -> 0.98 | N44: =F38 -> 1.02 | O44: =G38 -> 1.03
A45: Fiscal year ends in Sep 30 | USD | I45: =A39 -> Regular Dividend Per Share Calc | J45: =B39 -> 0.85 | K45: =C39 -> 0.9 | L45: =D39 -> 0.94 | M45: =E39 -> 0.98 | N45: =F39 -> 1.02 | O45: =G39 -> 1.03
I46: =A40 -> Reported Normalized Diluted EPS | J46: =B40 | K46: =C40 | L46: =D40 | M46: =E40 -> 6.75 | N46: =F40 | O46: =G40
I47: =A41 -> Basic EPS | J47: =B41 -> 5.67 | K47: =C41 -> 6.15 | L47: =D41 -> 6.16 | M47: =E41 -> 6.11 | N47: =F41 -> 7.49 | O47: =G41 -> 7.93
I48: =A42 -> Diluted EPS | J48: =B42 -> 5.61 | K48: =C42 -> 6.11 | L48: =D42 -> 6.13 | M48: =E42 -> 6.08 | N48: =F42 -> 7.46 | O48: =G42 -> 7.9
I49: =A43 -> Basic WASO | J49: =B43 -> 16701272000 | K49: =C43 -> 16215963000 | L49: =D43 -> 15744231000 | M49: =E43 -> 15343783000 | N49: =F43 -> 14948500000 | O49: =G43 -> 14865108500
I50: =A44 -> Diluted WASO | J50: =B44 -> 16864919000 | K50: =C44 -> 16325819000 | L50: =D44 -> 15812547000 | M50: =E44 -> 15408095000 | N50: =F44 -> 15004697000 | O50: =G44 -> 14919569750
I51: =A45 -> Fiscal year ends in Sep 30 | USD | J51: =B45 -> 0 | K51: =C45 -> 0 | L51: =D45 -> 0 | M51: =E45 -> 0 | N51: =F45 -> 0 | O51: =G45 -> 0

Sheet Income Statement
B1: Income Statement | I1: CHECK | J1: =AND('Raw (Income Statement)'!P7,'Raw (Income Statement)'!P13) -> TRUE
B2: Historical Financial Analysis | All figures in USD ($millions) | Inputs in Blue
B4: USD ($millions) | C4: ="FY"&'Raw (Income Statement)'!B2 -> FY2021 | D4: ="FY"&'Raw (Income Statement)'!C2 -> FY2022 | E4: ="FY"&'Raw (Income Statement)'!D2 -> FY2023 | F4: ="FY"&'Raw (Income Statement)'!E2 -> FY2024 | G4: ="FY"&'Raw (Income Statement)'!F2 -> FY2025 | H4: ="FY"&(MID(G4,3,4)+1) -> FY2026 | I4: ="FY"&(MID(H4,3,4)+1) -> FY2027 | J4: ="FY"&(MID(I4,3,4)+1) -> FY2028 | K4: ="FY"&(MID(J4,3,4)+1) -> FY2029 | L4: ="FY"&(MID(K4,3,4)+1) -> FY2030
B6: REVENUE | H6: ="PROJECTED " & B6 -> PROJECTED REVENUE
B7: Product Revenue | C7: ='Raw (Income Statement)'!J5 -> 297392000000 | D7: ='Raw (Income Statement)'!K5 -> 316199000000 | E7: ='Raw (Income Statement)'!L5 -> 298085000000 | F7: ='Raw (Income Statement)'!M5 -> 294866000000 | G7: ='Raw (Income Statement)'!N5 -> 307003000000 | H7: =G7*(1+'Assumptions & Drivers'!E7) -> 3.1963957e+11 | I7: =H7*(1+'Assumptions & Drivers'!F7) -> 3.3279628e+11 | J7: =I7*(1+'Assumptions & Drivers'!G7) -> 3.4649453e+11 | K7: =J7*(1+'Assumptions & Drivers'!H7) -> 3.6075661e+11 | L7: =K7*(1+'Assumptions & Drivers'!I7) -> 3.7560574e+11
B8: Service Revenue | C8: ='Raw (Income Statement)'!J6 -> 68425000000 | D8: ='Raw (Income Statement)'!K6 -> 78129000000 | E8: ='Raw (Income Statement)'!L6 -> 85200000000 | F8: ='Raw (Income Statement)'!M6 -> 96169000000 | G8: ='Raw (Income Statement)'!N6 -> 109158000000 | H8: =G8*(1+'Assumptions & Drivers'!E8) -> 1.2390135e+11 | I8: =H8*(1+'Assumptions & Drivers'!F8) -> 1.40636e+11 | J8: =I8*(1+'Assumptions & Drivers'!G8) -> 1.5963091e+11 | K8: =J8*(1+'Assumptions & Drivers'!H8) -> 1.8119135e+11 | L8: =K8*(1+'Assumptions & Drivers'!I8) -> 2.0566383e+11
B9: Other Revenue | C9: 0 | D9: 0 | E9: 0 | F9: 0 | G9: 0 | H9: 0 | I9: 0 | J9: 0 | K9: 0 | L9: 0
B10: Total Revenue (Net Sales) | C10: =SUM(C7:C9) -> 365817000000 | D10: =SUM(D7:D9) -> 394328000000 | E10: =SUM(E7:E9) -> 383285000000 | F10: =SUM(F7:F9) -> 391035000000 | G10: =SUM(G7:G9) -> 416161000000 | H10: =SUM(H7:H9) -> 4.4354092e+11 | I10: =SUM(I7:I9) -> 4.7343228e+11 | J10: =SUM(J7:J9) -> 5.0612544e+11 | ... L10: =SUM(L7:L9) -> 5.8126957e+11
B11: Revenue Growth YoY | D11: =D10/C10-1 -> 0.077937876 | E11: =E10/D10-1 -> -0.028004605 | F11: =F10/E10-1 -> 0.020219941 | G11: =G10/F10-1 -> 0.064255118 | H11: =H10/G10-1 -> 0.065791658 | I11: =I10/H10-1 -> 0.067392559 | J11: =J10/I10-1 -> 0.069055612 | K11: =K10/J10-1 -> 0.070777957 | L11: =L10/K10-1 -> 0.072556068
B13: COST OF GOODS SOLD (COGS) | H13: ="PROJECTED " & B13 -> PROJECTED COST OF GOODS SOLD (COGS)
B14: Cost of Products Sold | C14: ='Raw (Income Statement)'!J11 -> 192266000000 | D14: ='Raw (Income Statement)'!K11 -> 201471000000 | E14: ='Raw (Income Statement)'!L11 -> 189282000000 | F14: ='Raw (Income Statement)'!M11 -> 185233000000 | G14: ='Raw (Income Statement)'!N11 -> 194116000000 | H14: =H7*(1-'Assumptions & Drivers'!E11) -> 2.0233185e+11 | I14: =I7*(1-'Assumptions & Drivers'!F11) -> 2.0899606e+11 | J14: =J7*(1-'Assumptions & Drivers'!G11) -> 2.1586609e+11 | K14: =K7*(1-'Assumptions & Drivers'!H11) -> 2.2727667e+11 | L14: =L7*(1-'Assumptions & Drivers'!I11) -> 2.3663162e+11
B15: Cost of Services Sold | C15: ='Raw (Income Statement)'!J12 -> 20715000000 | D15: ='Raw (Income Statement)'!K12 -> 22075000000 | E15: ='Raw (Income Statement)'!L12 -> 24855000000 | F15: ='Raw (Income Statement)'!M12 -> 25119000000 | G15: ='Raw (Income Statement)'!N12 -> 26844000000 | H15: =H8*(1-'Assumptions & Drivers'!E12) -> 3.0108028e+10 | I15: =I8*(1-'Assumptions & Drivers'!F12) -> 3.3471368e+10 | J15: =J8*(1-'Assumptions & Drivers'!G12) -> 3.7194001e+10 | K15: =K8*(1-'Assumptions & Drivers'!H12) -> 4.5297836e+10 | L15: =L8*(1-'Assumptions & Drivers'!I12) -> 5.1415957e+10
B16: Depreciation in COGS | C16: 0 | D16: 0 | E16: 0 | F16: 0 | G16: 0 | H16: 0 | I16: 0 | J16: 0 | K16: 0 | L16: 0
B17: Other COGS | C17: 0 | D17: 0 | E17: 0 | F17: 0 | G17: 0 | H17: 0 | I17: 0 | J17: 0 | K17: 0 | L17: 0
B18: Total COGS | C18: =SUM(C14:C17) -> 212981000000 | D18: =SUM(D14:D17) -> 223546000000 | E18: =SUM(E14:E17) -> 214137000000 | F18: =SUM(F14:F17) -> 210352000000 | G18: =SUM(G14:G17) -> 220960000000 | H18: =SUM(H14:H17) -> 2.3243988e+11 | I18: =SUM(I14:I17) -> 2.4246743e+11 | J18: =SUM(J14:J17) -> 2.5306009e+11 | ... L18: =SUM(L14:L17) -> 2.8804758e+11
B19: COGS YoY | D19: =D18/C18-1 -> 0.049605364 | E19: =E18/D18-1 -> -0.042089771 | F19: =F18/E18-1 -> -0.0176756 | G19: =G18/F18-1 -> 0.050429756 | H19: =H18/G18-1 -> 0.051954549 | I19: =I18/H18-1 -> 0.043140421 | J19: =J18/I18-1 -> 0.043686947 | K19: =K18/J18-1 -> 0.077113742 | L19: =L18/K18-1 -> 0.056766395
B21: GROSS PROFIT | C21: =C10-C18 -> 152836000000 | D21: =D10-D18 -> 170782000000 | E21: =E10-E18 -> 169148000000 | F21: =F10-F18 -> 180683000000 | G21: =G10-G18 -> 195201000000 | H21: =H10-H18 -> 2.1110105e+11 | I21: =I10-I18 -> 2.3096485e+11 | J21: =J10-J18 -> 2.5306534e+11 | ... L21: =L10-L18 -> 2.93222e+11
B22: Gross Margin % | C22: =C21/C10 -> 0.4177936 | D22: =D21/D10 -> 0.43309631 | E22: =E21/E10 -> 0.4413113 | F22: =F21/F10 -> 0.4620635 | G22: =G21/G10 -> 0.46905164 | H22: =H21/H10 -> 0.47594491 | I22: =I21/I10 -> 0.48785192 | J22: =J21/J10 -> 0.50000519 | ... L22: =L21/L10 -> 0.50445097
B24: OPERATING EXPENSES | H24: ="PROJECTED " & B24 -> PROJECTED OPERATING EXPENSES
B25: Research & Development | C25: =ABS('Raw (Income Statement)'!J16) -> 21914000000 | D25: =ABS('Raw (Income Statement)'!K16) -> 26251000000 | E25: =ABS('Raw (Income Statement)'!L16) -> 29915000000 | F25: =ABS('Raw (Income Statement)'!M16) -> 31370000000 | G25: =ABS('Raw (Income Statement)'!N16) -> 34550000000 | H25: =H10*'Assumptions & Drivers'!E13 -> 3.7257437e+10 | I25: =I10*'Assumptions & Drivers'!F13 -> 3.9294879e+10 | J25: =J10*'Assumptions & Drivers'!G13 -> 4.1502286e+10 | K25: =K10*'Assumptions & Drivers'!H13 -> 4.3897785e+10 | L25: =L10*'Assumptions & Drivers'!I13 -> 4.6501566e+10
B26: Sales & Marketing
B27: General & Administrative
B28: SG&A | C28: =ABS('Raw (Income Statement)'!J15) -> 21973000000 | D28: =ABS('Raw (Income Statement)'!K15) -> 25094000000 | E28: =ABS('Raw (Income Statement)'!L15) -> 24932000000 | F28: =ABS('Raw (Income Statement)'!M15) -> 26097000000 | G28: =ABS('Raw (Income Statement)'!N15) -> 27601000000 | H28: =H10*'Assumptions & Drivers'!E14 -> 2.883016e+10 | I28: =I10*'Assumptions & Drivers'!F14 -> 3.0299666e+10 | J28: =J10*'Assumptions & Drivers'!G14 -> 3.1885902e+10 | K28: =K10*'Assumptions & Drivers'!H14 -> 3.3600774e+10 | L28: =L10*'Assumptions & Drivers'!I14 -> 3.5457444e+10
B29: Depreciation & Amortization (ex. COGS) | C29: 0 | D29: 0 | E29: 0 | F29: 0 | G29: 0 | H29: 0 | I29: 0 | J29: 0 | K29: 0 | L29: 0
B30: Restructuring & Other Charges | C30: 0 | D30: 0 | E30: 0 | F30: 0 | G30: 0 | H30: 0 | I30: 0 | J30: 0 | K30: 0 | L30: 0
B31: Other Operating Expenses / (Income) | C31: 0 | D31: 0 | E31: 0 | F31: 0 | G31: 0 | H31: 0 | I31: 0 | J31: 0 | K31: 0 | L31: 0
B32: Total Operating Expenses | C32: =SUM(C25:C31) -> 43887000000 | D32: =SUM(D25:D31) -> 51345000000 | E32: =SUM(E25:E31) -> 54847000000 | F32: =SUM(F25:F31) -> 57467000000 | G32: =SUM(G25:G31) -> 62151000000 | H32: =SUM(H25:H31) -> 6.6087597e+10 | I32: =SUM(I25:I31) -> 6.9594545e+10 | J32: =SUM(J25:J31) -> 7.3388188e+10 | ... L32: =SUM(L25:L31) -> 8.195901e+10
B34: OPERATING INCOME (EBIT) | C34: =C21-C32 -> 108949000000 | D34: =D21-D32 -> 119437000000 | E34: =E21-E32 -> 114301000000 | F34: =F21-F32 -> 123216000000 | G34: =G21-G32 -> 133050000000 | H34: =H21-H32 -> 1.4501345e+11 | I34: =I21-I32 -> 1.613703e+11 | J34: =J21-J32 -> 1.7967715e+11 | ... L34: =L21-L32 -> 2.1126299e+11
B35: Operating Margin (EBIT) % | C35: =C34/C10 -> 0.29782378 | D35: =D34/D10 -> 0.30288744 | E35: =E34/E10 -> 0.29821412 | F35: =F34/F10 -> 0.31510223 | G35: =G34/G10 -> 0.319708 | H35: =H34/H10 -> 0.32694491 | I35: =I34/I10 -> 0.34085192 | J35: =J34/J10 -> 0.35500519 | ... L35: =L34/L10 -> 0.36345097
B37: NON-OPERATING ITEMS | H37: ="PROJECTED " & B37 -> PROJECTED NON-OPERATING ITEMS
B38: Interest Expense | C38: ='Raw (Income Statement)'!J22 -> -2645000000 | D38: ='Raw (Income Statement)'!K22 -> -2931000000 | E38: ='Raw (Income Statement)'!L22 -> -3933000000 | F38: ='Raw (Income Statement)'!M22 | G38: ='Raw (Income Statement)'!N22 | H38: =-78328*'Assumptions & Drivers'!E292 -> 0 | I38: =-78328*'Assumptions & Drivers'!F292 -> 0 | J38: =-78328*'Assumptions & Drivers'!G292 -> 0 | K38: =-78328*'Assumptions & Drivers'!H292 -> 0 | L38: =-78328*'Assumptions & Drivers'!I292 -> 0
B39: Interest Income | C39: ='Raw (Income Statement)'!J23 -> 2843000000 | D39: ='Raw (Income Statement)'!K23 -> 2825000000 | E39: ='Raw (Income Statement)'!L23 -> 3750000000 | F39: ='Raw (Income Statement)'!M23 | G39: ='Raw (Income Statement)'!N23 | H39: =-78328*'Assumptions & Drivers'!E293 -> 0 | I39: =-78328*'Assumptions & Drivers'!F293 -> 0 | J39: =-78328*'Assumptions & Drivers'!G293 -> 0 | K39: =-78328*'Assumptions & Drivers'!H293 -> 0 | L39: =-78328*'Assumptions & Drivers'!I293 -> 0
B40: Gain / (Loss) on Investments | C40: 0 | D40: 0 | E40: 0 | F40: 0 | G40: 0 | H40: 0 | I40: 0 | J40: 0 | K40: 0 | L40: 0
B41: Other Non-Operating Income / (Expense) | C41: ='Raw (Income Statement)'!J19 -> 60000000 | D41: ='Raw (Income Statement)'!K19 -> -228000000 | E41: ='Raw (Income Statement)'!L19 -> -382000000 | F41: ='Raw (Income Statement)'!M19 -> 269000000 | G41: ='Raw (Income Statement)'!N19 -> -321000000 | H41: 0 | I41: 0 | J41: 0 | K41: 0 | L41: 0
B42: Total Non-Operating Items | C42: =SUM(C38:C41) -> 258000000 | D42: =SUM(D38:D41) -> -334000000 | E42: =SUM(E38:E41) -> -565000000 | F42: =SUM(F38:F41) -> 269000000 | G42: =SUM(G38:G41) -> -321000000 | H42: =SUM(H38:H41) -> 0 | I42: =SUM(I38:I41) -> 0 | J42: =SUM(J38:J41) -> 0 | ... L42: =SUM(L38:L41) -> 0
B44: INCOME BEFORE TAXES (EBT) | C44: =C34+C42 -> 109207000000 | D44: =D34+D42 -> 119103000000 | E44: =E34+E42 -> 113736000000 | F44: =F34+F42 -> 123485000000 | G44: =G34+G42 -> 132729000000 | H44: =H34+H42 -> 1.4501345e+11 | I44: =I34+I42 -> 1.613703e+11 | J44: =J34+J42 -> 1.7967715e+11 | ... L44: =L34+L42 -> 2.1126299e+11
B46: INCOME TAXES | H46: ="PROJECTED " & B46 -> PROJECTED INCOME TAXES
B47: Income Tax Expense / (Benefit) | C47: =ABS('Raw (Income Statement)'!J25) -> 14527000000 | D47: =ABS('Raw (Income Statement)'!K25) -> 19300000000 | E47: =ABS('Raw (Income Statement)'!L25) -> 16741000000 | F47: =ABS('Raw (Income Statement)'!M25) -> 29749000000 | G47: =ABS('Raw (Income Statement)'!N25) -> 20719000000 | H47: =H44*'Assumptions & Drivers'!E27 -> 3.0452824e+10 | I47: =I44*'Assumptions & Drivers'!F27 -> 3.3887764e+10 | J47: =J44*'Assumptions & Drivers'!G27 -> 3.7732202e+10 | K47: =K44*'Assumptions & Drivers'!H27 -> 4.0293729e+10 | L47: =L44*'Assumptions & Drivers'!I27 -> 4.4365227e+10
B49: NET INCOME | C49: =C44-C47 -> 94680000000 | D49: =D44-D47 -> 99803000000 | E49: =E44-E47 -> 96995000000 | F49: =F44-F47 -> 93736000000 | G49: =G44-G47 -> 112010000000 | H49: =H44-H47 -> 1.1456062e+11 | I49: =I44-I47 -> 1.2748254e+11 | J49: =J44-J47 -> 1.4194495e+11 | ... L49: =L44-L47 -> 1.6689776e+11
B50: Net Profit Margin % | C50: =C49/C10 -> 0.25881793 | D50: =D49/D10 -> 0.25309641 | E50: =E49/E10 -> 0.25306234 | F50: =F49/F10 -> 0.23971256 | G50: =G49/G10 -> 0.26915064 | H50: =H49/H10 -> 0.25828648 | I50: =I49/I10 -> 0.26927302 | J50: =J49/J10 -> 0.2804541 | ... L50: =L49/L10 -> 0.28712626
B52: SUPPLEMENTAL DATA | H52: ="PROJECTED " & B52 -> PROJECTED SUPPLEMENTAL DATA
B53: Weighted Avg. Diluted Shares Outstanding | C53: ='Raw (Income Statement)'!J43 -> 16864919000 | D53: ='Raw (Income Statement)'!K43 -> 16325819000 | E53: ='Raw (Income Statement)'!L43 -> 15812547000 | F53: ='Raw (Income Statement)'!M43 -> 15408095000 | G53: ='Raw (Income Statement)'!N43 -> 15004697000 | H53: =G53-'Assumptions & Drivers'!E49+'Assumptions & Drivers'!E50 -> 14554697000 | I53: =H53-'Assumptions & Drivers'!F49+'Assumptions & Drivers'!F50 -> 14149697000 | J53: =I53-'Assumptions & Drivers'!G49+'Assumptions & Drivers'!G50 -> 13779697000 | K53: =J53-'Assumptions & Drivers'!H49+'Assumptions & Drivers'!H50 -> 13444697000 | L53: =K53-'Assumptions & Drivers'!I49+'Assumptions & Drivers'!I50 -> 13134697000
B54: Diluted EPS | C54: =IFERROR(C49/C53,"-") -> 5.6140204 | D54: =IFERROR(D49/D53,"-") -> 6.1132002 | E54: =IFERROR(E49/E53,"-") -> 6.1340529 | F54: =IFERROR(F49/F53,"-") -> 6.0835554 | G54: =IFERROR(G49/G53,"-") -> 7.4649958 | H54: =IFERROR(H49/H53,"-") -> 7.8710415 | I54: =IFERROR(I49/I53,"-") -> 9.0095597 | J54: =IFERROR(J49/J53,"-") -> 10.301021 | ... L54: =IFERROR(L49/L53,"-") -> 12.706632
B55: D&A (total, for EBITDA bridge) | C55: =C29 -> 0 | D55: =D29 -> 0 | E55: =E29 -> 0 | F55: =F29 -> 0 | G55: =G29 -> 0 | H55: =H10*'Assumptions & Drivers'!E17 -> 1.2419146e+10 | I55: =I10*'Assumptions & Drivers'!F17 -> 1.3256104e+10 | J55: =J10*'Assumptions & Drivers'!G17 -> 1.3665387e+10 | K55: =K10*'Assumptions & Drivers'!H17 -> 1.4632595e+10 | L55: =L10*'Assumptions & Drivers'!I17 -> 1.5694278e+10
B56: EBITDA | C56: =C34+C55 -> 108949000000 | D56: =D34+D55 -> 119437000000 | E56: =E34+E55 -> 114301000000 | F56: =F34+F55 -> 123216000000 | G56: =G34+G55 -> 133050000000 | H56: =H34+H55 -> 1.5743259e+11 | I56: =I34+I55 -> 1.7462641e+11 | J56: =J34+J55 -> 1.9334254e+11 | ... L56: =L34+L55 -> 2.2695727e+11
B57: EBITDA Margin % | C57: =C56/C10 -> 0.29782378 | D57: =D56/D10 -> 0.30288744 | E57: =E56/E10 -> 0.29821412 | F57: =F56/F10 -> 0.31510223 | G57: =G56/G10 -> 0.319708 | H57: =H56/H10 -> 0.35494491 | I57: =I56/I10 -> 0.36885192 | J57: =J56/J10 -> 0.38200519 | ... L57: =L56/L10 -> 0.39045097
B59: Total Comprehensive Income | C59: 95249000000 | D59: 88531000000 | E59: 96652000000 | F59: 98016000000 | G59: 113611000000
B60: Fluctuation Check | C60: =ABS(C59-C49)/MIN(C49,C59)<0.05 -> TRUE | D60: =ABS(D59-D49)/MIN(D49,D59)<0.05 -> FALSE | E60: =ABS(E59-E49)/MIN(E49,E59)<0.05 -> TRUE | F60: =ABS(F59-F49)/MIN(F49,F59)<0.05 -> TRUE | G60: =ABS(G59-G49)/MIN(G49,G59)<0.05 -> TRUE
G61: =AND(C60:G60) -> FALSE

Sheet Cash Flow Statement
B1: Cash Flow Statement | I1: CHECK | J1: =AND('Raw (CF Statement)'!P33,'Raw (CF Statement)'!P55) -> TRUE
B2: Historical Financial Analysis | All figures in USD ($millions) | Inputs in Blue
B4: USD ($millions) | C4: FY2021 | D4: FY2022 | E4: FY2023 | F4: FY2024 | G4: FY2025 | H4: ="FY"&(MID(G4,3,4)+1) -> FY2026 | I4: ="FY"&(MID(H4,3,4)+1) -> FY2027 | J4: ="FY"&(MID(I4,3,4)+1) -> FY2028 | K4: ="FY"&(MID(J4,3,4)+1) -> FY2029 | L4: ="FY"&(MID(K4,3,4)+1) -> FY2030
B6: OPERATING ACTIVITIES | H6: ="PROJECTED " & B6 -> PROJECTED OPERATING ACTIVITIES
B7: Net Income | C7: ='Raw (CF Statement)'!J6 -> 94680000000 | D7: ='Raw (CF Statement)'!K6 -> 99803000000 | E7: ='Raw (CF Statement)'!L6 -> 96995000000 | F7: ='Raw (CF Statement)'!M6 -> 93736000000 | G7: ='Raw (CF Statement)'!N6 -> 112010000000 | H7: ='Income Statement'!H49 -> 1.1456062e+11 | I7: ='Income Statement'!I49 -> 1.2748254e+11 | J7: ='Income Statement'!J49 -> 1.4194495e+11 | K7: ='Income Statement'!K49 -> 1.5158117e+11 | L7: ='Income Statement'!L49 -> 1.6689776e+11
B8: Non-Cash Adjustments:
B9: Depreciation & Amortization | C9: ='Raw (CF Statement)'!J9 -> 11284000000 | D9: ='Raw (CF Statement)'!K9 -> 11104000000 | E9: ='Raw (CF Statement)'!L9 -> 11519000000 | F9: ='Raw (CF Statement)'!M9 -> 11445000000 | G9: ='Raw (CF Statement)'!N9 -> 11698000000 | H9: ='Income Statement'!H55 -> 1.2419146e+10 | I9: ='Income Statement'!I55 -> 1.3256104e+10 | J9: ='Income Statement'!J55 -> 1.3665387e+10 | K9: ='Income Statement'!K55 -> 1.4632595e+10 | L9: ='Income Statement'!L55 -> 1.5694278e+10
B10: Stock-Based Compensation | C10: ='Raw (CF Statement)'!J10 -> 7906000000 | D10: ='Raw (CF Statement)'!K10 -> 9038000000 | E10: ='Raw (CF Statement)'!L10 -> 10833000000 | F10: ='Raw (CF Statement)'!M10 -> 11688000000 | G10: ='Raw (CF Statement)'!N10 -> 12863000000 | H10: ='Income Statement'!H10*'Assumptions & Drivers'!E19 -> 1.3749769e+10 | I10: ='Income Statement'!I10*'Assumptions & Drivers'!F19 -> 1.4676401e+10 | J10: ='Income Statement'!J10*'Assumptions & Drivers'!G19 -> 1.5183763e+10 | K10: ='Income Statement'!K10*'Assumptions & Drivers'!H19 -> 1.6258439e+10 | L10: ='Income Statement'!L10*'Assumptions & Drivers'!I19 -> 1.6856818e+10
B11: Deferred Income Taxes | C11: ='Raw (CF Statement)'!J12 -> -4774000000 | D11: ='Raw (CF Statement)'!K12 -> 895000000 | E11: ='Raw (CF Statement)'!L12 | F11: ='Raw (CF Statement)'!M12 | G11: ='Raw (CF Statement)'!N12 | H11: 0 | I11: 0 | J11: 0 | K11: 0 | L11: 0
B12: Impairment Charges | C12: 0 | D12: 0 | E12: 0 | F12: 0 | G12: 0 | H12: 0 | I12: 0 | J12: 0 | K12: 0 | L12: 0
B13: Other Non-Cash Items | C13: ='Raw (CF Statement)'!J11 -> -147000000 | D13: ='Raw (CF Statement)'!K11 -> 111000000 | E13: ='Raw (CF Statement)'!L11 -> -2227000000 | F13: ='Raw (CF Statement)'!M11 -> -2266000000 | G13: ='Raw (CF Statement)'!N11 -> -89000000 | H13: 0 | I13: 0 | J13: 0 | K13: 0 | L13: 0
B14: Changes in Working Capital:
B15: (Increase) / Decrease in Accounts Receivable & Non-Trade Receivables | C15: ='Raw (CF Statement)'!J15 -> -14028000000 | D15: ='Raw (CF Statement)'!K15 -> -9343000000 | E15: ='Raw (CF Statement)'!L15 -> -417000000 | F15: ='Raw (CF Statement)'!M15 -> -5144000000 | G15: ='Raw (CF Statement)'!N15 -> -7029000000 | H15: =-('Balance Sheet'!H10+'Balance Sheet'!H11-'Balance Sheet'!G10-'Balance Sheet'!G11) -> -4340846726 | I15: =-('Balance Sheet'!I10+'Balance Sheet'!I11-'Balance Sheet'!H10-'Balance Sheet'!H11) -> -4362806639 | J15: =-('Balance Sheet'!J10+'Balance Sheet'!J11-'Balance Sheet'!I10-'Balance Sheet'!I11) -> -4715462965 | K15: =-('Balance Sheet'!K10+'Balance Sheet'!K11-'Balance Sheet'!J10-'Balance Sheet'!J11) -> -6354286417 | L15: =-('Balance Sheet'!L10+'Balance Sheet'!L11-'Balance Sheet'!K10-'Balance Sheet'!K11) -> -6081872842
B16: (Increase) / Decrease in Inventories | C16: ='Raw (CF Statement)'!J14 -> -2642000000 | D16: ='Raw (CF Statement)'!K14 -> 1484000000 | E16: ='Raw (CF Statement)'!L14 -> -1618000000 | F16: ='Raw (CF Statement)'!M14 -> -1046000000 | G16: ='Raw (CF Statement)'!N14 -> 1400000000 | H16: =-('Balance Sheet'!H12-'Balance Sheet'!G12) -> -297076111 | I16: =-('Balance Sheet'!I12-'Balance Sheet'!H12) -> -259492915 | J16: =-('Balance Sheet'!J12-'Balance Sheet'!I12) -> -274116763 | K16: =-('Balance Sheet'!K12-'Balance Sheet'!J12) -> -504993665 | L16: =-('Balance Sheet'!L12-'Balance Sheet'!K12) -> -400411954
B17: (Increase) / Decrease in Prepaid & Other | C17: ='Raw (CF Statement)'!J18 -> -8042000000 | D17: ='Raw (CF Statement)'!K18 -> -6499000000 | E17: ='Raw (CF Statement)'!L18 -> -5684000000 | F17: ='Raw (CF Statement)'!M18 -> -11731000000 | G17: ='Raw (CF Statement)'!N18 -> -9197000000 | H17: =-('Balance Sheet'!H13-'Balance Sheet'!G13) -> -959571335 | I17: =-('Balance Sheet'!I13-'Balance Sheet'!H13) -> -1047588435 | J17: =-('Balance Sheet'!J13-'Balance Sheet'!I13) -> -1145781748 | K17: =-('Balance Sheet'!K13-'Balance Sheet'!J13) -> -1255455262 | L17: =-('Balance Sheet'!L13-'Balance Sheet'!K13) -> -1378086183
B18: Increase / (Decrease) in Accounts Payable | C18: ='Raw (CF Statement)'!J19 -> 12326000000 | D18: ='Raw (CF Statement)'!K19 -> 9448000000 | E18: ='Raw (CF Statement)'!L19 -> -1889000000 | F18: ='Raw (CF Statement)'!M19 -> 6020000000 | G18: ='Raw (CF Statement)'!N19 -> 902000000 | H18: ='Balance Sheet'!H31-'Balance Sheet'!G31 -> 3629544796 | I18: ='Balance Sheet'!I31-'Balance Sheet'!H31 -> 3170369889 | J18: ='Balance Sheet'!J31-'Balance Sheet'!I31 -> 3349037606 | K18: ='Balance Sheet'!K31-'Balance Sheet'!J31 -> 6169789693 | L18: ='Balance Sheet'!L31-'Balance Sheet'!K31 -> 4892056508
B19: Increase / (Decrease) in Accrued Liabilities | C19: ='Raw (CF Statement)'!J22 -> 5799000000 | D19: ='Raw (CF Statement)'!K22 -> 5632000000 | E19: ='Raw (CF Statement)'!L22 -> 3031000000 | F19: ='Raw (CF Statement)'!M22 -> 15552000000 | G19: ='Raw (CF Statement)'!N22 -> -11076000000 | H19: ='Balance Sheet'!H35-'Balance Sheet'!G35 -> 4367710814 | I19: ='Balance Sheet'!I35-'Balance Sheet'!H35 -> 4768340995 | J19: ='Balance Sheet'!J35-'Balance Sheet'!I35 -> 5215290568 | K19: ='Balance Sheet'!K35-'Balance Sheet'!J35 -> 5714494925 | L19: ='Balance Sheet'!L35-'Balance Sheet'!K35 -> 6272677920
B20: Increase / (Decrease) in Deferred Revenue | C20: ='Raw (CF Statement)'!J23 -> 1676000000 | D20: ='Raw (CF Statement)'!K23 -> 478000000 | E20: ='Raw (CF Statement)'!L23 | F20: ='Raw (CF Statement)'!M23 | G20: ='Raw (CF Statement)'!N23 | H20: ='Balance Sheet'!H34-'Balance Sheet'!G34 -> 1223007362 | I20: ='Balance Sheet'!I34-'Balance Sheet'!H34 -> 1388192012 | J20: ='Balance Sheet'!J34-'Balance Sheet'!I34 -> 1575687214 | K20: ='Balance Sheet'!K34-'Balance Sheet'!J34 -> 1788506326 | L20: ='Balance Sheet'!L34-'Balance Sheet'!K34 -> 2030069706
B21: Other Changes in Working Capital | C21: 0 | D21: 0 | E21: 0 | F21: 0 | G21: 0 | H21: 0 | I21: 0 | J21: 0 | K21: 0 | L21: 0
B22: Net Cash from Operating Activities (CFO) | C22: =SUM(C7:C21) -> 104038000000 | D22: =SUM(D7:D21) -> 122151000000 | E22: =SUM(E7:E21) -> 110543000000 | F22: =SUM(F7:F21) -> 118254000000 | G22: =SUM(G7:G21) -> 111482000000 | H22: =SUM(H7:H21) -> 1.4435231e+11 | I22: =SUM(I7:I21) -> 1.5907206e+11 | J22: =SUM(J7:J21) -> 1.7479876e+11 | ... L22: =SUM(L7:L21) -> 2.0478329e+11
B24: INVESTING ACTIVITIES | H24: ="PROJECTED " & B24 -> PROJECTED INVESTING ACTIVITIES
B25: Capital Expenditures (CapEx) | C25: ='Raw (CF Statement)'!J27 -> -11085000000 | D25: ='Raw (CF Statement)'!K27 -> -10708000000 | E25: ='Raw (CF Statement)'!L27 -> -10959000000 | F25: ='Raw (CF Statement)'!M27 -> -9447000000 | G25: ='Raw (CF Statement)'!N27 -> -12715000000 | H25: =-'Income Statement'!H10*'Assumptions & Drivers'!E18 -> -1.3749769e+10 | I25: =-'Income Statement'!I10*'Assumptions & Drivers'!F18 -> -1.4202968e+10 | J25: =-'Income Statement'!J10*'Assumptions & Drivers'!G18 -> -1.4677638e+10 | K25: =-'Income Statement'!K10*'Assumptions & Drivers'!H18 -> -1.5716491e+10 | L25: =-'Income Statement'!L10*'Assumptions & Drivers'!I18 -> -1.6275548e+10
B26: Purchases of Short-Term Investments | C26: ='Raw (CF Statement)'!J29 -> -109689000000 | D26: ='Raw (CF Statement)'!K29 -> -76923000000 | E26: ='Raw (CF Statement)'!L29 -> -29513000000 | F26: ='Raw (CF Statement)'!M29 -> -48656000000 | G26: ='Raw (CF Statement)'!N29 -> -24407000000 | H26: 0 | I26: 0 | J26: 0 | K26: 0 | L26: 0
B27: Maturities of Short-Term Investments | C27: ='Raw (CF Statement)'!J31 -> 59023000000 | D27: ='Raw (CF Statement)'!K31 -> 29917000000 | E27: ='Raw (CF Statement)'!L31 -> 39686000000 | F27: ='Raw (CF Statement)'!M31 -> 51211000000 | G27: ='Raw (CF Statement)'!N31 -> 40907000000 | H27: ='Balance Sheet'!G9-'Balance Sheet'!H9 -> 0 | I27: ='Balance Sheet'!H9-'Balance Sheet'!I9 -> 0 | J27: ='Balance Sheet'!I9-'Balance Sheet'!J9 -> 0 | K27: ='Balance Sheet'!J9-'Balance Sheet'!K9 -> 0 | L27: ='Balance Sheet'!K9-'Balance Sheet'!L9 -> 0
B28: Proceeds from Sale of Investments | C28: ='Raw (CF Statement)'!J32 -> 47847000000 | D28: ='Raw (CF Statement)'!K32 -> 37446000000 | E28: ='Raw (CF Statement)'!L32 -> 5828000000 | F28: ='Raw (CF Statement)'!M32 -> 11135000000 | G28: ='Raw (CF Statement)'!N32 -> 12890000000 | H28: 0 | I28: 0 | J28: 0 | K28: 0 | L28: 0
B29: Acquisitions, net of Cash Acquired | C29: ='Raw (CF Statement)'!J36 -> -33000000 | D29: ='Raw (CF Statement)'!K36 -> -306000000 | E29: ='Raw (CF Statement)'!L36 | F29: ='Raw (CF Statement)'!M36 | G29: ='Raw (CF Statement)'!N36 | H29: 0 | I29: 0 | J29: 0 | K29: 0 | L29: 0
B30: Proceeds from Divestitures | C30: 0 | D30: 0 | E30: 0 | F30: 0 | G30: 0 | H30: 0 | I30: 0 | J30: 0 | K30: 0 | L30: 0
B31: Other Investing Activities | C31: ='Raw (CF Statement)'!J34 -> -608000000 | D31: ='Raw (CF Statement)'!K34 -> -1780000000 | E31: ='Raw (CF Statement)'!L34 -> -1337000000 | F31: ='Raw (CF Statement)'!M34 -> -1308000000 | G31: ='Raw (CF Statement)'!N34 -> -1480000000 | H31: ='Balance Sheet'!G24-'Balance Sheet'!H24 -> 0 | I31: ='Balance Sheet'!H24-'Balance Sheet'!I24 -> 0 | J31: ='Balance Sheet'!I24-'Balance Sheet'!J24 -> 0 | K31: ='Balance Sheet'!J24-'Balance Sheet'!K24 -> 0 | L31: ='Balance Sheet'!K24-'Balance Sheet'!L24 -> 0
B32: Net Cash from Investing Activities (CFI) | C32: =SUM(C25:C31) -> -14545000000 | D32: =SUM(D25:D31) -> -22354000000 | E32: =SUM(E25:E31) -> 3705000000 | F32: =SUM(F25:F31) -> 2935000000 | G32: =SUM(G25:G31) -> 15195000000 | H32: =SUM(H25:H31) -> -1.3749769e+10 | I32: =SUM(I25:I31) -> -1.4202968e+10 | J32: =SUM(J25:J31) -> -1.4677638e+10 | ... L32: =SUM(L25:L31) -> -1.6275548e+10
B34: FINANCING ACTIVITIES | H34: ="PROJECTED " & B34 -> PROJECTED FINANCING ACTIVITIES
B35: Taxes related to net share settlement of equity awards | C35: =-'Raw (CF Statement)'!J53 -> -6685000000 | D35: =-'Raw (CF Statement)'!K53 -> -6223000000 | E35: =-'Raw (CF Statement)'!L53 -> -5431000000 | F35: =-'Raw (CF Statement)'!M53 -> -5441000000 | G35: =-'Raw (CF Statement)'!N53 -> -5960000000 | H35: 0 | I35: 0 | J35: 0 | K35: 0 | L35: 0
B36: Proceeds from Issuance of Short-Term Debt | C36: ='Raw (CF Statement)'!J45 -> 1022000000 | D36: ='Raw (CF Statement)'!K45 -> 3955000000 | E36: ='Raw (CF Statement)'!L45 -> -3978000000 | F36: ='Raw (CF Statement)'!M45 -> 3960000000 | G36: ='Raw (CF Statement)'!N45 -> -2032000000 | H36: 0 | I36: 0 | J36: 0 | K36: 0 | L36: 0
B37: Proceeds from Issuance of Long-Term Debt | C37: ='Raw (CF Statement)'!J47 -> 20393000000 | D37: ='Raw (CF Statement)'!K47 -> 5465000000 | E37: ='Raw (CF Statement)'!L47 -> 5228000000 | F37: ='Raw (CF Statement)'!M47 -> 0 | G37: ='Raw (CF Statement)'!N47 -> 4481000000 | H37: 0 | I37: 0 | J37: 0 | K37: 0 | L37: 0
B38: Repayment of Long-Term Debt | C38: ='Raw (CF Statement)'!J48 -> -8750000000 | D38: ='Raw (CF Statement)'!K48 -> -9543000000 | E38: ='Raw (CF Statement)'!L48 -> -11151000000 | F38: ='Raw (CF Statement)'!M48 -> -9958000000 | G38: ='Raw (CF Statement)'!N48 -> -10932000000 | H38: 0 | I38: 0 | J38: 0 | K38: 0 | L38: 0
B39: Proceeds from Equity Issuance | C39: 0 | D39: 0 | E39: 0 | F39: 0 | G39: 0 | H39: 0 | I39: 0 | J39: 0 | K39: 0 | L39: 0
B40: Share Repurchases / Buybacks | C40: ='Raw (CF Statement)'!J41 -> -84866000000 | D40: ='Raw (CF Statement)'!K41 -> -89402000000 | E40: ='Raw (CF Statement)'!L41 -> -77550000000 | F40: ='Raw (CF Statement)'!M41 -> -94949000000 | G40: ='Raw (CF Statement)'!N41 -> -90711000000 | H40: =-'Assumptions & Drivers'!E32*1000000 -> -90000000000 | I40: =-'Assumptions & Drivers'!F32*1000000 -> -85000000000 | J40: =-'Assumptions & Drivers'!G32*1000000 -> -80000000000 | K40: =-'Assumptions & Drivers'!H32*1000000 -> -75000000000 | L40: =-'Assumptions & Drivers'!I32*1000000 -> -70000000000
B41: Dividends Paid | C41: ='Raw (CF Statement)'!J49 -> -14467000000 | D41: ='Raw (CF Statement)'!K49 -> -14841000000 | E41: ='Raw (CF Statement)'!L49 -> -15025000000 | F41: ='Raw (CF Statement)'!M49 -> -15234000000 | G41: ='Raw (CF Statement)'!N49 -> -15421000000 | H41: =-'Assumptions & Drivers'!E33*'Income Statement'!H53 -> -1.568625e+10 | I41: =-'Assumptions & Drivers'!F33*'Income Statement'!I53 -> -1.5957248e+10 | J41: =-'Assumptions & Drivers'!G33*'Income Statement'!J53 -> -1.6228967e+10 | K41: =-'Assumptions & Drivers'!H33*'Income Statement'!K53 -> -1.6506657e+10 | L41: =-'Assumptions & Drivers'!I33*'Income Statement'!L53 -> -1.6782791e+10
B42: Other Financing Activities | C42: =-'Raw (CF Statement)'!J54 -> 0 | D42: =-'Raw (CF Statement)'!K54 -> -160000000 | E42: =-'Raw (CF Statement)'!L54 -> -581000000 | F42: =-'Raw (CF Statement)'!M54 -> -361000000 | G42: =-'Raw (CF Statement)'!N54 -> -111000000 | H42: 0 | I42: 0 | J42: 0 | K42: 0 | L42: 0
B43: Net Cash from Financing Activities (CFF) | C43: =SUM(C35:C42) -> -93353000000 | D43: =SUM(D35:D42) -> -110749000000 | E43: =SUM(E35:E42) -> -108488000000 | F43: =SUM(F35:F42) -> -121983000000 | G43: =SUM(G35:G42) -> -120686000000 | H43: =SUM(H35:H42) -> -1.0568625e+11 | I43: =SUM(I35:I42) -> -1.0095725e+11 | J43: =SUM(J35:J42) -> -9.6228967e+10 | ... L43: =SUM(L35:L42) -> -8.6782791e+10
B45: CASH RECONCILIATION | H45: ="PROJECTED " & B45 -> PROJECTED CASH RECONCILIATION
B46: Beginning Cash & Cash Equivalents | C46: ='Raw (CF Statement)'!J59 -> 39789000000 | D46: ='Raw (CF Statement)'!K59 -> 35929000000 | E46: ='Raw (CF Statement)'!L59 -> 24977000000 | F46: ='Raw (CF Statement)'!M59 -> 30737000000 | G46: ='Raw (CF Statement)'!N59 -> 29943000000 | H46: =G49 -> 35934000000 | I46: =H49 -> 6.0850289e+10 | J46: =I49 -> 1.0476213e+11 | K46: =J49 -> 1.6865428e+11 | L46: =K49 -> 2.4946139e+11
B47: Effect of Exchange Rate Changes | C47: 0 | D47: 0 | E47: 0 | F47: 0 | G47: 0 | H47: 0 | I47: 0 | J47: 0 | K47: 0 | L47: 0
B48: Net Change in Cash | C48: =C22+C32+C43 -> -3860000000 | D48: =D22+D32+D43 -> -10952000000 | E48: =E22+E32+E43 -> 5760000000 | F48: =F22+F32+F43 -> -794000000 | G48: =G22+G32+G43 -> 5991000000 | H48: =H22+H32+H43 -> 2.4916289e+10 | I48: =I22+I32+I43 -> 4.3911843e+10 | J48: =J22+J32+J43 -> 6.3892151e+10 | ... L48: =L22+L32+L43 -> 1.0172495e+11
B49: Ending Cash & Cash Equivalents | C49: =C46+C48+C47 -> 35929000000 | D49: =D46+D48+D47 -> 24977000000 | E49: =E46+E48+E47 -> 30737000000 | F49: =F46+F48+F47 -> 29943000000 | G49: =G46+G48+G47 -> 35934000000 | H49: =H46+H48+H47 -> 6.0850289e+10 | I49: =I46+I48+I47 -> 1.0476213e+11 | J49: =J46+J48+J47 -> 1.6865428e+11 | ... L49: =L46+L48+L47 -> 3.5118634e+11
B51: FREE CASH FLOW | H51: ="PROJECTED " & B51 -> PROJECTED FREE CASH FLOW
B52: Capital Expenditures (CapEx) [re-enter from above] | C52: =C25 -> -11085000000 | D52: =D25 -> -10708000000 | E52: =E25 -> -10959000000 | F52: =F25 -> -9447000000 | G52: =G25 -> -12715000000 | H52: =H25 -> -1.3749769e+10 | I52: =I25 -> -1.4202968e+10 | J52: =J25 -> -1.4677638e+10 | ... L52: =L25 -> -1.6275548e+10
B53: Free Cash Flow (FCF) | C53: =C22+C52 -> 92953000000 | D53: =D22+D52 -> 111443000000 | E53: =E22+E52 -> 99584000000 | F53: =F22+F52 -> 108807000000 | G53: =G22+G52 -> 98767000000 | H53: =H22+H52 -> 1.3060254e+11 | I53: =I22+I52 -> 1.4486909e+11 | J53: =J22+J52 -> 1.6012112e+11 | ... L53: =L22+L52 -> 1.8850774e+11

Sheet Raw (CF Statement)
A1: RAW | I1: ADJUSTED
A2: AAPL_cash-flow_Annual_As_Originally_Reported | B2: 2021 | C2: 2022 | D2: 2023 | E2: 2024 | F2: 2025 | G2: TTM | I2: =A2 -> AAPL_cash-flow_Annual_As_Originally_Reported | J2: =B2 -> 2021 | K2: =C2 -> 2022 | L2: =D2 -> 2023 | M2: =E2 -> 2024 | N2: =F2 -> 2025 | O2: =G2 -> TTM
A3: Cash Flow from Operating Activities, Indirect | B3: 104038000000 | C3: 122151000000 | D3: 110543000000 | E3: 118254000000 | F3: 111482000000 | G3: 135472000000 | I3: =A3 -> Cash Flow from Operating Activities, Indirect | J3: =B3 -> 104038000000 | K3: =C3 -> 122151000000 | L3: =D3 -> 110543000000 | M3: =E3 -> 118254000000 | N3: =F3 -> 111482000000 | O3: =G3 -> 135472000000
A4: Net Cash Flow from Continuing Operating Activities, Indirect | B4: 104038000000 | C4: 122151000000 | D4: 110543000000 | E4: 118254000000 | F4: 111482000000 | G4: 135472000000 | I4: =A4 -> Net Cash Flow from Continuing Operating Activities, Indirect | J4: =B4 -> 104038000000 | K4: =C4 -> 122151000000 | L4: =D4 -> 110543000000 | M4: =E4 -> 118254000000 | N4: =F4 -> 111482000000 | O4: =G4 -> 135472000000
A5: Cash Generated from Operating Activities | B5: 104038000000 | C5: 122151000000 | D5: 110543000000 | E5: 118254000000 | F5: 111482000000 | G5: 135472000000 | I5: =A5 -> Cash Generated from Operating Activities | J5: =B5 -> 104038000000 | K5: =C5 -> 122151000000 | L5: =D5 -> 110543000000 | M5: =E5 -> 118254000000 | N5: =F5 -> 111482000000 | O5: =G5 -> 135472000000
A6: Income/Loss before Non-Cash Adjustment | B6: 94680000000 | C6: 99803000000 | D6: 96995000000 | E6: 93736000000 | F6: 112010000000 | G6: 117777000000 | I6: =A6 -> Income/Loss before Non-Cash Adjustment | J6: =B6 -> 94680000000 | K6: =C6 -> 99803000000 | L6: =D6 -> 96995000000 | M6: =E6 -> 93736000000 | N6: =F6 -> 112010000000 | O6: =G6 -> 117777000000
A7: Total Adjustments for Non-Cash Items | B7: 14269000000 | C7: 21148000000 | D7: 20125000000 | E7: 20867000000 | F7: 24472000000 | G7: 26395000000 | I7: =A7 -> Total Adjustments for Non-Cash Items | J7: =B7 -> 14269000000 | K7: =C7 -> 21148000000 | L7: =D7 -> 20125000000 | M7: =E7 -> 20867000000 | N7: =F7 -> 24472000000 | O7: =G7 -> 26395000000
A8: Depreciation, Amortization and Depletion, Non-Cash Adjustment | B8: 11284000000 | C8: 11104000000 | D8: 11519000000 | E8: 11445000000 | F8: 11698000000 | G8: 11832000000 | I8: =A8 -> Depreciation, Amortization and Depletion, Non-Cash Adjustment | J8: =B8 -> 11284000000 | K8: =C8 -> 11104000000 | L8: =D8 -> 11519000000 | M8: =E8 -> 11445000000 | N8: =F8 -> 11698000000 | O8: =G8 -> 11832000000
A9: Depreciation and Amortization, Non-Cash Adjustment | B9: 11284000000 | C9: 11104000000 | D9: 11519000000 | E9: 11445000000 | F9: 11698000000 | G9: 11832000000 | I9: =A9 -> Depreciation and Amortization, Non-Cash Adjustment | J9: =B9 -> 11284000000 | K9: =C9 -> 11104000000 | L9: =D9 -> 11519000000 | M9: =E9 -> 11445000000 | N9: =F9 -> 11698000000 | O9: =G9 -> 11832000000
A10: Stock-Based Compensation, Non-Cash Adjustment | B10: 7906000000 | C10: 9038000000 | D10: 10833000000 | E10: 11688000000 | F10: 12863000000 | G10: 13171000000 | I10: =A10 -> Stock-Based Compensation, Non-Cash Adjustment | J10: =B10 -> 7906000000 | K10: =C10 -> 9038000000 | L10: =D10 -> 10833000000 | M10: =E10 -> 11688000000 | N10: =F10 -> 12863000000 | O10: =G10 -> 13171000000
A11: Other Non-Cash Items | B11: -147000000 | C11: 111000000 | D11: -2227000000 | E11: -2266000000 | F11: -89000000 | G11: 1392000000 | I11: =A11 -> Other Non-Cash Items | J11: =B11 -> -147000000 | K11: =C11 -> 111000000 | L11: =D11 -> -2227000000 | M11: =E11 -> -2266000000 | N11: =F11 -> -89000000 | O11: =G11 -> 1392000000
A12: Deferred Taxes, Non-Cash Adjustment | B12: -4774000000 | C12: 895000000 | I12: =A12 -> Deferred Taxes, Non-Cash Adjustment | J12: =B12 -> -4774000000 | K12: =C12 -> 895000000 | L12: =D12 | M12: =E12 | N12: =F12 | O12: =G12
A13: Changes in Operating Capital | B13: -4911000000 | C13: 1200000000 | D13: -6577000000 | E13: 3651000000 | F13: -25000000000 | G13: -8700000000 | I13: =A13 -> Changes in Operating Capital | J13: =B13 -> -4911000000 | K13: =C13 -> 1200000000 | L13: =D13 -> -6577000000 | M13: =E13 -> 3651000000 | N13: =F13 -> -25000000000 | O13: =G13 -> -8700000000
A14: Change in Inventories | B14: -2642000000 | C14: 1484000000 | D14: -1618000000 | E14: -1046000000 | F14: 1400000000 | G14: 974000000 | I14: =A14 -> Change in Inventories | J14: =B14 -> -2642000000 | K14: =C14 -> 1484000000 | L14: =D14 -> -1618000000 | M14: =E14 -> -1046000000 | N14: =F14 -> 1400000000 | O14: =G14 -> 974000000
A15: Change in Trade and Other Receivables | B15: -14028000000 | C15: -9343000000 | D15: -417000000 | E15: -5144000000 | F15: -7029000000 | G15: -11164000000 | I15: =A15 -> Change in Trade and Other Receivables | J15: =B15 -> -14028000000 | K15: =C15 -> -9343000000 | L15: =D15 -> -417000000 | M15: =E15 -> -5144000000 | N15: =F15 -> -7029000000 | O15: =G15 -> -11164000000
A16: Change in Trade/Accounts Receivable | B16: -10125000000 | C16: -1823000000 | D16: -1688000000 | E16: -3788000000 | F16: -6682000000 | G16: -10432000000 | I16: =A16 -> Change in Trade/Accounts Receivable | J16: =B16 -> -10125000000 | K16: =C16 -> -1823000000 | L16: =D16 -> -1688000000 | M16: =E16 -> -3788000000 | N16: =F16 -> -6682000000 | O16: =G16 -> -10432000000
A17: Change in Other Receivables | B17: -3903000000 | C17: -7520000000 | D17: 1271000000 | E17: -1356000000 | F17: -347000000 | G17: -732000000 | I17: =A17 -> Change in Other Receivables | J17: =B17 -> -3903000000 | K17: =C17 -> -7520000000 | L17: =D17 -> 1271000000 | M17: =E17 -> -1356000000 | N17: =F17 -> -347000000 | O17: =G17 -> -732000000
A18: Change in Other Current Assets | B18: -8042000000 | C18: -6499000000 | D18: -5684000000 | E18: -11731000000 | F18: -9197000000 | G18: -20386000000 | I18: =A18 -> Change in Other Current Assets | J18: =B18 -> -8042000000 | K18: =C18 -> -6499000000 | L18: =D18 -> -5684000000 | M18: =E18 -> -11731000000 | N18: =F18 -> -9197000000 | O18: =G18 -> -20386000000
A19: Change in Payables and Accrued Expenses | B19: 12326000000 | C19: 9448000000 | D19: -1889000000 | E19: 6020000000 | F19: 902000000 | G19: 8421000000 | I19: =A19 -> Change in Payables and Accrued Expenses | J19: =B19 -> 12326000000 | K19: =C19 -> 9448000000 | L19: =D19 -> -1889000000 | M19: =E19 -> 6020000000 | N19: =F19 -> 902000000 | O19: =G19 -> 8421000000
A20: Change in Trade and Other Payables | B20: 12326000000 | C20: 9448000000 | D20: -1889000000 | E20: 6020000000 | F20: 902000000 | G20: 8421000000 | I20: =A20 -> Change in Trade and Other Payables | J20: =B20 -> 12326000000 | K20: =C20 -> 9448000000 | L20: =D20 -> -1889000000 | M20: =E20 -> 6020000000 | N20: =F20 -> 902000000 | O20: =G20 -> 8421000000
A21: Change in Trade/Accounts Payable | B21: 12326000000 | C21: 9448000000 | D21: -1889000000 | E21: 6020000000 | F21: 902000000 | G21: 8421000000 | I21: =A21 -> Change in Trade/Accounts Payable | J21: =B21 -> 12326000000 | K21: =C21 -> 9448000000 | L21: =D21 -> -1889000000 | M21: =E21 -> 6020000000 | N21: =F21 -> 902000000 | O21: =G21 -> 8421000000
A22: Change in Other Current Liabilities | B22: 5799000000 | C22: 5632000000 | D22: 3031000000 | E22: 15552000000 | F22: -11076000000 | G22: 13455000000 | I22: =A22 -> Change in Other Current Liabilities | J22: =B22 -> 5799000000 | K22: =C22 -> 5632000000 | L22: =D22 -> 3031000000 | M22: =E22 -> 15552000000 | N22: =F22 -> -11076000000 | O22: =G22 -> 13455000000
A23: Change in Deferred Assets/Liabilities | B23: 1676000000 | C23: 478000000 | I23: =A23 -> Change in Deferred Assets/Liabilities | J23: =B23 -> 1676000000 | K23: =C23 -> 478000000 | L23: =D23 | M23: =E23 | N23: =F23 | O23: =G23
A24: Cash Flow from Investing Activities | B24: -14545000000 | C24: -22354000000 | D24: 3705000000 | E24: 2935000000 | F24: 15195000000 | G24: 517000000 | I24: =A24 -> Cash Flow from Investing Activities | J24: =B24 -> -14545000000 | K24: =C24 -> -22354000000 | L24: =D24 -> 3705000000 | M24: =E24 -> 2935000000 | N24: =F24 -> 15195000000 | O24: =G24 -> 517000000
A25: Cash Flow from Continuing Investing Activities | B25: -14545000000 | C25: -22354000000 | D25: 3705000000 | E25: 2935000000 | F25: 15195000000 | G25: 517000000 | I25: =A25 -> Cash Flow from Continuing Investing Activities | J25: =B25 -> -14545000000 | K25: =C25 -> -22354000000 | L25: =D25 -> 3705000000 | M25: =E25 -> 2935000000 | N25: =F25 -> 15195000000 | O25: =G25 -> 517000000
A26: Purchase/Sale and Disposal of Property, Plant and Equipment, Net | B26: -11085000000 | C26: -10708000000 | D26: -10959000000 | E26: -9447000000 | F26: -12715000000 | G26: -12148000000 | I26: =A26 -> Purchase/Sale and Disposal of Property, Plant and Equipment, Net | J26: =B26 -> -11085000000 | K26: =C26 -> -10708000000 | L26: =D26 -> -10959000000 | M26: =E26 -> -9447000000 | N26: =F26 -> -12715000000 | O26: =G26 -> -12148000000
A27: Purchase of Property, Plant and Equipment | B27: -11085000000 | C27: -10708000000 | D27: -10959000000 | E27: -9447000000 | F27: -12715000000 | G27: -12148000000 | I27: =A27 -> Purchase of Property, Plant and Equipment | J27: =B27 -> -11085000000 | K27: =C27 -> -10708000000 | L27: =D27 -> -10959000000 | M27: =E27 -> -9447000000 | N27: =F27 -> -12715000000 | O27: =G27 -> -12148000000
A28: Purchase/Sale of Investments, Net | B28: -2819000000 | C28: -9560000000 | D28: 16001000000 | E28: 13690000000 | F28: 29390000000 | G28: 13696000000 | I28: =A28 -> Purchase/Sale of Investments, Net | J28: =B28 -> -2819000000 | K28: =C28 -> -9560000000 | L28: =D28 -> 16001000000 | M28: =E28 -> 13690000000 | N28: =F28 -> 29390000000 | O28: =G28 -> 13696000000
A29: Purchase of Investments | B29: -109689000000 | C29: -76923000000 | D29: -29513000000 | E29: -48656000000 | F29: -24407000000 | G29: -30976000000 | I29: =A29 -> Purchase of Investments | J29: =B29 -> -109689000000 | K29: =C29 -> -76923000000 | L29: =D29 -> -29513000000 | M29: =E29 -> -48656000000 | N29: =F29 -> -24407000000 | O29: =G29 -> -30976000000
A30: Sale of Investments | B30: 106870000000 | C30: 67363000000 | D30: 45514000000 | E30: 62346000000 | F30: 53797000000 | G30: 44672000000 | I30: =A30 -> Sale of Investments | J30: =B30 -> 106870000000 | K30: =C30 -> 67363000000 | L30: =D30 -> 45514000000 | M30: =E30 -> 62346000000 | N30: =F30 -> 53797000000
A31: Other Investing Cash Flow | B31: -608000000 | C31: -1780000000 | D31: -1337000000 | E31: -1308000000 | F31: -1480000000 | G31: -1031000000 | I31: -Maturities of Marketable Securities | J31: 59023000000 | K31: 29917000000 | L31: 39686000000 | M31: 51211000000 | N31: 40907000000
A32: Purchase/Sale of Business, Net | B32: -33000000 | C32: -306000000 | I32: -Sales of Marketable Securities | J32: 47847000000 | K32: 37446000000 | L32: 5828000000 | M32: 11135000000 | N32: 12890000000
A33: Purchase/Acquisition of Business | B33: -33000000 | C33: -306000000 | I33: Reconcialiation Check | J33: =ABS(SUM(J31:J32))=ABS(J30) -> TRUE | K33: =ABS(SUM(K31:K32))=ABS(K30) -> TRUE | L33: =ABS(SUM(L31:L32))=ABS(L30) -> TRUE | M33: =ABS(SUM(M31:M32))=ABS(M30) -> TRUE | N33: =ABS(SUM(N31:N32))=ABS(N30) -> TRUE | P33: =AND(J33:O33) -> TRUE
A34: Purchase/Sale of Intangibles, Net | I34: =A31 -> Other Investing Cash Flow | J34: =B31 -> -608000000 | K34: =C31 -> -1780000000 | L34: =D31 -> -1337000000 | M34: =E31 -> -1308000000 | N34: =F31 -> -1480000000 | O34: =G34
A35: Purchase of Intangibles | I35: =A32 -> Purchase/Sale of Business, Net | J35: =B32 -> -33000000 | K35: =C32 -> -306000000 | L35: =D32 | M35: =E32 | N35: =F32 | O35: =G35
A36: Cash Flow from Financing Activities | B36: -93353000000 | C36: -110749000000 | D36: -108488000000 | E36: -121983000000 | F36: -120686000000 | G36: -120971000000 | I36: =A33 -> Purchase/Acquisition of Business | J36: =B33 -> -33000000 | K36: =C33 -> -306000000 | L36: =D33 | M36: =E33 | N36: =F33 | O36: =G36 -> -120971000000
A37: Cash Flow from Continuing Financing Activities | B37: -93353000000 | C37: -110749000000 | D37: -108488000000 | E37: -121983000000 | F37: -120686000000 | G37: -120971000000 | I37: =A34 -> Purchase/Sale of Intangibles, Net | J37: =B34 | K37: =C34 | L37: =D34 | M37: =E34 | N37: =F34 | O37: =G37 -> -120971000000
A38: Issuance of/Payments for Common Stock, Net | B38: -84866000000 | C38: -89402000000 | D38: -77550000000 | E38: -94949000000 | F38: -90711000000 | G38: -91806000000 | I38: =A35 -> Purchase of Intangibles | J38: =B35 | K38: =C35 | L38: =D35 | M38: =E35 | N38: =F35 | O38: =G38 -> -91806000000
A39: Payments for Common Stock | B39: -85971000000 | C39: -89402000000 | D39: -77550000000 | E39: -94949000000 | F39: -90711000000 | G39: -91806000000 | I39: =A36 -> Cash Flow from Financing Activities | J39: =B36 -> -93353000000 | K39: =C36 -> -110749000000 | L39: =D36 -> -108488000000 | M39: =E36 -> -121983000000 | N39: =F36 -> -120686000000 | O39: =G39 -> -91806000000
A40: Proceeds from Issuance of Common Stock | B40: 1105000000 | I40: =A37 -> Cash Flow from Continuing Financing Activities | J40: =B37 -> -93353000000 | K40: =C37 -> -110749000000 | L40: =D37 -> -108488000000 | M40: =E37 -> -121983000000 | N40: =F37 -> -120686000000 | O40: =G40
A41: Issuance of/Repayments for Debt, Net | B41: 12665000000 | C41: -123000000 | D41: -9901000000 | E41: -5998000000 | F41: -8483000000 | G41: -7604000000 | I41: =A38 -> Issuance of/Payments for Common Stock, Net | J41: =B38 -> -84866000000 | K41: =C38 -> -89402000000 | L41: =D38 -> -77550000000 | M41: =E38 -> -94949000000 | N41: =F38 -> -90711000000 | O41: =G41 -> -7604000000
A42: Issuance of/Repayments for Short Term Debt, Net | B42: 1022000000 | C42: 3955000000 | D42: -3978000000 | E42: 3960000000 | F42: -2032000000 | G42: 2000000 | I42: =A39 -> Payments for Common Stock | J42: =B39 -> -85971000000 | K42: =C39 -> -89402000000 | L42: =D39 -> -77550000000 | M42: =E39 -> -94949000000 | N42: =F39 -> -90711000000 | O42: =G42 -> 2000000
A43: Issuance of/Repayments for Long Term Debt, Net | B43: 11643000000 | C43: -4078000000 | D43: -5923000000 | E43: -9958000000 | F43: -6451000000 | G43: -7606000000 | I43: =A40 -> Proceeds from Issuance of Common Stock | J43: =B40 -> 1105000000 | K43: =C40 | L43: =D40 | M43: =E40 | N43: =F40 | O43: =G43 -> -7606000000
A44: Proceeds from Issuance of Long Term Debt | B44: 20393000000 | C44: 5465000000 | D44: 5228000000 | E44: 0 | F44: 4481000000 | I44: =A41 -> Issuance of/Repayments for Debt, Net | J44: =B41 -> 12665000000 | K44: =C41 -> -123000000 | L44: =D41 -> -9901000000 | M44: =E41 -> -5998000000 | N44: =F41 -> -8483000000 | O44: =G44
A45: Repayments for Long Term Debt | B45: -8750000000 | C45: -9543000000 | D45: -11151000000 | E45: -9958000000 | F45: -10932000000 | G45: -12087000000 | I45: =A42 -> Issuance of/Repayments for Short Term Debt, Net | J45: =B42 -> 1022000000 | K45: =C42 -> 3955000000 | L45: =D42 -> -3978000000 | M45: =E42 -> 3960000000 | N45: =F42 -> -2032000000 | O45: =G45 -> -12087000000
A46: Cash Dividends and Interest Paid | B46: -14467000000 | C46: -14841000000 | D46: -15025000000 | E46: -15234000000 | F46: -15421000000 | G46: -15486000000 | I46: =A43 -> Issuance of/Repayments for Long Term Debt, Net | J46: =B43 -> 11643000000 | K46: =C43 -> -4078000000 | L46: =D43 -> -5923000000 | M46: =E43 -> -9958000000 | N46: =F43 -> -6451000000 | O46: =G46 -> -15486000000
A47: Cash Dividends Paid | B47: -14467000000 | C47: -14841000000 | D47: -15025000000 | E47: -15234000000 | F47: -15421000000 | G47: -15486000000 | I47: =A44 -> Proceeds from Issuance of Long Term Debt | J47: =B44 -> 20393000000 | K47: =C44 -> 5465000000 | L47: =D44 -> 5228000000 | M47: =E44 -> 0 | N47: =F44 -> 4481000000 | O47: =G47 -> -15486000000
A48: Common Stock Dividends Paid | B48: -14467000000 | D48: -15025000000 | E48: -15234000000 | F48: -15421000000 | G48: -15486000000 | I48: =A45 -> Repayments for Long Term Debt | J48: =B45 -> -8750000000 | K48: =C45 -> -9543000000 | L48: =D45 -> -11151000000 | M48: =E45 -> -9958000000 | N48: =F45 -> -10932000000 | O48: =G48 -> -15486000000
A49: Other Financing Cash Flow | B49: -6685000000 | C49: -6383000000 | D49: -6012000000 | E49: -5802000000 | F49: -6071000000 | G49: -6075000000 | I49: =A46 -> Cash Dividends and Interest Paid | J49: =B46 -> -14467000000 | K49: =C46 -> -14841000000 | L49: =D46 -> -15025000000 | M49: =E46 -> -15234000000 | N49: =F46 -> -15421000000 | O49: =G49 -> -6075000000
A50: Excess Tax Benefit from Share-Based Compensation, Financing Activities | I50: =A47 -> Cash Dividends Paid | J50: =B47 -> -14467000000 | K50: =C47 -> -14841000000 | L50: =D47 -> -15025000000 | M50: =E47 -> -15234000000 | N50: =F47 -> -15421000000 | O50: =G50
A51: Cash and Cash Equivalents, End of Period | B51: 35929000000 | C51: 24977000000 | D51: 30737000000 | E51: 29943000000 | F51: 35934000000 | G51: 45317000000 | I51: =A48 -> Common Stock Dividends Paid | J51: =B48 -> -14467000000 | K51: =C48 | L51: =D48 -> -15025000000 | M51: =E48 -> -15234000000 | N51: =F48 -> -15421000000 | O51: =G51 -> 45317000000
A52: Change in Cash | B52: -3860000000 | C52: -10952000000 | D52: 5760000000 | E52: -794000000 | F52: 5991000000 | G52: 15018000000 | I52: =A49 -> Other Financing Cash Flow | J52: =B49 -> -6685000000 | K52: =C49 -> -6383000000 | L52: =D49 -> -6012000000 | M52: =E49 -> -5802000000 | N52: =F49 -> -6071000000 | O52: =G52 -> 15018000000
A53: Cash and Cash Equivalents, Beginning of Period | B53: 39789000000 | C53: 35929000000 | D53: 24977000000 | E53: 30737000000 | F53: 29943000000 | G53: 30299000000 | I53: -Taxes related to net share settlement of equity awards | J53: 6685000000 | K53: 6223000000 | L53: 5431000000 | M53: 5441000000 | N53: 5960000000
A54: Cash Flow Supplemental Section | I54: -Other | J54: 0 | K54: 160000000 | L54: 581000000 | M54: 361000000 | N54: 111000000
A55: Change in Cash as Reported, Supplemental | B55: -3860000000 | C55: -10952000000 | D55: 5760000000 | E55: -794000000 | F55: 5991000000 | G55: 15018000000 | I55: Reconcialiation Check | J55: =ABS(SUM(J53:J54))=ABS(J52) -> TRUE | K55: =ABS(SUM(K53:K54))=ABS(K52) -> TRUE | L55: =ABS(SUM(L53:L54))=ABS(L52) -> TRUE | M55: =ABS(SUM(M53:M54))=ABS(M52) -> TRUE | N55: =ABS(SUM(N53:N54))=ABS(N52) -> TRUE | P55: =AND(J55:O55) -> TRUE
A56: Income Tax Paid, Supplemental | B56: -25385000000 | C56: -19573000000 | D56: -18679000000 | E56: -26102000000 | F56: -43369000000 | G56: -28152000000 | I56: =A50 -> Excess Tax Benefit from Share-Based Compensation, Financing Activities | J56: =B50 | K56: =C50 | L56: =D50 | M56: =E50 | N56: =F50 | O56: =G53 -> 30299000000
A57: Interest Paid, Supplemental | B57: -2687000000 | C57: -2865000000 | D57: -3803000000 | I57: =A51 -> Cash and Cash Equivalents, End of Period | J57: =B51 -> 35929000000 | K57: =C51 -> 24977000000 | L57: =D51 -> 30737000000 | M57: =E51 -> 29943000000 | N57: =F51 -> 35934000000 | O57: =G54
A58: Fiscal year ends in Sep 30 | USD | I58: =A52 -> Change in Cash | J58: =B52 -> -3860000000 | K58: =C52 -> -10952000000 | L58: =D52 -> 5760000000 | M58: =E52 -> -794000000 | N58: =F52 -> 5991000000 | O58: =G55 -> 15018000000
I59: =A53 -> Cash and Cash Equivalents, Beginning of Period | J59: =B53 -> 39789000000 | K59: =C53 -> 35929000000 | L59: =D53 -> 24977000000 | M59: =E53 -> 30737000000 | N59: =F53 -> 29943000000 | O59: =G56 -> -28152000000
I60: =A54 -> Cash Flow Supplemental Section | J60: =B54 | K60: =C54 | L60: =D54 | M60: =E54 | N60: =F54 | O60: =G57
I61: =A55 -> Change in Cash as Reported, Supplemental | J61: =B55 -> -3860000000 | K61: =C55 -> -10952000000 | L61: =D55 -> 5760000000 | M61: =E55 -> -794000000 | N61: =F55 -> 5991000000
I62: =A56 -> Income Tax Paid, Supplemental | J62: =B56 -> -25385000000 | K62: =C56 -> -19573000000 | L62: =D56 -> -18679000000 | M62: =E56 -> -26102000000 | N62: =F56 -> -43369000000
I63: =A57 -> Interest Paid, Supplemental | J63: =B57 -> -2687000000 | K63: =C57 -> -2865000000 | L63: =D57 -> -3803000000 | M63: =E57 | N63: =F57
I64: Fiscal year ends in Sep 30 | USD

Sheet Balance Sheet
B1: Balance Sheet | I1: CHECK | J1: =AND(L59) -> TRUE
B2: Historical Financial Analysis | All figures in USD ($millions) | Inputs in Blue
B4: USD ($millions) | C4: FY2021 | D4: FY2022 | E4: FY2023 | F4: FY2024 | G4: FY2025 | H4: ="FY"&(MID(G4,3,4)+1) -> FY2026 | I4: ="FY"&(MID(H4,3,4)+1) -> FY2027 | J4: ="FY"&(MID(I4,3,4)+1) -> FY2028 | K4: ="FY"&(MID(J4,3,4)+1) -> FY2029 | L4: ="FY"&(MID(K4,3,4)+1) -> FY2030
B6: ASSETS
B7: Current Assets | H7: ="PROJECTED " & B7 -> PROJECTED Current Assets
B8: Cash & Cash Equivalents | C8: ='Raw (Balance Sheet)'!J6 -> 34940000000 | D8: ='Raw (Balance Sheet)'!K6 -> 23646000000 | E8: ='Raw (Balance Sheet)'!L6 -> 29965000000 | F8: ='Raw (Balance Sheet)'!M6 -> 29943000000 | G8: ='Raw (Balance Sheet)'!N6 -> 35934000000 | H8: ='Cash Flow Statement'!H49 -> 6.0850289e+10 | I8: ='Cash Flow Statement'!I49 -> 1.0476213e+11 | J8: ='Cash Flow Statement'!J49 -> 1.6865428e+11 | K8: ='Cash Flow Statement'!K49 -> 2.4946139e+11 | L8: ='Cash Flow Statement'!L49 -> 3.5118634e+11
B9: Short-Term Investments | C9: ='Raw (Balance Sheet)'!J9 -> 27699000000 | D9: ='Raw (Balance Sheet)'!K9 -> 24658000000 | E9: ='Raw (Balance Sheet)'!L9 -> 31590000000 | F9: ='Raw (Balance Sheet)'!M9 -> 35228000000 | G9: ='Raw (Balance Sheet)'!N9 -> 18763000000 | H9: 18763000000 | I9: 18763000000 | J9: 18763000000 | K9: 18763000000 | L9: 18763000000
B10: Accounts Receivable, net | C10: ='Raw (Balance Sheet)'!J13 -> 26278000000 | D10: ='Raw (Balance Sheet)'!K13 -> 28184000000 | E10: ='Raw (Balance Sheet)'!L13 -> 29508000000 | F10: ='Raw (Balance Sheet)'!M13 -> 33410000000 | G10: ='Raw (Balance Sheet)'!N13 -> 39777000000 | H10: =ROUND('Assumptions & Drivers'!$D$22/365*'Income Statement'!H10,0) -> 42393994789 | I10: =ROUND('Assumptions & Drivers'!$D$22/365*'Income Statement'!I10,0) -> 45251034567 | J10: =ROUND('Assumptions & Drivers'!$D$22/365*'Income Statement'!J10,0) -> 48375872456 | K10: =ROUND('Assumptions & Drivers'!$D$22/365*'Income Statement'!K10,0) -> 51799817877 | L10: =ROUND('Assumptions & Drivers'!$D$22/365*'Income Statement'!L10,0) -> 55558208971
B11: Vendor non-trade Receivables | C11: ='Raw (Balance Sheet)'!J16 -> 25228000000 | D11: ='Raw (Balance Sheet)'!K16 -> 32748000000 | E11: ='Raw (Balance Sheet)'!L16 -> 31477000000 | F11: ='Raw (Balance Sheet)'!M16 -> 32833000000 | G11: ='Raw (Balance Sheet)'!N16 -> 33180000000 | H11: =ROUND('Balance Sheet'!G11/'Income Statement'!G18*'Income Statement'!H18,0) -> 34903851937 | I11: =ROUND('Balance Sheet'!H11/'Income Statement'!H18*'Income Statement'!I18,0) -> 36409618798 | J11: =ROUND('Balance Sheet'!I11/'Income Statement'!I18*'Income Statement'!J18,0) -> 38000243874 | K11: =ROUND('Balance Sheet'!J11/'Income Statement'!J18*'Income Statement'!K18,0) -> 40930584870 | L11: =ROUND('Balance Sheet'!K11/'Income Statement'!K18*'Income Statement'!L18,0) -> 43254066618
B12: Inventories | C12: ='Raw (Balance Sheet)'!J11 -> 6580000000 | D12: ='Raw (Balance Sheet)'!K11 -> 4946000000 | E12: ='Raw (Balance Sheet)'!L11 -> 6331000000 | F12: ='Raw (Balance Sheet)'!M11 -> 7286000000 | G12: ='Raw (Balance Sheet)'!N11 -> 5718000000 | H12: =ROUND('Assumptions & Drivers'!$D$23/365*'Income Statement'!H18,0) -> 6015076111 | I12: =ROUND('Assumptions & Drivers'!$D$23/365*'Income Statement'!I18,0) -> 6274569026 | J12: =ROUND('Assumptions & Drivers'!$D$23/365*'Income Statement'!J18,0) -> 6548685789 | K12: =ROUND('Assumptions & Drivers'!$D$23/365*'Income Statement'!K18,0) -> 7053679454 | L12: =ROUND('Assumptions & Drivers'!$D$23/365*'Income Statement'!L18,0) -> 7454091408
B13: Prepaid Expenses & Other Current Assets | C13: ='Raw (Balance Sheet)'!J17 -> 14111000000 | D13: ='Raw (Balance Sheet)'!K17 -> 21223000000 | E13: ='Raw (Balance Sheet)'!L17 -> 14695000000 | F13: ='Raw (Balance Sheet)'!M17 -> 14287000000 | G13: ='Raw (Balance Sheet)'!N17 -> 14585000000 | H13: =ROUND('Balance Sheet'!G13/'Income Statement'!G10*'Income Statement'!H10,0) -> 15544571335 | I13: =ROUND('Balance Sheet'!H13/'Income Statement'!H10*'Income Statement'!I10,0) -> 16592159770 | J13: =ROUND('Balance Sheet'!I13/'Income Statement'!I10*'Income Statement'!J10,0) -> 17737941518 | K13: =ROUND('Balance Sheet'!J13/'Income Statement'!J10*'Income Statement'!K10,0) -> 18993396780 | L13: =ROUND('Balance Sheet'!K13/'Income Statement'!K10*'Income Statement'!L10,0) -> 20371482963
B14: Total Current Assets | C14: =SUM(C8:C13) -> 134836000000 | D14: =SUM(D8:D13) -> 135405000000 | E14: =SUM(E8:E13) -> 143566000000 | F14: =SUM(F8:F13) -> 152987000000 | G14: =SUM(G8:G13) -> 147957000000 | H14: =SUM(H8:H13) -> 1.7847078e+11 | I14: =SUM(I8:I13) -> 2.2805251e+11 | J14: =SUM(J8:J13) -> 2.9808003e+11 | ... L14: =SUM(L8:L13) -> 4.9658719e+11
B16: Non-Current Assets | H16: ="PROJECTED " & B16 -> PROJECTED Non-Current Assets
B17: Property, Plant & Equipment, gross | C17: ='Raw (Balance Sheet)'!J20 -> 119810000000 | D17: ='Raw (Balance Sheet)'!K20 -> 124874000000 | E17: ='Raw (Balance Sheet)'!L20 -> 114599000000 | F17: ='Raw (Balance Sheet)'!M20 -> 119128000000 | G17: ='Raw (Balance Sheet)'!N20 -> 125848000000 | H17: =G17-'Cash Flow Statement'!H25 -> 1.3959777e+11 | I17: =H17-'Cash Flow Statement'!I25 -> 1.5380074e+11 | J17: =I17-'Cash Flow Statement'!J25 -> 1.6847837e+11 | K17: =J17-'Cash Flow Statement'!K25 -> 1.8419487e+11 | L17: =K17-'Cash Flow Statement'!L25 -> 2.0047041e+11
B18: Less: Accumulated Depreciation | C18: ='Raw (Balance Sheet)'!J27 -> -70283000000 | D18: ='Raw (Balance Sheet)'!K27 -> -72340000000 | E18: ='Raw (Balance Sheet)'!L27 -> -70884000000 | F18: ='Raw (Balance Sheet)'!M27 -> -73448000000 | G18: ='Raw (Balance Sheet)'!N27 -> -76014000000 | H18: =G18-'Income Statement'!H55 -> -8.8433146e+10 | I18: =H18-'Income Statement'!I55 -> -1.0168925e+11 | J18: =I18-'Income Statement'!J55 -> -1.1535464e+11 | K18: =J18-'Income Statement'!K55 -> -1.2998723e+11 | L18: =K18-'Income Statement'!L55 -> -1.4568151e+11
B19: PP&E, net | C19: ='Raw (Balance Sheet)'!J19 -> 49527000000 | D19: ='Raw (Balance Sheet)'!K19 -> 52534000000 | E19: ='Raw (Balance Sheet)'!L19 -> 43715000000 | F19: ='Raw (Balance Sheet)'!M19 -> 45680000000 | G19: ='Raw (Balance Sheet)'!N19 -> 49834000000 | H19: =H17+H18 -> 5.1164623e+10 | I19: =I17+I18 -> 5.2111487e+10 | J19: =J17+J18 -> 5.3123738e+10 | K19: =K17+K18 -> 5.4207634e+10 | L19: =L17+L18 -> 5.4788904e+10
B20: Goodwill | C20: =IF('Raw (Balance Sheet)'!J39="",0,'Raw (Balance Sheet)'!J39) -> 0 | D20: =IF('Raw (Balance Sheet)'!K39="",0,'Raw (Balance Sheet)'!K39) -> 0 | E20: =IF('Raw (Balance Sheet)'!L39="",0,'Raw (Balance Sheet)'!L39) -> 0 | F20: =IF('Raw (Balance Sheet)'!M39="",0,'Raw (Balance Sheet)'!M39) -> 0 | G20: =IF('Raw (Balance Sheet)'!N39="",0,'Raw (Balance Sheet)'!N39) -> 0 | H20: 0 | I20: 0 | J20: 0 | K20: 0 | L20: 0
B21: Intangible Assets, net | C21: =IF('Raw (Balance Sheet)'!J40="",0,'Raw (Balance Sheet)'!J40) -> 0 | D21: =IF('Raw (Balance Sheet)'!K40="",0,'Raw (Balance Sheet)'!K40) -> 0 | E21: =IF('Raw (Balance Sheet)'!L40="",0,'Raw (Balance Sheet)'!L40) -> 0 | F21: =IF('Raw (Balance Sheet)'!M40="",0,'Raw (Balance Sheet)'!M40) -> 0 | G21: =IF('Raw (Balance Sheet)'!N40="",0,'Raw (Balance Sheet)'!N40) -> 0 | H21: 0 | I21: 0 | J21: 0 | K21: 0 | L21: 0
B22: Long-Term Investments | C22: 0 | D22: 0 | E22: 0 | F22: 0 | G22: 0 | H22: 0 | I22: 0 | J22: 0 | K22: 0 | L22: 0
B23: Deferred Tax Assets | C23: =IF('Raw (Balance Sheet)'!J35="",0,'Raw (Balance Sheet)'!J35) -> 0 | D23: =IF('Raw (Balance Sheet)'!K35="",0,'Raw (Balance Sheet)'!K35) -> 0 | E23: =IF('Raw (Balance Sheet)'!L35="",0,'Raw (Balance Sheet)'!L35) -> 17852000000 | F23: =IF('Raw (Balance Sheet)'!M35="",0,'Raw (Balance Sheet)'!M35) -> 19499000000 | G23: =IF('Raw (Balance Sheet)'!N35="",0,'Raw (Balance Sheet)'!N35) -> 20777000000 | H23: 20777000000 | I23: 20777000000 | J23: 20777000000 | K23: 20777000000 | L23: 20777000000
B24: Other Non-Current Assets | C24: =IF('Raw (Balance Sheet)'!J29="",0,'Raw (Balance Sheet)'!J29)+'Raw (Balance Sheet)'!J36 -> 166639000000 | D24: =IF('Raw (Balance Sheet)'!K29="",0,'Raw (Balance Sheet)'!K29)+'Raw (Balance Sheet)'!K36 -> 164816000000 | E24: =IF('Raw (Balance Sheet)'!L29="",0,'Raw (Balance Sheet)'!L29)+'Raw (Balance Sheet)'!L36 -> 147450000000 | F24: =IF('Raw (Balance Sheet)'!M29="",0,'Raw (Balance Sheet)'!M29)+'Raw (Balance Sheet)'!M36 -> 146814000000 | G24: =IF('Raw (Balance Sheet)'!N29="",0,'Raw (Balance Sheet)'!N29)+'Raw (Balance Sheet)'!N36 -> 140673000000 | H24: 140673000000 | I24: 140673000000 | J24: 140673000000 | K24: 140673000000 | L24: 140673000000
B25: Total Non-Current Assets | C25: =SUM(C19:C24) -> 216166000000 | D25: =SUM(D19:D24) -> 217350000000 | E25: =SUM(E19:E24) -> 209017000000 | F25: =SUM(F19:F24) -> 211993000000 | G25: =SUM(G19:G24) -> 211284000000 | H25: =SUM(H19:H24) -> 2.1261462e+11 | I25: =SUM(I19:I24) -> 2.1356149e+11 | J25: =SUM(J19:J24) -> 2.1457374e+11 | ... L25: =SUM(L19:L24) -> 2.162389e+11
B27: TOTAL ASSETS | C27: =C14+C25 -> 351002000000 | D27: =D14+D25 -> 352755000000 | E27: =E14+E25 -> 352583000000 | F27: =F14+F25 -> 364980000000 | G27: =G14+G25 -> 359241000000 | H27: =H14+H25 -> 3.9108541e+11 | I27: =I14+I25 -> 4.41614e+11 | J27: =J14+J25 -> 5.1265376e+11 | ... L27: =L14+L25 -> 7.128261e+11
B29: LIABILITIES & SHAREHOLDERS' EQUITY
B30: Current Liabilities | H30: ="PROJECTED " & B30 -> PROJECTED Current Liabilities
B31: Accounts Payable | C31: ='Raw (Balance Sheet)'!J51 -> 54763000000 | D31: ='Raw (Balance Sheet)'!K51 -> 64115000000 | E31: ='Raw (Balance Sheet)'!L51 -> 62611000000 | F31: ='Raw (Balance Sheet)'!M51 -> 68960000000 | G31: ='Raw (Balance Sheet)'!N51 -> 69860000000 | H31: =ROUND('Assumptions & Drivers'!$D$24/365*'Income Statement'!H18,0) -> 73489544796 | I31: =ROUND('Assumptions & Drivers'!$D$24/365*'Income Statement'!I18,0) -> 76659914685 | J31: =ROUND('Assumptions & Drivers'!$D$24/365*'Income Statement'!J18,0) -> 80008952291 | K31: =ROUND('Assumptions & Drivers'!$D$24/365*'Income Statement'!K18,0) -> 86178741984 | L31: =ROUND('Assumptions & Drivers'!$D$24/365*'Income Statement'!L18,0) -> 91070798492
B32: Commerical Paper | C32: ='Raw (Balance Sheet)'!J56 -> 6000000000 | D32: ='Raw (Balance Sheet)'!K56 -> 9982000000 | E32: ='Raw (Balance Sheet)'!L56 -> 5985000000 | F32: ='Raw (Balance Sheet)'!M56 -> 9967000000 | G32: ='Raw (Balance Sheet)'!N56 -> 7979000000 | H32: 7979000000 | I32: 7979000000 | J32: 7979000000 | K32: 7979000000 | L32: 7979000000
B33: Short-Term Debt & Current Portion of LTD | C33: ='Raw (Balance Sheet)'!J58 -> 11141000000 | D33: ='Raw (Balance Sheet)'!K58 -> 12791000000 | E33: ='Raw (Balance Sheet)'!L58 -> 11397000000 | F33: ='Raw (Balance Sheet)'!M58 -> 10912000000 | G33: ='Raw (Balance Sheet)'!N58 -> 12350000000 | H33: 12350000000 | I33: 12350000000 | J33: 12350000000 | K33: 12350000000 | L33: 12350000000
B34: Deferred Revenue (current) | C34: ='Raw (Balance Sheet)'!J63 -> 7612000000 | D34: ='Raw (Balance Sheet)'!K63 -> 7912000000 | E34: ='Raw (Balance Sheet)'!L63 -> 8061000000 | F34: ='Raw (Balance Sheet)'!M63 -> 8249000000 | G34: ='Raw (Balance Sheet)'!N63 -> 9055000000 | H34: =ROUND('Balance Sheet'!G34/'Income Statement'!G8*'Income Statement'!H8,0) -> 10278007362 | I34: =ROUND('Balance Sheet'!H34/'Income Statement'!H8*'Income Statement'!I8,0) -> 11666199374 | J34: =ROUND('Balance Sheet'!I34/'Income Statement'!I8*'Income Statement'!J8,0) -> 13241886588 | K34: =ROUND('Balance Sheet'!J34/'Income Statement'!J8*'Income Statement'!K8,0) -> 15030392914 | L34: =ROUND('Balance Sheet'!K34/'Income Statement'!K8*'Income Statement'!L8,0) -> 17060462620
B35: Other Current Liabilities | C35: =IF('Raw (Balance Sheet)'!J52="",0,'Raw (Balance Sheet)'!J52)+IF('Raw (Balance Sheet)'!J53="",0,'Raw (Balance Sheet)'!J53)+IF('Raw (Balance Sheet)'!J65="",0,'Raw (Balance Sheet)'!J65) -> 45965000000 | D35: =IF('Raw (Balance Sheet)'!K52="",0,'Raw (Balance Sheet)'!K52)+IF('Raw (Balance Sheet)'!K53="",0,'Raw (Balance Sheet)'!K53)+IF('Raw (Balance Sheet)'!K65="",0,'Raw (Balance Sheet)'!K65) -> 59182000000 | E35: =IF('Raw (Balance Sheet)'!L52="",0,'Raw (Balance Sheet)'!L52)+IF('Raw (Balance Sheet)'!L53="",0,'Raw (Balance Sheet)'!L53)+IF('Raw (Balance Sheet)'!L65="",0,'Raw (Balance Sheet)'!L65) -> 57254000000 | F35: =IF('Raw (Balance Sheet)'!M52="",0,'Raw (Balance Sheet)'!M52)+IF('Raw (Balance Sheet)'!M53="",0,'Raw (Balance Sheet)'!M53)+IF('Raw (Balance Sheet)'!M65="",0,'Raw (Balance Sheet)'!M65) -> 78304000000 | G35: =IF('Raw (Balance Sheet)'!N52="",0,'Raw (Balance Sheet)'!N52)+IF('Raw (Balance Sheet)'!N53="",0,'Raw (Balance Sheet)'!N53)+IF('Raw (Balance Sheet)'!N65="",0,'Raw (Balance Sheet)'!N65) -> 66387000000 | H35: =ROUND('Balance Sheet'!G35/'Income Statement'!G10*'Income Statement'!H10,0) -> 70754710814 | I35: =ROUND('Balance Sheet'!H35/'Income Statement'!H10*'Income Statement'!I10,0) -> 75523051809 | J35: =ROUND('Balance Sheet'!I35/'Income Statement'!I10*'Income Statement'!J10,0) -> 80738342377 | K35: =ROUND('Balance Sheet'!J35/'Income Statement'!J10*'Income Statement'!K10,0) -> 86452837302 | L35: =ROUND('Balance Sheet'!K35/'Income Statement'!K10*'Income Statement'!L10,0) -> 92725515222
B36: Total Current Liabilities | C36: =SUM(C31:C35) -> 125481000000 | D36: =SUM(D31:D35) -> 153982000000 | E36: =SUM(E31:E35) -> 145308000000 | F36: =SUM(F31:F35) -> 176392000000 | G36: =SUM(G31:G35) -> 165631000000 | H36: =SUM(H31:H35) -> 174851262972 | I36: =SUM(I31:I35) -> 184178165868 | J36: =SUM(J31:J35) -> 194318181256 | ... L36: =SUM(L31:L35) -> 221185776334
B38: Non-Current Liabilities | H38: ="PROJECTED " & B38 -> PROJECTED Non-Current Liabilities
B39: Long-Term Debt | C39: ='Raw (Balance Sheet)'!J67 -> 119381000000 | D39: ='Raw (Balance Sheet)'!K67 -> 109707000000 | E39: ='Raw (Balance Sheet)'!L67 -> 106548000000 | F39: ='Raw (Balance Sheet)'!M67 -> 85750000000 | G39: ='Raw (Balance Sheet)'!N67 -> 78328000000 | H39: =G39+'Cash Flow Statement'!H37+'Cash Flow Statement'!H38 -> 78328000000 | I39: =H39+'Cash Flow Statement'!I37+'Cash Flow Statement'!I38 -> 78328000000 | J39: =I39+'Cash Flow Statement'!J37+'Cash Flow Statement'!J38 -> 78328000000 | K39: =J39+'Cash Flow Statement'!K37+'Cash Flow Statement'!K38 -> 78328000000 | L39: =K39+'Cash Flow Statement'!L37+'Cash Flow Statement'!L38 -> 78328000000
B40: Deferred Tax Liabilities | C40: 0 | D40: 0 | E40: 0 | F40: 0 | G40: 0 | H40: 0 | I40: 0 | J40: 0 | K40: 0 | L40: 0
B41: Pension & Post-Retirement Obligations | C41: 0 | D41: 0 | E41: 0 | F41: 0 | G41: 0 | H41: 0 | I41: 0 | J41: 0 | K41: 0 | L41: 0
B42: Other Non-Current Liabilities | C42: ='Raw (Balance Sheet)'!J73+IF('Raw (Balance Sheet)'!J74="",0,'Raw (Balance Sheet)'!J74) -> 43050000000 | D42: ='Raw (Balance Sheet)'!K73+IF('Raw (Balance Sheet)'!K74="",0,'Raw (Balance Sheet)'!K74) -> 38394000000 | E42: ='Raw (Balance Sheet)'!L73+IF('Raw (Balance Sheet)'!L74="",0,'Raw (Balance Sheet)'!L74) -> 38581000000 | F42: ='Raw (Balance Sheet)'!M73+IF('Raw (Balance Sheet)'!M74="",0,'Raw (Balance Sheet)'!M74) -> 45888000000 | G42: ='Raw (Balance Sheet)'!N73+IF('Raw (Balance Sheet)'!N74="",0,'Raw (Balance Sheet)'!N74) -> 41549000000 | H42: 41549000000 | I42: 41549000000 | J42: 41549000000 | K42: 41549000000 | L42: 41549000000
B43: Total Non-Current Liabilities | C43: =SUM(C39:C42) -> 162431000000 | D43: =SUM(D39:D42) -> 148101000000 | E43: =SUM(E39:E42) -> 145129000000 | F43: =SUM(F39:F42) -> 131638000000 | G43: =SUM(G39:G42) -> 119877000000 | H43: =SUM(H39:H42) -> 119877000000 | I43: =SUM(I39:I42) -> 119877000000 | J43: =SUM(J39:J42) -> 119877000000 | ... L43: =SUM(L39:L42) -> 119877000000
B45: Total Liabilities | C45: =C36+C43 -> 287912000000 | D45: =D36+D43 -> 302083000000 | E45: =E36+E43 -> 290437000000 | F45: =F36+F43 -> 308030000000 | G45: =G36+G43 -> 285508000000 | H45: =H36+H43 -> 294728262972 | I45: =I36+I43 -> 304055165868 | J45: =J36+J43 -> 314195181256 | ... L45: =L36+L43 -> 341062776334
B47: Shareholders' Equity | H47: ="PROJECTED " & B47 -> PROJECTED Shareholders' Equity
B48: Common Stock & Additional Paid-In Capital | C48: ='Raw (Balance Sheet)'!J83 -> 57365000000 | D48: ='Raw (Balance Sheet)'!K83 -> 64849000000 | E48: ='Raw (Balance Sheet)'!L83 -> 73812000000 | F48: ='Raw (Balance Sheet)'!M83 -> 83276000000 | G48: ='Raw (Balance Sheet)'!N83 -> 93568000000 | H48: =G48+'Cash Flow Statement'!H10 -> 1.0731777e+11 | I48: =H48+'Cash Flow Statement'!I10 -> 1.2199417e+11 | J48: =I48+'Cash Flow Statement'!J10 -> 1.3717793e+11 | K48: =J48+'Cash Flow Statement'!K10 -> 1.5343637e+11 | L48: =K48+'Cash Flow Statement'!L10 -> 1.7029319e+11
B49: Retained Earnings / (Deficit) | C49: ='Raw (Balance Sheet)'!J85 -> 5562000000 | D49: ='Raw (Balance Sheet)'!K85 -> -3068000000 | E49: ='Raw (Balance Sheet)'!L85 -> -214000000 | F49: ='Raw (Balance Sheet)'!M85 -> -19154000000 | G49: ='Raw (Balance Sheet)'!N85 -> -14264000000 | H49: =G49+'Income Statement'!H49-'Assumptions & Drivers'!E33*'Income Statement'!H53-'Assumptions & Drivers'!E32*1000000 -> -5.389626e+09 | I49: =H49+'Income Statement'!I49-'Assumptions & Drivers'!F33*'Income Statement'!I53-'Assumptions & Drivers'!F32*1000000 -> 2.1135666e+10 | J49: =I49+'Income Statement'!J49-'Assumptions & Drivers'!G33*'Income Statement'!J53-'Assumptions & Drivers'!G32*1000000 -> 6.6851651e+10 | K49: =J49+'Income Statement'!K49-'Assumptions & Drivers'!H33*'Income Statement'!K53-'Assumptions & Drivers'!H32*1000000 -> 1.2692616e+11 | L49: =K49+'Income Statement'!L49-'Assumptions & Drivers'!I33*'Income Statement'!L53-'Assumptions & Drivers'!I32*1000000 -> 2.0704113e+11
B50: Accumulated Other Comprehensive Income / (Loss) | C50: ='Raw (Balance Sheet)'!J86 -> 163000000 | D50: ='Raw (Balance Sheet)'!K86 -> -11109000000 | E50: ='Raw (Balance Sheet)'!L86 -> -11452000000 | F50: ='Raw (Balance Sheet)'!M86 -> -7172000000 | G50: ='Raw (Balance Sheet)'!N86 -> -5571000000 | H50: -5571000000 | I50: -5571000000 | J50: -5571000000 | K50: -5571000000 | L50: -5571000000
B51: Treasury Stock | C51: 0 | D51: 0 | E51: 0 | F51: 0 | G51: 0 | H51: 0 | I51: 0 | J51: 0 | K51: 0 | L51: 0
B52: Non-Controlling Interests | C52: 0 | D52: 0 | E52: 0 | F52: 0 | G52: 0 | H52: 0 | I52: 0 | J52: 0 | K52: 0 | L52: 0
B53: Total Shareholders' Equity | C53: =SUM(C48:C52) -> 63090000000 | D53: =SUM(D48:D52) -> 50672000000 | E53: =SUM(E48:E52) -> 62146000000 | F53: =SUM(F48:F52) -> 56950000000 | G53: =SUM(G48:G52) -> 73733000000 | H53: =SUM(H48:H52) -> 9.6357143e+10 | I53: =SUM(I48:I52) -> 1.3755884e+11 | J53: =SUM(J48:J52) -> 1.9845858e+11 | ... L53: =SUM(L48:L52) -> 3.7176332e+11
B55: TOTAL LIABILITIES & EQUITY | C55: =C45+C53 -> 351002000000 | D55: =D45+D53 -> 352755000000 | E55: =E45+E53 -> 352583000000 | F55: =F45+F53 -> 364980000000 | G55: =G45+G53 -> 359241000000 | H55: =H45+H53 -> 3.9108541e+11 | I55: =I45+I53 -> 4.41614e+11 | J55: =J45+J53 -> 5.1265376e+11 | ... L55: =L45+L53 -> 7.128261e+11
B57: Balance Sheet Check (Assets – L&E) → Should be $0 | C57: =C27-C55 -> 0 | D57: =D27-D55 -> 0 | E57: =E27-E55 -> 0 | F57: =F27-F55 -> 0 | G57: =G27-G55 -> 0 | H57: =H27-H55 -> 0 | I57: =I27-I55 -> 0 | J57: =J27-J55 -> 0 | ... L57: =L27-L55 -> 0
B58: Reconcialiation Check | C58: =C57=0 -> TRUE | D58: =D57=0 -> TRUE | E58: =E57=0 -> TRUE | F58: =F57=0 -> TRUE | G58: =G57=0 -> TRUE | H58: =H57=0 -> TRUE | I58: =I57=0 -> TRUE | J58: =J57=0 -> TRUE | ... L58: =L57=0 -> TRUE
L59: =AND(C58:L58) -> TRUE

Sheet Raw (Balance Sheet)
A1: RAW | I1: ADJUSTED
A2: AAPL_balance-sheet_Annual_As_Originally_Reported | B2: 2021 | C2: 2022 | D2: 2023 | E2: 2024 | F2: 2025 | G2: TTM | I2: =A2 -> AAPL_balance-sheet_Annual_As_Originally_Reported | J2: =B2 -> 2021 | K2: =C2 -> 2022 | L2: =D2 -> 2023 | M2: =E2 -> 2024 | N2: =F2 -> 2025 | O2: =G2 -> TTM
A3: Total Assets | B3: 351002000000 | C3: 352755000000 | D3: 352583000000 | E3: 364980000000 | F3: 359241000000 | I3: =A3 -> Total Assets | J3: =B3 -> 351002000000 | K3: =C3 -> 352755000000 | L3: =D3 -> 352583000000 | M3: =E3 -> 364980000000 | N3: =F3 -> 359241000000
A4: Total Current Assets | B4: 134836000000 | C4: 135405000000 | D4: 143566000000 | E4: 152987000000 | F4: 147957000000 | I4: =A4 -> Total Current Assets | J4: =B4 -> 134836000000 | K4: =C4 -> 135405000000 | L4: =D4 -> 143566000000 | M4: =E4 -> 152987000000 | N4: =F4 -> 147957000000
A5: Cash, Cash Equivalents and Short Term Investments | B5: 62639000000 | C5: 48304000000 | D5: 61555000000 | E5: 65171000000 | F5: 54697000000 | I5: =A5 -> Cash, Cash Equivalents and Short Term Investments | J5: =B5 -> 62639000000 | K5: =C5 -> 48304000000 | L5: =D5 -> 61555000000 | M5: =E5 -> 65171000000 | N5: =F5 -> 54697000000
A6: Cash and Cash Equivalents | B6: 34940000000 | C6: 23646000000 | D6: 29965000000 | E6: 29943000000 | F6: 35934000000 | I6: =A6 -> Cash and Cash Equivalents | J6: =B6 -> 34940000000 | K6: =C6 -> 23646000000 | L6: =D6 -> 29965000000 | M6: =E6 -> 29943000000 | N6: =F6 -> 35934000000
A7: Cash | B7: 17305000000 | C7: 18546000000 | D7: 28359000000 | E7: 27199000000 | F7: 28267000000 | I7: =A7 -> Cash | J7: =B7 -> 17305000000 | K7: =C7 -> 18546000000 | L7: =D7 -> 28359000000 | M7: =E7 -> 27199000000 | N7: =F7 -> 28267000000
A8: Cash Equivalents | B8: 17635000000 | C8: 5100000000 | D8: 1606000000 | E8: 2744000000 | F8: 7667000000 | I8: =A8 -> Cash Equivalents | J8: =B8 -> 17635000000 | K8: =C8 -> 5100000000 | L8: =D8 -> 1606000000 | M8: =E8 -> 2744000000 | N8: =F8 -> 7667000000
A9: Short Term Investments | B9: 27699000000 | C9: 24658000000 | D9: 31590000000 | E9: 35228000000 | F9: 18763000000 | I9: =A9 -> Short Term Investments | J9: =B9 -> 27699000000 | K9: =C9 -> 24658000000 | L9: =D9 -> 31590000000 | M9: =E9 -> 35228000000 | N9: =F9 -> 18763000000
A10: Other Short Term Investments | B10: 27699000000 | C10: 24658000000 | D10: 31590000000 | E10: 35228000000 | F10: 18763000000 | I10: =A10 -> Other Short Term Investments | J10: =B10 -> 27699000000 | K10: =C10 -> 24658000000 | L10: =D10 -> 31590000000 | M10: =E10 -> 35228000000 | N10: =F10 -> 18763000000
A11: Inventories | B11: 6580000000 | C11: 4946000000 | D11: 6331000000 | E11: 7286000000 | F11: 5718000000 | I11: =A11 -> Inventories | J11: =B11 -> 6580000000 | K11: =C11 -> 4946000000 | L11: =D11 -> 6331000000 | M11: =E11 -> 7286000000 | N11: =F11 -> 5718000000
A12: Trade and Other Receivables, Current | B12: 51506000000 | C12: 60932000000 | D12: 60985000000 | E12: 66243000000 | F12: 72957000000 | I12: =A12 -> Trade and Other Receivables, Current | J12: =B12 -> 51506000000 | K12: =C12 -> 60932000000 | L12: =D12 -> 60985000000 | M12: =E12 -> 66243000000 | N12: =F12 -> 72957000000
A13: Trade/Accounts Receivable, Current | B13: 26278000000 | C13: 28184000000 | D13: 29508000000 | E13: 33410000000 | F13: 39777000000 | I13: =A13 -> Trade/Accounts Receivable, Current | J13: =B13 -> 26278000000 | K13: =C13 -> 28184000000 | L13: =D13 -> 29508000000 | M13: =E13 -> 33410000000 | N13: =F13 -> 39777000000
A14: Gross Trade/Accounts Receivable, Current | I14: =A14 -> Gross Trade/Accounts Receivable, Current | J14: =B14 | K14: =C14 | L14: =D14 | M14: =E14 | N14: =F14
A15: Allowance/Adjustments for Trade/Accounts Receivable, Current | I15: =A15 -> Allowance/Adjustments for Trade/Accounts Receivable, Current | J15: =B15 | K15: =C15 | L15: =D15 | M15: =E15 | N15: =F15
A16: Other Receivables, Current | B16: 25228000000 | C16: 32748000000 | D16: 31477000000 | E16: 32833000000 | F16: 33180000000 | I16: =A16 -> Other Receivables, Current | J16: =B16 -> 25228000000 | K16: =C16 -> 32748000000 | L16: =D16 -> 31477000000 | M16: =E16 -> 32833000000 | N16: =F16 -> 33180000000
A17: Other Current Assets | B17: 14111000000 | C17: 21223000000 | D17: 14695000000 | E17: 14287000000 | F17: 14585000000 | I17: =A17 -> Other Current Assets | J17: =B17 -> 14111000000 | K17: =C17 -> 21223000000 | L17: =D17 -> 14695000000 | M17: =E17 -> 14287000000 | N17: =F17 -> 14585000000
A18: Total Non-Current Assets | B18: 216166000000 | C18: 217350000000 | D18: 209017000000 | E18: 211993000000 | F18: 211284000000 | I18: =A18 -> Total Non-Current Assets | J18: =B18 -> 216166000000 | K18: =C18 -> 217350000000 | L18: =D18 -> 209017000000 | M18: =E18 -> 211993000000 | N18: =F18 -> 211284000000
A19: Net Property, Plant and Equipment | B19: 49527000000 | C19: 52534000000 | D19: 43715000000 | E19: 45680000000 | F19: 49834000000 | I19: =A19 -> Net Property, Plant and Equipment | J19: =B19 -> 49527000000 | K19: =C19 -> 52534000000 | L19: =D19 -> 43715000000 | M19: =E19 -> 45680000000 | N19: =F19 -> 49834000000
A20: Gross Property, Plant and Equipment | B20: 119810000000 | C20: 124874000000 | D20: 114599000000 | E20: 119128000000 | F20: 125848000000 | I20: =A20 -> Gross Property, Plant and Equipment | J20: =B20 -> 119810000000 | K20: =C20 -> 124874000000 | L20: =D20 -> 114599000000 | M20: =E20 -> 119128000000 | N20: =F20 -> 125848000000
A21: Properties | B21: 31064000000 | C21: 33397000000 | D21: 36285000000 | E21: 38923000000 | F21: 42428000000 | I21: =A21 -> Properties | J21: =B21 -> 31064000000 | K21: =C21 -> 33397000000 | L21: =D21 -> 36285000000 | M21: =E21 -> 38923000000 | N21: =F21 -> 42428000000
A22: Land and Improvements | B22: 20041000000 | C22: 22126000000 | D22: 23446000000 | E22: 24690000000 | F22: 27337000000 | I22: =A22 -> Land and Improvements | J22: =B22 -> 20041000000 | K22: =C22 -> 22126000000 | L22: =D22 -> 23446000000 | M22: =E22 -> 24690000000 | N22: =F22 -> 27337000000
A23: Leasehold and Improvements | B23: 11023000000 | C23: 11271000000 | D23: 12839000000 | E23: 14233000000 | F23: 15091000000 | I23: =A23 -> Leasehold and Improvements | J23: =B23 -> 11023000000 | K23: =C23 -> 11271000000 | L23: =D23 -> 12839000000 | M23: =E23 -> 14233000000 | N23: =F23 -> 15091000000
A24: Machinery, Furniture and Equipment | B24: 78659000000 | C24: 81060000000 | D24: 78314000000 | E24: 80205000000 | F24: 83420000000 | I24: =A24 -> Machinery, Furniture and Equipment | J24: =B24 -> 78659000000 | K24: =C24 -> 81060000000 | L24: =D24 -> 78314000000 | M24: =E24 -> 80205000000 | N24: =F24 -> 83420000000
A25: Plant and Machinery | B25: 78659000000 | C25: 81060000000 | D25: 78314000000 | E25: 80205000000 | F25: 83420000000 | I25: =A25 -> Plant and Machinery | J25: =B25 -> 78659000000 | K25: =C25 -> 81060000000 | L25: =D25 -> 78314000000 | M25: =E25 -> 80205000000 | N25: =F25 -> 83420000000
A26: Leased Property, Plant and Equipment | B26: 10087000000 | C26: 10417000000 | I26: =A26 -> Leased Property, Plant and Equipment | J26: =B26 -> 10087000000 | K26: =C26 -> 10417000000 | L26: =D26 | M26: =E26 | N26: =F26
A27: Accumulated Depreciation and Impairment | B27: -70283000000 | C27: -72340000000 | D27: -70884000000 | E27: -73448000000 | F27: -76014000000 | I27: =A27 -> Accumulated Depreciation and Impairment | J27: =B27 -> -70283000000 | K27: =C27 -> -72340000000 | L27: =D27 -> -70884000000 | M27: =E27 -> -73448000000 | N27: =F27 -> -76014000000
A28: Accumulated Depreciation | B28: -70283000000 | C28: -72340000000 | D28: -70884000000 | E28: -73448000000 | F28: -76014000000 | I28: =A28 -> Accumulated Depreciation | J28: =B28 -> -70283000000 | K28: =C28 -> -72340000000 | L28: =D28 -> -70884000000 | M28: =E28 -> -73448000000 | N28: =F28 -> -76014000000
A29: Total Long Term Investments | B29: 127877000000 | C29: 120805000000 | D29: 100544000000 | E29: 91479000000 | F29: 77723000000 | I29: =A29 -> Total Long Term Investments | J29: =B29 -> 127877000000 | K29: =C29 -> 120805000000 | L29: =D29 -> 100544000000 | M29: =E29 -> 91479000000 | N29: =F29 -> 77723000000
A30: Investment in Financial Assets, Non-Current | C30: 120805000000 | D30: 100544000000 | E30: 91479000000 | F30: 77723000000 | I30: =A30 -> Investment in Financial Assets, Non-Current | J30: =B30 | K30: =C30 -> 120805000000 | L30: =D30 -> 100544000000 | M30: =E30 -> 91479000000 | N30: =F30 -> 77723000000
A31: Other Financial Assets, Non-Current | C31: 120805000000 | E31: 91479000000 | F31: 77723000000 | I31: =A31 -> Other Financial Assets, Non-Current | J31: =B31 | K31: =C31 -> 120805000000 | L31: =D31 | M31: =E31 -> 91479000000 | N31: =F31 -> 77723000000
A32: Financial Investment Securities, Available-for-Sale & Held-to-Maturity, Non-Current | D32: 100544000000 | I32: =A32 -> Financial Investment Securities, Available-for-Sale & Held-to-Maturity, Non-Current | J32: =B32 | K32: =C32 | L32: =D32 -> 100544000000 | M32: =E32 | N32: =F32
A33: Available-for-Sale Securities, Non-Current | D33: 100544000000 | I33: =A33 -> Available-for-Sale Securities, Non-Current | J33: =B33 | K33: =C33 | L33: =D33 -> 100544000000 | M33: =E33 | N33: =F33
A34: Other Investments, Non-Current | B34: 127877000000 | I34: =A34 -> Other Investments, Non-Current | J34: =B34 -> 127877000000 | K34: =C34 | L34: =D34 | M34: =E34 | N34: =F34
A35: Deferred Tax Assets, Non-Current | D35: 17852000000 | E35: 19499000000 | F35: 20777000000 | I35: =A35 -> Deferred Tax Assets, Non-Current | J35: =B35 | K35: =C35 | L35: =D35 -> 17852000000 | M35: =E35 -> 19499000000 | N35: =F35 -> 20777000000
A36: Other Non-Current Assets | B36: 38762000000 | C36: 44011000000 | D36: 46906000000 | E36: 55335000000 | F36: 62950000000 | I36: =A36 -> Other Non-Current Assets | J36: =B36 -> 38762000000 | K36: =C36 -> 44011000000 | L36: =D36 -> 46906000000 | M36: =E36 -> 55335000000 | N36: =F36 -> 62950000000
A37: Net Intangible Assets | I37: =A37 -> Net Intangible Assets | J37: =B37 | K37: =C37 | L37: =D37 | M37: =E37 | N37: =F37
A38: Gross Goodwill and Other Intangible Assets | I38: =A38 -> Gross Goodwill and Other Intangible Assets | J38: =B38 | K38: =C38 | L38: =D38 | M38: =E38 | N38: =F38
A39: Goodwill | I39: =A39 -> Goodwill | J39: =B39 | K39: =C39 | L39: =D39 | M39: =E39 | N39: =F39
A40: Intangibles other than Goodwill | I40: =A40 -> Intangibles other than Goodwill | J40: =B40 | K40: =C40 | L40: =D40 | M40: =E40 | N40: =F40
A41: Trademarks and Patents | I41: =A41 -> Trademarks and Patents | J41: =B41 | K41: =C41 | L41: =D41 | M41: =E41 | N41: =F41
A42: Other Intangible Assets | I42: =A42 -> Other Intangible Assets | J42: =B42 | K42: =C42 | L42: =D42 | M42: =E42 | N42: =F42
A43: Accumulated Amortization and Impairment | I43: =A43 -> Accumulated Amortization and Impairment | J43: =B43 | K43: =C43 | L43: =D43 | M43: =E43 | N43: =F43
A44: Accumulated Amortization of Intangible Assets | I44: =A44 -> Accumulated Amortization of Intangible Assets | J44: =B44 | K44: =C44 | L44: =D44 | M44: =E44 | N44: =F44
A45: Accumulated Amortization of Intangibles other than Goodwill | I45: =A45 -> Accumulated Amortization of Intangibles other than Goodwill | J45: =B45 | K45: =C45 | L45: =D45 | M45: =E45 | N45: =F45
A46: Accumulated Amortization of Other Intangible Assets | I46: =A46 -> Accumulated Amortization of Other Intangible Assets | J46: =B46 | K46: =C46 | L46: =D46 | M46: =E46 | N46: =F46
A47: Total Liabilities | B47: 287912000000 | C47: 302083000000 | D47: 290437000000 | E47: 308030000000 | F47: 285508000000 | I47: =A47 -> Total Liabilities | J47: =B47 -> 287912000000 | K47: =C47 -> 302083000000 | L47: =D47 -> 290437000000 | M47: =E47 -> 308030000000 | N47: =F47 -> 285508000000
A48: Total Current Liabilities | B48: 125481000000 | C48: 153982000000 | D48: 145308000000 | E48: 176392000000 | F48: 165631000000 | I48: =A48 -> Total Current Liabilities | J48: =B48 -> 125481000000 | K48: =C48 -> 153982000000 | L48: =D48 -> 145308000000 | M48: =E48 -> 176392000000 | N48: =F48 -> 165631000000
A49: Payables and Accrued Expenses, Current | B49: 54763000000 | C49: 64115000000 | D49: 71430000000 | E49: 95561000000 | F49: 91795000000 | I49: =A49 -> Payables and Accrued Expenses, Current | J49: =B49 -> 54763000000 | K49: =C49 -> 64115000000 | L49: =D49 -> 71430000000 | M49: =E49 -> 95561000000 | N49: =F49 -> 91795000000
A50: Trade and Other Payables, Current | B50: 54763000000 | C50: 64115000000 | D50: 71430000000 | E50: 95561000000 | F50: 82876000000 | I50: =A50 -> Trade and Other Payables, Current | J50: =B50 -> 54763000000 | K50: =C50 -> 64115000000 | L50: =D50 -> 71430000000 | M50: =E50 -> 95561000000 | N50: =F50 -> 82876000000
A51: Trade/Accounts Payable, Current | B51: 54763000000 | C51: 64115000000 | D51: 62611000000 | E51: 68960000000 | F51: 69860000000 | I51: =A51 -> Trade/Accounts Payable, Current | J51: =B51 -> 54763000000 | K51: =C51 -> 64115000000 | L51: =D51 -> 62611000000 | M51: =E51 -> 68960000000 | N51: =F51 -> 69860000000
A52: Taxes Payable, Current | D52: 8819000000 | E52: 26601000000 | F52: 13016000000 | I52: =A52 -> Taxes Payable, Current | J52: =B52 | K52: =C52 | L52: =D52 -> 8819000000 | M52: =E52 -> 26601000000 | N52: =F52 -> 13016000000
A53: Accrued Expenses, Current | F53: 8919000000 | I53: =A53 -> Accrued Expenses, Current | J53: =B53 | K53: =C53 | L53: =D53 | M53: =E53 | N53: =F53 -> 8919000000
A54: Financial Liabilities, Current | B54: 17141000000 | C54: 22773000000 | D54: 17382000000 | E54: 20879000000 | F54: 20329000000 | I54: =A54 -> Financial Liabilities, Current | J54: =B54 -> 17141000000 | K54: =C54 -> 22773000000 | L54: =D54 -> 17382000000 | M54: =E54 -> 20879000000 | N54: =F54 -> 20329000000
A55: Current Debt and Capital Lease Obligation | B55: 17141000000 | C55: 22773000000 | D55: 17382000000 | E55: 20879000000 | F55: 20329000000 | I55: =A55 -> Current Debt and Capital Lease Obligation | J55: =B55 -> 17141000000 | K55: =C55 -> 22773000000 | L55: =D55 -> 17382000000 | M55: =E55 -> 20879000000 | N55: =F55 -> 20329000000
A56: Current Debt | B56: 6000000000 | C56: 9982000000 | D56: 5985000000 | E56: 9967000000 | F56: 7979000000 | I56: =A56 -> Current Debt | J56: =B56 -> 6000000000 | K56: =C56 -> 9982000000 | L56: =D56 -> 5985000000 | M56: =E56 -> 9967000000 | N56: =F56 -> 7979000000
A57: Commercial Paper | B57: 6000000000 | C57: 9982000000 | D57: 5985000000 | E57: 9967000000 | F57: 7979000000 | I57: =A57 -> Commercial Paper | J57: =B57 -> 6000000000 | K57: =C57 -> 9982000000 | L57: =D57 -> 5985000000 | M57: =E57 -> 9967000000 | N57: =F57 -> 7979000000
A58: Current Portion of Long Term Debt and Capital Lease | B58: 11141000000 | C58: 12791000000 | D58: 11397000000 | E58: 10912000000 | F58: 12350000000 | I58: =A58 -> Current Portion of Long Term Debt and Capital Lease | J58: =B58 -> 11141000000 | K58: =C58 -> 12791000000 | L58: =D58 -> 11397000000 | M58: =E58 -> 10912000000 | N58: =F58 -> 12350000000
A59: Current Portion of Long Term Debt | B59: 9613000000 | C59: 11128000000 | D59: 9822000000 | E59: 10912000000 | F59: 12350000000 | I59: =A59 -> Current Portion of Long Term Debt | J59: =B59 -> 9613000000 | K59: =C59 -> 11128000000 | L59: =D59 -> 9822000000 | M59: =E59 -> 10912000000 | N59: =F59 -> 12350000000
A60: Other Current Portion of LT Debt | B60: 9613000000 | C60: 11128000000 | D60: 9822000000 | E60: 10912000000 | F60: 12350000000 | I60: =A60 -> Other Current Portion of LT Debt | J60: =B60 -> 9613000000 | K60: =C60 -> 11128000000 | L60: =D60 -> 9822000000 | M60: =E60 -> 10912000000 | N60: =F60 -> 12350000000
A61: Bank/Institutional Loans, Current Portion of LT Debt | I61: =A61 -> Bank/Institutional Loans, Current Portion of LT Debt | J61: =B61 | K61: =C61 | L61: =D61 | M61: =E61 | N61: =F61
A62: Capital Lease Obligations, Current | B62: 1528000000 | C62: 1663000000 | D62: 1575000000 | I62: =A62 -> Capital Lease Obligations, Current | J62: =B62 -> 1528000000 | K62: =C62 -> 1663000000 | L62: =D62 -> 1575000000 | M62: =E62 | N62: =F62
A63: Deferred Liabilities, Current | B63: 7612000000 | C63: 7912000000 | D63: 8061000000 | E63: 8249000000 | F63: 9055000000 | I63: =A63 -> Deferred Liabilities, Current | J63: =B63 -> 7612000000 | K63: =C63 -> 7912000000 | L63: =D63 -> 8061000000 | M63: =E63 -> 8249000000 | N63: =F63 -> 9055000000
A64: Deferred Income/Customer Advances/Billings in Excess of Cost, Current | B64: 7612000000 | C64: 7912000000 | D64: 8061000000 | E64: 8249000000 | F64: 9055000000 | I64: =A64 -> Deferred Income/Customer Advances/Billings in Excess of Cost, Current | J64: =B64 -> 7612000000 | K64: =C64 -> 7912000000 | L64: =D64 -> 8061000000 | M64: =E64 -> 8249000000 | N64: =F64 -> 9055000000
A65: Other Current Liabilities | B65: 45965000000 | C65: 59182000000 | D65: 48435000000 | E65: 51703000000 | F65: 44452000000 | I65: =A65 -> Other Current Liabilities | J65: =B65 -> 45965000000 | K65: =C65 -> 59182000000 | L65: =D65 -> 48435000000 | M65: =E65 -> 51703000000 | N65: =F65 -> 44452000000
A66: Total Non-Current Liabilities | B66: 162431000000 | C66: 148101000000 | D66: 145129000000 | E66: 131638000000 | F66: 119877000000 | I66: =A66 -> Total Non-Current Liabilities | J66: =B66 -> 162431000000 | K66: =C66 -> 148101000000 | L66: =D66 -> 145129000000 | M66: =E66 -> 131638000000 | N66: =F66 -> 119877000000
A67: Financial Liabilities, Non-Current | B67: 119381000000 | C67: 109707000000 | D67: 106548000000 | E67: 85750000000 | F67: 78328000000 | I67: =A67 -> Financial Liabilities, Non-Current | J67: =B67 -> 119381000000 | K67: =C67 -> 109707000000 | L67: =D67 -> 106548000000 | M67: =E67 -> 85750000000 | N67: =F67 -> 78328000000
A68: Long Term Debt and Capital Lease Obligation | B68: 119381000000 | C68: 109707000000 | D68: 106548000000 | E68: 85750000000 | F68: 78328000000 | I68: =A68 -> Long Term Debt and Capital Lease Obligation | J68: =B68 -> 119381000000 | K68: =C68 -> 109707000000 | L68: =D68 -> 106548000000 | M68: =E68 -> 85750000000 | N68: =F68 -> 78328000000
A69: Long Term Debt | B69: 109106000000 | C69: 98959000000 | D69: 95281000000 | E69: 85750000000 | F69: 78328000000 | I69: =A69 -> Long Term Debt | J69: =B69 -> 109106000000 | K69: =C69 -> 98959000000 | L69: =D69 -> 95281000000 | M69: =E69 -> 85750000000 | N69: =F69 -> 78328000000
A70: Notes Payables, Non-Current | B70: 109106000000 | C70: 98959000000 | D70: 95281000000 | E70: 85750000000 | F70: 78328000000 | I70: =A70 -> Notes Payables, Non-Current | J70: =B70 -> 109106000000 | K70: =C70 -> 98959000000 | L70: =D70 -> 95281000000 | M70: =E70 -> 85750000000 | N70: =F70 -> 78328000000
A71: Bank/Institutional Loans, Non-Current | I71: =A71 -> Bank/Institutional Loans, Non-Current | J71: =B71 | K71: =C71 | L71: =D71 | M71: =E71 | N71: =F71
A72: Capital Lease Obligations, Non-Current | B72: 10275000000 | C72: 10748000000 | D72: 11267000000 | I72: =A72 -> Capital Lease Obligations, Non-Current | J72: =B72 -> 10275000000 | K72: =C72 -> 10748000000 | L72: =D72 -> 11267000000 | M72: =E72 | N72: =F72
A73: Other Non-Current Liabilities | B73: 18361000000 | C73: 21737000000 | D73: 23124000000 | E73: 36634000000 | F73: 41549000000 | I73: =A73 -> Other Non-Current Liabilities | J73: =B73 -> 18361000000 | K73: =C73 -> 21737000000 | L73: =D73 -> 23124000000 | M73: =E73 -> 36634000000 | N73: =F73 -> 41549000000
A74: Payables and Accrued Expenses, Non-Current | B74: 24689000000 | C74: 16657000000 | D74: 15457000000 | E74: 9254000000 | I74: =A74 -> Payables and Accrued Expenses, Non-Current | J74: =B74 -> 24689000000 | K74: =C74 -> 16657000000 | L74: =D74 -> 15457000000 | M74: =E74 -> 9254000000 | N74: =F74
A75: Trade and Other Payables, Non-Current | B75: 24689000000 | C75: 16657000000 | D75: 15457000000 | E75: 9254000000 | I75: =A75 -> Trade and Other Payables, Non-Current | J75: =B75 -> 24689000000 | K75: =C75 -> 16657000000 | L75: =D75 -> 15457000000 | M75: =E75 -> 9254000000 | N75: =F75
A76: Taxes Payable, Non-Current | B76: 24689000000 | C76: 16657000000 | D76: 15457000000 | E76: 9254000000 | I76: =A76 -> Taxes Payable, Non-Current | J76: =B76 -> 24689000000 | K76: =C76 -> 16657000000 | L76: =D76 -> 15457000000 | M76: =E76 -> 9254000000 | N76: =F76
A77: Tax Liabilities, Non-Current | I77: =A77 -> Tax Liabilities, Non-Current | J77: =B77 | K77: =C77 | L77: =D77 | M77: =E77 | N77: =F77
A78: Deferred Tax Liabilities, Non-Current | I78: =A78 -> Deferred Tax Liabilities, Non-Current | J78: =B78 | K78: =C78 | L78: =D78 | M78: =E78 | N78: =F78
A79: Deferred Liabilities, Non-Current | I79: =A79 -> Deferred Liabilities, Non-Current | J79: =B79 | K79: =C79 | L79: =D79 | M79: =E79 | N79: =F79
A80: Deferred Income/Customer Advances/Billings in Excess of Cost, Non-Current | I80: =A80 -> Deferred Income/Customer Advances/Billings in Excess of Cost, Non-Current | J80: =B80 | K80: =C80 | L80: =D80 | M80: =E80 | N80: =F80
A81: Total Equity | B81: 63090000000 | C81: 50672000000 | D81: 62146000000 | E81: 56950000000 | F81: 73733000000 | I81: =A81 -> Total Equity | J81: =B81 -> 63090000000 | K81: =C81 -> 50672000000 | L81: =D81 -> 62146000000 | M81: =E81 -> 56950000000 | N81: =F81 -> 73733000000
A82: Equity Attributable to Parent Stockholders | B82: 63090000000 | C82: 50672000000 | D82: 62146000000 | E82: 56950000000 | F82: 73733000000 | I82: =A82 -> Equity Attributable to Parent Stockholders | J82: =B82 -> 63090000000 | K82: =C82 -> 50672000000 | L82: =D82 -> 62146000000 | M82: =E82 -> 56950000000 | N82: =F82 -> 73733000000
A83: Paid in Capital | B83: 57365000000 | C83: 64849000000 | D83: 73812000000 | E83: 83276000000 | F83: 93568000000 | I83: =A83 -> Paid in Capital | J83: =B83 -> 57365000000 | K83: =C83 -> 64849000000 | L83: =D83 -> 73812000000 | M83: =E83 -> 83276000000 | N83: =F83 -> 93568000000
A84: Capital Stock | B84: 57365000000 | C84: 64849000000 | D84: 73812000000 | E84: 83276000000 | F84: 93568000000 | I84: =A84 -> Capital Stock | J84: =B84 -> 57365000000 | K84: =C84 -> 64849000000 | L84: =D84 -> 73812000000 | M84: =E84 -> 83276000000 | N84: =F84 -> 93568000000
A85: Retained Earnings/Accumulated Deficit | B85: 5562000000 | C85: -3068000000 | D85: -214000000 | E85: -19154000000 | F85: -14264000000 | I85: =A85 -> Retained Earnings/Accumulated Deficit | J85: =B85 -> 5562000000 | K85: =C85 -> -3068000000 | L85: =D85 -> -214000000 | M85: =E85 -> -19154000000 | N85: =F85 -> -14264000000
A86: Reserves/Accumulated Comprehensive Income/Losses | B86: 163000000 | C86: -11109000000 | D86: -11452000000 | E86: -7172000000 | F86: -5571000000 | I86: =A86 -> Reserves/Accumulated Comprehensive Income/Losses | J86: =B86 -> 163000000 | K86: =C86 -> -11109000000 | L86: =D86 -> -11452000000 | M86: =E86 -> -7172000000 | N86: =F86 -> -5571000000
A87: Other Reserves/Accum.Comp.Inc | B87: 163000000 | C87: -11109000000 | D87: -11452000000 | E87: -7172000000 | F87: -5571000000 | I87: =A87 -> Other Reserves/Accum.Comp.Inc | J87: =B87 -> 163000000 | K87: =C87 -> -11109000000 | L87: =D87 -> -11452000000 | M87: =E87 -> -7172000000 | N87: =F87 -> -5571000000
A88: Debt Maturity Schedule Total | B88: 124719000000 | C88: 120069000000 | D88: 111088000000 | E88: 106629000000 | F88: 98657000000 | I88: =A88 -> Debt Maturity Schedule Total | J88: =B88 -> 124719000000 | K88: =C88 -> 120069000000 | L88: =D88 -> 111088000000 | M88: =E88 -> 106629000000 | N88: =F88 -> 98657000000
A89: Debt due in Year 1 | B89: 15583000000 | C89: 21121000000 | D89: 15928000000 | E89: 20897000000 | F89: 20372000000 | I89: =A89 -> Debt due in Year 1 | J89: =B89 -> 15583000000 | K89: =C89 -> 21121000000 | L89: =D89 -> 15928000000 | M89: =E89 -> 20897000000 | N89: =F89 -> 20372000000
A90: Debt due in Year 2 | B90: 11391000000 | C90: 9910000000 | D90: 10775000000 | E90: 12342000000 | F90: 10078000000 | I90: =A90 -> Debt due in Year 2 | J90: =B90 -> 11391000000 | K90: =C90 -> 9910000000 | L90: =D90 -> 10775000000 | M90: =E90 -> 12342000000 | N90: =F90 -> 10078000000
A91: Debt due in Year 3 | B91: 10202000000 | C91: 10645000000 | D91: 12265000000 | E91: 9936000000 | F91: 9300000000 | I91: =A91 -> Debt due in Year 3 | J91: =B91 -> 10202000000 | K91: =C91 -> 10645000000 | L91: =D91 -> 12265000000 | M91: =E91 -> 9936000000 | N91: =F91 -> 9300000000
A92: Debt due in Year 4 | B92: 10914000000 | C92: 11209000000 | D92: 9786000000 | E92: 7800000000 | F92: 5235000000 | I92: =A92 -> Debt due in Year 4 | J92: =B92 -> 10914000000 | K92: =C92 -> 11209000000 | L92: =D92 -> 9786000000 | M92: =E92 -> 7800000000 | N92: =F92 -> 5235000000
... A127: Total Contractual Obligations - Interests Charges and Other Adjustments | B127: -994000000 | C127: -3462000000 | D127: -3893000000 | E127: -3039000000 | F127: -3187000000 | I127: =A127 -> Total Contractual Obligations - Interests Charges and Other Adjustments | J127: =B127 -> -994000000 | K127: =C127 -> -3462000000 | L127: =D127 -> -3893000000 | M127: =E127 -> -3039000000 | N127: =F127 -> -3187000000
A128: Other Contractual Obligations Maturity Schedule Total | I128: =A128 -> Other Contractual Obligations Maturity Schedule Total | J128: =B128 | K128: =C128 | L128: =D128 | M128: =E128 | N128: =F128
A129: Other Contractual Obligations due in Year 1 | I129: =A129 -> Other Contractual Obligations due in Year 1 | J129: =B129 | K129: =C129 | L129: =D129 | M129: =E129 | N129: =F129
A130: Other Contractual Obligations due in Year 3 | I130: =A130 -> Other Contractual Obligations due in Year 3 | J130: =B130 | K130: =C130 | L130: =D130 | M130: =E130 | N130: =F130
A131: Other Contractual Obligations due in Year 5 | I131: =A131 -> Other Contractual Obligations due in Year 5 | J131: =B131 | K131: =C131 | L131: =D131 | M131: =E131 | N131: =F131
A132: Other Contractual Obligations due Beyond | I132: =A132 -> Other Contractual Obligations due Beyond | J132: =B132 | K132: =C132 | L132: =D132 | M132: =E132 | N132: =F132
A133: Fiscal year ends in Sep 30 | USD | I133: =A133 -> Fiscal year ends in Sep 30 | USD | J133: =B133 -> 0 | K133: =C133 -> 0 | L133: =D133 -> 0 | M133: =E133 -> 0 | N133: =F133 -> 0

Sheet Financial Summary
B1: Financial Summary & Key Ratios
B2: Formulas auto-calculated from Balance Sheet, Income Statement, and Cash Flow tabs | Green text = cross-sheet link
B4: USD ($000s) | C4: FY2021 | D4: FY2022 | E4: FY2023 | F4: FY2024 | G4: FY2025
B6: INCOME STATEMENT HIGHLIGHTS
B7: Total Revenue ($000s) | C7: ='Income Statement'!C10 -> 365817000000 | D7: ='Income Statement'!D10 -> 394328000000 | E7: ='Income Statement'!E10 -> 383285000000 | F7: ='Income Statement'!F10 -> 391035000000 | G7: ='Income Statement'!G10 -> 416161000000
B8: Gross Profit ($000s) | C8: ='Income Statement'!C21 -> 152836000000 | D8: ='Income Statement'!D21 -> 170782000000 | E8: ='Income Statement'!E21 -> 169148000000 | F8: ='Income Statement'!F21 -> 180683000000 | G8: ='Income Statement'!G21 -> 195201000000
B9: EBITDA ($000s) | C9: ='Income Statement'!C56 -> 108949000000 | D9: ='Income Statement'!D56 -> 119437000000 | E9: ='Income Statement'!E56 -> 114301000000 | F9: ='Income Statement'!F56 -> 123216000000 | G9: ='Income Statement'!G56 -> 133050000000
B10: EBIT / Operating Income ($000s) | C10: ='Income Statement'!C34 -> 108949000000 | D10: ='Income Statement'!D34 -> 119437000000 | E10: ='Income Statement'!E34 -> 114301000000 | F10: ='Income Statement'!F34 -> 123216000000 | G10: ='Income Statement'!G34 -> 133050000000
B11: Net Income ($000s) | C11: ='Income Statement'!C49 -> 94680000000 | D11: ='Income Statement'!D49 -> 99803000000 | E11: ='Income Statement'!E49 -> 96995000000 | F11: ='Income Statement'!F49 -> 93736000000 | G11: ='Income Statement'!G49 -> 112010000000
B13: BALANCE SHEET HIGHLIGHTS
B14: Total Current Assets ($000s) | C14: ='Balance Sheet'!C14 -> 134836000000 | D14: ='Balance Sheet'!D14 -> 135405000000 | E14: ='Balance Sheet'!E14 -> 143566000000 | F14: ='Balance Sheet'!F14 -> 152987000000 | G14: ='Balance Sheet'!G14 -> 147957000000
B15: Total Assets ($000s) | C15: ='Balance Sheet'!C27 -> 351002000000 | D15: ='Balance Sheet'!D27 -> 352755000000 | E15: ='Balance Sheet'!E27 -> 352583000000 | F15: ='Balance Sheet'!F27 -> 364980000000 | G15: ='Balance Sheet'!G27 -> 359241000000
B16: Total Current Liabilities ($000s) | C16: ='Balance Sheet'!C36 -> 125481000000 | D16: ='Balance Sheet'!D36 -> 153982000000 | E16: ='Balance Sheet'!E36 -> 145308000000 | F16: ='Balance Sheet'!F36 -> 176392000000 | G16: ='Balance Sheet'!G36 -> 165631000000
B17: Total Liabilities ($000s) | C17: ='Balance Sheet'!C45 -> 287912000000 | D17: ='Balance Sheet'!D45 -> 302083000000 | E17: ='Balance Sheet'!E45 -> 290437000000 | F17: ='Balance Sheet'!F45 -> 308030000000 | G17: ='Balance Sheet'!G45 -> 285508000000
B18: Total Shareholders' Equity ($000s) | C18: ='Balance Sheet'!C53 -> 63090000000 | D18: ='Balance Sheet'!D53 -> 50672000000 | E18: ='Balance Sheet'!E53 -> 62146000000 | F18: ='Balance Sheet'!F53 -> 56950000000 | G18: ='Balance Sheet'!G53 -> 73733000000
B20: CASH FLOW HIGHLIGHTS
B21: Operating Cash Flow (CFO) ($000s) | C21: ='Cash Flow Statement'!C22 -> 104038000000 | D21: ='Cash Flow Statement'!D22 -> 122151000000 | E21: ='Cash Flow Statement'!E22 -> 110543000000 | F21: ='Cash Flow Statement'!F22 -> 118254000000 | G21: ='Cash Flow Statement'!G22 -> 111482000000
B22: Capital Expenditures ($000s) | C22: ='Cash Flow Statement'!C52 -> -11085000000 | D22: ='Cash Flow Statement'!D52 -> -10708000000 | E22: ='Cash Flow Statement'!E52 -> -10959000000 | F22: ='Cash Flow Statement'!F52 -> -9447000000 | G22: ='Cash Flow Statement'!G52 -> -12715000000
B23: Free Cash Flow (FCF) ($000s) | C23: ='Cash Flow Statement'!C53 -> 92953000000 | D23: ='Cash Flow Statement'!D53 -> 111443000000 | E23: ='Cash Flow Statement'!E53 -> 99584000000 | F23: ='Cash Flow Statement'!F53 -> 108807000000 | G23: ='Cash Flow Statement'!G53 -> 98767000000
B25: KEY FINANCIAL RATIOS
B26: Liquidity Ratios
B27: Current Ratio | C27: =IFERROR(C14/C16,"-") -> 1.0745531 | D27: =IFERROR(D14/D16,"-") -> 0.87935603 | E27: =IFERROR(E14/E16,"-") -> 0.98801167 | F27: =IFERROR(F14/F16,"-") -> 0.86731258 | G27: =IFERROR(G14/G16,"-") -> 0.89329292
B28: Quick Ratio (approx. ex-Inventory) | C28: =IFERROR((C14-'Balance Sheet'!C12)/C16,"-") -> 1.0221149 | D28: =IFERROR((D14-'Balance Sheet'!D12)/D16,"-") -> 0.84723539 | E28: =IFERROR((E14-'Balance Sheet'!E12)/E16,"-") -> 0.94444215 | F28: =IFERROR((F14-'Balance Sheet'!F12)/F16,"-") -> 0.82600685 | G28: =IFERROR((G14-'Balance Sheet'!G12)/G16,"-") -> 0.8587704
B29: Cash Ratio | C29: =IFERROR('Balance Sheet'!C8/C16,"-") -> 0.27844853 | D29: =IFERROR('Balance Sheet'!D8/D16,"-") -> 0.1535634 | E29: =IFERROR('Balance Sheet'!E8/E16,"-") -> 0.20621714 | F29: =IFERROR('Balance Sheet'!F8/F16,"-") -> 0.1697526 | G29: =IFERROR('Balance Sheet'!G8/G16,"-") -> 0.21695214
B31: Leverage & Solvency Ratios
B32: Debt-to-Equity (Total Liabilities / Equity) | C32: =IFERROR(C17/C18,"-") -> 4.5635124 | D32: =IFERROR(D17/D18,"-") -> 5.9615369 | E32: =IFERROR(E17/E18,"-") -> 4.6734625 | F32: =IFERROR(F17/F18,"-") -> 5.4087796 | G32: =IFERROR(G17/G18,"-") -> 3.8721875
B33: Total Debt-to-Assets (Total Liabilities / Total Assets) | C33: =IFERROR(C17/C15,"-") -> 0.82025743 | D33: =IFERROR(D17/D15,"-") -> 0.85635356 | E33: =IFERROR(E17/E15,"-") -> 0.82374079 | F33: =IFERROR(F17/F15,"-") -> 0.84396405 | G33: =IFERROR(G17/G15,"-") -> 0.79475338
B34: Equity Multiplier (Total Assets / Equity) | C34: =IFERROR(C15/C18,"-") -> 5.5635124 | D34: =IFERROR(D15/D18,"-") -> 6.9615369 | E34: =IFERROR(E15/E18,"-") -> 5.6734625 | F34: =IFERROR(F15/F18,"-") -> 6.4087796 | G34: =IFERROR(G15/G18,"-") -> 4.8721875
B35: Net Debt (Total Liabilities – Current Assets) | C35: =C17-C14 -> 153076000000 | D35: =D17-D14 -> 166678000000 | E35: =E17-E14 -> 146871000000 | F35: =F17-F14 -> 155043000000 | G35: =G17-G14 -> 137551000000
B36: Net Debt / EBITDA | C36: =IFERROR((C17-C14)/C9,"-") -> 1.4050244 | D36: =IFERROR((D17-D14)/D9,"-") -> 1.3955307 | E36: =IFERROR((E17-E14)/E9,"-") -> 1.2849494 | F36: =IFERROR((F17-F14)/F9,"-") -> 1.2583025 | G36: =IFERROR((G17-G14)/G9,"-") -> 1.0338294
B38: Profitability Margins
B39: Gross Margin | C39: =IFERROR(C8/C7,"-") -> 0.4177936 | D39: =IFERROR(D8/D7,"-") -> 0.43309631 | E39: =IFERROR(E8/E7,"-") -> 0.4413113 | F39: =IFERROR(F8/F7,"-") -> 0.4620635 | G39: =IFERROR(G8/G7,"-") -> 0.46905164
B40: EBITDA Margin | C40: =IFERROR(C9/C7,"-") -> 0.29782378 | D40: =IFERROR(D9/D7,"-") -> 0.30288744 | E40: =IFERROR(E9/E7,"-") -> 0.29821412 | F40: =IFERROR(F9/F7,"-") -> 0.31510223 | G40: =IFERROR(G9/G7,"-") -> 0.319708
B41: EBIT Margin (Operating Margin) | C41: =IFERROR(C10/C7,"-") -> 0.29782378 | D41: =IFERROR(D10/D7,"-") -> 0.30288744 | E41: =IFERROR(E10/E7,"-") -> 0.29821412 | F41: =IFERROR(F10/F7,"-") -> 0.31510223 | G41: =IFERROR(G10/G7,"-") -> 0.319708
B42: Net Profit Margin | C42: =IFERROR(C11/C7,"-") -> 0.25881793 | D42: =IFERROR(D11/D7,"-") -> 0.25309641 | E42: =IFERROR(E11/E7,"-") -> 0.25306234 | F42: =IFERROR(F11/F7,"-") -> 0.23971256 | G42: =IFERROR(G11/G7,"-") -> 0.26915064
B43: FCF Margin (FCF / Revenue) | C43: =IFERROR(C23/C7,"-") -> 0.25409699 | D43: =IFERROR(D23/D7,"-") -> 0.28261498 | E43: =IFERROR(E23/E7,"-") -> 0.25981711 | F43: =IFERROR(F23/F7,"-") -> 0.27825386 | G43: =IFERROR(G23/G7,"-") -> 0.23732882
B45: Return Ratios
B46: Return on Equity (ROE = NI / Equity) | C46: =IFERROR(C11/C18,"-") -> 1.5007133 | D46: =IFERROR(D11/D18,"-") -> 1.9695887 | E46: =IFERROR(E11/E18,"-") -> 1.5607601 | F46: =IFERROR(F11/F18,"-") -> 1.645935 | G46: =IFERROR(G11/G18,"-") -> 1.5191298
B47: Return on Assets (ROA = NI / Total Assets) | C47: =IFERROR(C11/C15,"-") -> 0.26974205 | D47: =IFERROR(D11/D15,"-") -> 0.28292441 | E47: =IFERROR(E11/E15,"-") -> 0.27509835 | F47: =IFERROR(F11/F15,"-") -> 0.25682503 | G47: =IFERROR(G11/G15,"-") -> 0.31179626
B48: Return on Invested Capital (ROIC = EBIT / (Assets – Current Liabilities)) | C48: =IFERROR(C10/(C15-C16),"-") -> 0.48309913 | D48: =IFERROR(D10/(D15-D16),"-") -> 0.60087135 | E48: =IFERROR(E10/(E15-E16),"-") -> 0.55144615 | F48: =IFERROR(F10/(F15-F16),"-") -> 0.65336077 | G48: =IFERROR(G10/(G15-G16),"-") -> 0.68720624
B49: Return on Capital Employed (ROCE = EBIT / (Assets – Current Liab)) | C49: =IFERROR(C10/(C15-C16),"-") -> 0.48309913 | D49: =IFERROR(D10/(D15-D16),"-") -> 0.60087135 | E49: =IFERROR(E10/(E15-E16),"-") -> 0.55144615 | F49: =IFERROR(F10/(F15-F16),"-") -> 0.65336077 | G49: =IFERROR(G10/(G15-G16),"-") -> 0.68720624
B51: Efficiency Ratios
B52: Asset Turnover (Revenue / Total Assets) | C52: =IFERROR(C7/C15,"-") -> 1.0422077 | D52: =IFERROR(D7/D15,"-") -> 1.1178523 | E52: =IFERROR(E7/E15,"-") -> 1.0870774 | F52: =IFERROR(F7/F15,"-") -> 1.0713875 | G52: =IFERROR(G7/G15,"-") -> 1.1584452
B53: Revenue per Employee (enter headcount in CFO section as memo) | C53: "-" | D53: "-" | E53: "-" | F53: "-" | G53: "-"
B55: Cash Flow Ratios
B56: CFO-to-Net Income | C56: =IFERROR(C21/C11,"-") -> 1.0988382 | D56: =IFERROR(D21/D11,"-") -> 1.2239211 | E56: =IFERROR(E21/E11,"-") -> 1.1396773 | F56: =IFERROR(F21/F11,"-") -> 1.2615644 | G56: =IFERROR(G21/G11,"-") -> 0.99528614
B57: CapEx Intensity (CapEx / Revenue) | C57: =IFERROR(ABS(C22)/C7,"-") -> 0.030302036 | D57: =IFERROR(ABS(D22)/D7,"-") -> 0.027155059 | E57: =IFERROR(ABS(E22)/E7,"-") -> 0.028592301 | F57: =IFERROR(ABS(F22)/F7,"-") -> 0.024158963 | G57: =IFERROR(ABS(G22)/G7,"-") -> 0.030553079
B58: FCF Conversion (FCF / Net Income) | C58: =IFERROR(C23/C11,"-") -> 0.98175961 | D58: =IFERROR(D23/D11,"-") -> 1.1166298 | E58: =IFERROR(E23/E11,"-") -> 1.0266921 | F58: =IFERROR(F23/F11,"-") -> 1.1607813 | G58: =IFERROR(G23/G11,"-") -> 0.88176948

Sheet DCF
A1: DCF Valuation | Unlevered Free Cash Flow | USD ($M)
A2: Mid-year discounting | 3-year explicit period | All drivers from Assumptions tab
B3: ='Income Statement'!G4 -> FY2025 | C3: ='Income Statement'!H4 -> FY2026 | D3: ='Income Statement'!I4 -> FY2027 | E3: ='Income Statement'!J4 -> FY2028 | F3: ='Income Statement'!K4 -> FY2029 | G3: ='Income Statement'!L4 -> FY2030
A4: UFCF BUILD
A5: Revenue ($M) | B5: ='Income Statement'!G10 -> 416161000000 | C5: ='Income Statement'!H10 -> 4.4354092e+11 | D5: ='Income Statement'!I10 -> 4.7343228e+11 | E5: ='Income Statement'!J10 -> 5.0612544e+11 | F5: ='Income Statement'!K10 -> 5.4194796e+11 | G5: ='Income Statement'!L10 -> 5.8126957e+11
A6: EBITDA ($M) | B6: ='Income Statement'!G56 -> 133050000000 | C6: ='Income Statement'!H56 -> 1.5743259e+11 | D6: ='Income Statement'!I56 -> 1.7462641e+11 | E6: ='Income Statement'!J56 -> 1.9334254e+11 | F6: ='Income Statement'!K56 -> 2.0650749e+11 | G6: ='Income Statement'!L56 -> 2.2695727e+11
A7: (–) D&A ($M) | B7: ='Cash Flow Statement'!G9 -> 11698000000 | C7: ='Cash Flow Statement'!H9 -> 1.2419146e+10 | D7: ='Cash Flow Statement'!I9 -> 1.3256104e+10 | E7: ='Cash Flow Statement'!J9 -> 1.3665387e+10 | F7: ='Cash Flow Statement'!K9 -> 1.4632595e+10 | G7: ='Cash Flow Statement'!L9 -> 1.5694278e+10
A8: EBIT ($M) | B8: ='Income Statement'!G34 -> 133050000000 | C8: ='Income Statement'!H34 -> 1.4501345e+11 | D8: ='Income Statement'!I34 -> 1.613703e+11 | E8: ='Income Statement'!J34 -> 1.7967715e+11 | F8: ='Income Statement'!K34 -> 1.918749e+11 | G8: ='Income Statement'!L34 -> 2.1126299e+11
A9: (–) Tax on EBIT | B9: ='Income Statement'!G47 -> 20719000000 | C9: ='Income Statement'!H47 -> 3.0452824e+10 | D9: ='Income Statement'!I47 -> 3.3887764e+10 | E9: ='Income Statement'!J47 -> 3.7732202e+10 | F9: ='Income Statement'!K47 -> 4.0293729e+10 | G9: ='Income Statement'!L47 -> 4.4365227e+10
A10: NOPAT ($M) | B10: =B8-B9 -> 112331000000 | C10: =C8-C9 -> 1.1456062e+11 | D10: =D8-D9 -> 1.2748254e+11 | E10: =E8-E9 -> 1.4194495e+11 | F10: =F8-F9 -> 1.5158117e+11 | G10: =G8-G9 -> 1.6689776e+11
A11: (+) D&A | B11: =B7 -> 11698000000 | C11: =C7 -> 1.2419146e+10 | D11: =D7 -> 1.3256104e+10 | E11: =E7 -> 1.3665387e+10 | F11: =F7 -> 1.4632595e+10 | G11: =G7 -> 1.5694278e+10
A12: (–) CapEx ($M) | B12: =-'Cash Flow Statement'!G25 -> 12715000000 | C12: ='Cash Flow Statement'!H25 -> -1.3749769e+10 | D12: ='Cash Flow Statement'!I25 -> -1.4202968e+10 | E12: ='Cash Flow Statement'!J25 -> -1.4677638e+10 | F12: ='Cash Flow Statement'!K25 -> -1.5716491e+10 | G12: ='Cash Flow Statement'!L25 -> -1.6275548e+10
A13: (–) Change in NWC | B13: =('Balance Sheet'!G14-'Balance Sheet'!G8-'Balance Sheet'!G9)-('Balance Sheet'!G36-'Balance Sheet'!G33-'Balance Sheet'!G32)-(('Balance Sheet'!F14-'Balance Sheet'!F8-'Balance Sheet'!F9)-('Balance Sheet'!F36-'Balance Sheet'!F33-'Balance Sheet'!F32)) -> 15655000000 | C13: =-B13 -> -15655000000 | D13: =-C13 -> 15655000000 | E13: =-D13 -> -15655000000 | F13: =-E13 -> 15655000000 | G13: =-F13 -> -15655000000
A14: Unlevered FCF — UFCF ($M) | B14: =B10+B11-B12-B13 -> 95659000000 | C14: =C10+C11-C12-C13 -> 1.5638454e+11 | D14: =D10+D11-D12-D13 -> 1.3928661e+11 | E14: =E10+E11-E12-E13 -> 1.8594298e+11 | F14: =F10+F11-F12-F13 -> 1.6627526e+11 | G14: =G10+G11-G12-G13 -> 2.1452259e+11
A16: WACC
A17: Cost of Equity | B17: ='Assumptions & Drivers'!D39 -> 0.103
A18: After-Tax Cost of Debt | B18: ='Assumptions & Drivers'!D42 -> 0.0237
A19: WACC | B19: ='Assumptions & Drivers'!D45 -> 0.098242
A21: PV OF UFCF (Mid-Year Convention)
A22: Discount Period | B22: 0.5 | C22: 1.5 | D22: 2.5 | E22: 3.5 | F22: 4.5 | G22: 5.5
A23: Discount Factor [1/(1+WACC)^t] | B23: =1/(1+$B$19)^B22 -> 0.95422541 | C23: =1/(1+$B$19)^C22 -> 0.86886625 | D23: =1/(1+$B$19)^D22 -> 0.7911428 | E23: =1/(1+$B$19)^E22 -> 0.72037201 | F23: =1/(1+$B$19)^F22 -> 0.65593194 | G23: =1/(1+$B$19)^G22 -> 0.59725629
A24: PV of UFCF ($M) | B24: =B14*B23 -> 9.1280248e+10 | C24: =C14*C23 -> 1.3587725e+11 | D24: =D14*D23 -> 1.101956e+11 | E24: =E14*E23 -> 1.3394812e+11 | F24: =F14*F23 -> 1.0906525e+11 | G24: =G14*G23 -> 1.2812496e+11
A25: Sum of PV UFCFs ($M) | B25: =SUM(B24:G24) -> 7.0849143e+11
A27: TERMINAL VALUE
A28: Terminal Year EBITDA ($M) | B28: =G6 -> 2.2695727e+11
A29: TV – Gordon Growth [UFCF3×(1+g)/(WACC–g)] | B29: =G14*(1+'Assumptions & Drivers'!D53)/($B$19-'Assumptions & Drivers'!D53) -> 3.0021798e+12
A30: TV – Exit EV/EBITDA [EBITDA3 × multiple] | B30: =G6*'Assumptions & Drivers'!D54 -> 3.404359e+12
A31: PV of TV – Gordon Growth [TV/(1+WACC)³] | B31: =B29/(1+$B$19)^5.5 -> 1.7930708e+12
A32: PV of TV – Exit Multiple [TV/(1+WACC)³] | B32: =B30/(1+$B$19)^6 -> 1.9402025e+12
A34: ENTERPRISE VALUE
A35: EV – Gordon Growth ($M) | B35: =B25+B31 -> 2.5015622e+12
A36: EV – Exit Multiple ($M) | B36: =B25+B32 -> 2.6486939e+12
A38: EQUITY BRIDGE → IMPLIED SHARE PRICE
A39: (–) Net Debt ($M) | B39: =-('Raw (Balance Sheet)'!N6+'Raw (Balance Sheet)'!N9+'Raw (Balance Sheet)'!N29-'Raw (Balance Sheet)'!N56-'Raw (Balance Sheet)'!N59-'Raw (Balance Sheet)'!N69) -> -33763000000
A40: Equity Value – GGM ($M) | B40: =B35-B39 -> 2.5353252e+12
A41: Equity Value – Exit ($M) | B41: =B36-B39 -> 2.6824569e+12
A42: Shares Outstanding | B42: ='Income Statement'!G53 -> 15004697000
A43: ⭐ Implied Share Price – Gordon Growth ($) | B43: =IFERROR(B40/B42,0) -> 168.96877
A44: ⭐ Implied Share Price – Exit Multiple ($) | B44: =IFERROR(B41/B42,0) -> 178.77448
A45: ⭐ Book Value of Share Price | B45: ='Balance Sheet'!G53/'Assumptions & Drivers'!D48 -> 4.9139946 | C45: =B44/B45 -> 36.380683

Sheet Sensitivity Analysis
A1: Sensitivity Analysis | Heat-map
A2: All cells formula-linked: UFCFs from DCF tab, net debt & shares from Assumptions tab
A4: Table 1: Implied Price – GGM ($) | WACC (rows) vs Terminal Growth Rate (cols)
A5: WACC ↓ TGR → | B5: 0.02 | C5: 0.025 | D5: 0.03 | E5: 0.035 | F5: 0.04
A6: 8% | B6: =IFERROR(((DCF!$B$14/(1+$A6)^DCF!$B$22+DCF!$C$14/(1+$A6)^DCF!$C$22+DCF!$D$14/(1+$A6)^DCF!$D$22+DCF!$E$14/(1+$A6)^DCF!$E$22+DCF!$F$14/(1+$A6)^DCF!$F$22+DCF!$G$14/(1+$A6)^DCF!$G$22)+((DCF!$G$14*(1+B$5)/($A6-B$5))/(1+$A6)^5.5)-DCF!$B$39)/DCF!$B$42,0) -> 211.16684 | C6: =IFERROR(((DCF!$B$14/(1+$A6)^DCF!$B$22+DCF!$C$14/(1+$A6)^DCF!$C$22+DCF!$D$14/(1+$A6)^DCF!$D$22+DCF!$E$14/(1+$A6)^DCF!$E$22+DCF!$F$14/(1+$A6)^DCF!$F$22+DCF!$G$14/(1+$A6)^DCF!$G$22)+((DCF!$G$14*(1+C$5)/($A6-C$5))/(1+$A6)^5.5)-DCF!$B$39)/DCF!$B$42,0) -> 226.48812 | D6: =IFERROR(((DCF!$B$14/(1+$A6)^DCF!$B$22+DCF!$C$14/(1+$A6)^DCF!$C$22+DCF!$D$14/(1+$A6)^DCF!$D$22+DCF!$E$14/(1+$A6)^DCF!$E$22+DCF!$F$14/(1+$A6)^DCF!$F$22+DCF!$G$14/(1+$A6)^DCF!$G$22)+((DCF!$G$14*(1+D$5)/($A6-D$5))/(1+$A6)^5.5)-DCF!$B$39)/DCF!$B$42,0) -> 244.87365 | E6: =IFERROR(((DCF!$B$14/(1+$A6)^DCF!$B$22+DCF!$C$14/(1+$A6)^DCF!$C$22+DCF!$D$14/(1+$A6)^DCF!$D$22+DCF!$E$14/(1+$A6)^DCF!$E$22+DCF!$F$14/(1+$A6)^DCF!$F$22+DCF!$G$14/(1+$A6)^DCF!$G$22)+((DCF!$G$14*(1+E$5)/($A6-E$5))/(1+$A6)^5.5)-DCF!$B$39)/DCF!$B$42,0) -> 267.34486 | F6: =IFERROR(((DCF!$B$14/(1+$A6)^DCF!$B$22+DCF!$C$14/(1+$A6)^DCF!$C$22+DCF!$D$14/(1+$A6)^DCF!$D$22+DCF!$E$14/(1+$A6)^DCF!$E$22+DCF!$F$14/(1+$A6)^DCF!$F$22+DCF!$G$14/(1+$A6)^DCF!$G$22)+((DCF!$G$14*(1+F$5)/($A6-F$5))/(1+$A6)^5.5)-DCF!$B$39)/DCF!$B$42,0) -> 295.43387
A7: 9% | B7: =IFERROR(((DCF!$B$14/(1+$A7)^DCF!$B$22+DCF!$C$14/(1+$A7)^DCF!$C$22+DCF!$D$14/(1+$A7)^DCF!$D$22+DCF!$E$14/(1+$A7)^DCF!$E$22+DCF!$F$14/(1+$A7)^DCF!$F$22+DCF!$G$14/(1+$A7)^DCF!$G$22)+((DCF!$G$14*(1+B$5)/($A7-B$5))/(1+$A7)^5.5)-DCF!$B$39)/DCF!$B$42,0) -> 180.27267 | C7: =IFERROR(((DCF!$B$14/(1+$A7)^DCF!$B$22+DCF!$C$14/(1+$A7)^DCF!$C$22+DCF!$D$14/(1+$A7)^DCF!$D$22+DCF!$E$14/(1+$A7)^DCF!$E$22+DCF!$F$14/(1+$A7)^DCF!$F$22+DCF!$G$14/(1+$A7)^DCF!$G$22)+((DCF!$G$14*(1+C$5)/($A7-C$5))/(1+$A7)^5.5)-DCF!$B$39)/DCF!$B$42,0) -> 190.93336 | D7: =IFERROR(((DCF!$B$14/(1+$A7)^DCF!$B$22+DCF!$C$14/(1+$A7)^DCF!$C$22+DCF!$D$14/(1+$A7)^DCF!$D$22+DCF!$E$14/(1+$A7)^DCF!$E$22+DCF!$F$14/(1+$A7)^DCF!$F$22+DCF!$G$14/(1+$A7)^DCF!$G$22)+((DCF!$G$14*(1+D$5)/($A7-D$5))/(1+$A7)^5.5)-DCF!$B$39)/DCF!$B$42,0) -> 203.37082 | E7: =IFERROR(((DCF!$B$14/(1+$A7)^DCF!$B$22+DCF!$C$14/(1+$A7)^DCF!$C$22+DCF!$D$14/(1+$A7)^DCF!$D$22+DCF!$E$14/(1+$A7)^DCF!$E$22+DCF!$F$14/(1+$A7)^DCF!$F$22+DCF!$G$14/(1+$A7)^DCF!$G$22)+((DCF!$G$14*(1+E$5)/($A7-E$5))/(1+$A7)^5.5)-DCF!$B$39)/DCF!$B$42,0) -> 218.06965 | F7: =IFERROR(((DCF!$B$14/(1+$A7)^DCF!$B$22+DCF!$C$14/(1+$A7)^DCF!$C$22+DCF!$D$14/(1+$A7)^DCF!$D$22+DCF!$E$14/(1+$A7)^DCF!$E$22+DCF!$F$14/(1+$A7)^DCF!$F$22+DCF!$G$14/(1+$A7)^DCF!$G$22)+((DCF!$G$14*(1+F$5)/($A7-F$5))/(1+$A7)^5.5)-DCF!$B$39)/DCF!$B$42,0) -> 235.70824
A8: 10% | B8: =IFERROR(((DCF!$B$14/(1+$A8)^DCF!$B$22+DCF!$C$14/(1+$A8)^DCF!$C$22+DCF!$D$14/(1+$A8)^DCF!$D$22+DCF!$E$14/(1+$A8)^DCF!$E$22+DCF!$F$14/(1+$A8)^DCF!$F$22+DCF!$G$14/(1+$A8)^DCF!$G$22)+((DCF!$G$14*(1+B$5)/($A8-B$5))/(1+$A8)^5.5)-DCF!$B$39)/DCF!$B$42,0) -> 157.15409 | C8: =IFERROR(((DCF!$B$14/(1+$A8)^DCF!$B$22+DCF!$C$14/(1+$A8)^DCF!$C$22+DCF!$D$14/(1+$A8)^DCF!$D$22+DCF!$E$14/(1+$A8)^DCF!$E$22+DCF!$F$14/(1+$A8)^DCF!$F$22+DCF!$G$14/(1+$A8)^DCF!$G$22)+((DCF!$G$14*(1+C$5)/($A8-C$5))/(1+$A8)^5.5)-DCF!$B$39)/DCF!$B$42,0) -> 164.91294 | D8: =IFERROR(((DCF!$B$14/(1+$A8)^DCF!$B$22+DCF!$C$14/(1+$A8)^DCF!$C$22+DCF!$D$14/(1+$A8)^DCF!$D$22+DCF!$E$14/(1+$A8)^DCF!$E$22+DCF!$F$14/(1+$A8)^DCF!$F$22+DCF!$G$14/(1+$A8)^DCF!$G$22)+((DCF!$G$14*(1+D$5)/($A8-D$5))/(1+$A8)^5.5)-DCF!$B$39)/DCF!$B$42,0) -> 173.7802 | E8: =IFERROR(((DCF!$B$14/(1+$A8)^DCF!$B$22+DCF!$C$14/(1+$A8)^DCF!$C$22+DCF!$D$14/(1+$A8)^DCF!$D$22+DCF!$E$14/(1+$A8)^DCF!$E$22+DCF!$F$14/(1+$A8)^DCF!$F$22+DCF!$G$14/(1+$A8)^DCF!$G$22)+((DCF!$G$14*(1+E$5)/($A8-E$5))/(1+$A8)^5.5)-DCF!$B$39)/DCF!$B$42,0) -> 184.01166 | F8: =IFERROR(((DCF!$B$14/(1+$A8)^DCF!$B$22+DCF!$C$14/(1+$A8)^DCF!$C$22+DCF!$D$14/(1+$A8)^DCF!$D$22+DCF!$E$14/(1+$A8)^DCF!$E$22+DCF!$F$14/(1+$A8)^DCF!$F$22+DCF!$G$14/(1+$A8)^DCF!$G$22)+((DCF!$G$14*(1+F$5)/($A8-F$5))/(1+$A8)^5.5)-DCF!$B$39)/DCF!$B$42,0) -> 195.94835
A9: 11% | B9: =IFERROR(((DCF!$B$14/(1+$A9)^DCF!$B$22+DCF!$C$14/(1+$A9)^DCF!$C$22+DCF!$D$14/(1+$A9)^DCF!$D$22+DCF!$E$14/(1+$A9)^DCF!$E$22+DCF!$F$14/(1+$A9)^DCF!$F$22+DCF!$G$14/(1+$A9)^DCF!$G$22)+((DCF!$G$14*(1+B$5)/($A9-B$5))/(1+$A9)^5.5)-DCF!$B$39)/DCF!$B$42,0) -> 139.21668 | C9: =IFERROR(((DCF!$B$14/(1+$A9)^DCF!$B$22+DCF!$C$14/(1+$A9)^DCF!$C$22+DCF!$D$14/(1+$A9)^DCF!$D$22+DCF!$E$14/(1+$A9)^DCF!$E$22+DCF!$F$14/(1+$A9)^DCF!$F$22+DCF!$G$14/(1+$A9)^DCF!$G$22)+((DCF!$G$14*(1+C$5)/($A9-C$5))/(1+$A9)^5.5)-DCF!$B$39)/DCF!$B$42,0) -> 145.05921 | D9: =IFERROR(((DCF!$B$14/(1+$A9)^DCF!$B$22+DCF!$C$14/(1+$A9)^DCF!$C$22+DCF!$D$14/(1+$A9)^DCF!$D$22+DCF!$E$14/(1+$A9)^DCF!$E$22+DCF!$F$14/(1+$A9)^DCF!$F$22+DCF!$G$14/(1+$A9)^DCF!$G$22)+((DCF!$G$14*(1+D$5)/($A9-D$5))/(1+$A9)^5.5)-DCF!$B$39)/DCF!$B$42,0) -> 151.63205 | E9: =IFERROR(((DCF!$B$14/(1+$A9)^DCF!$B$22+DCF!$C$14/(1+$A9)^DCF!$C$22+DCF!$D$14/(1+$A9)^DCF!$D$22+DCF!$E$14/(1+$A9)^DCF!$E$22+DCF!$F$14/(1+$A9)^DCF!$F$22+DCF!$G$14/(1+$A9)^DCF!$G$22)+((DCF!$G$14*(1+E$5)/($A9-E$5))/(1+$A9)^5.5)-DCF!$B$39)/DCF!$B$42,0) -> 159.08128 | F9: =IFERROR(((DCF!$B$14/(1+$A9)^DCF!$B$22+DCF!$C$14/(1+$A9)^DCF!$C$22+DCF!$D$14/(1+$A9)^DCF!$D$22+DCF!$E$14/(1+$A9)^DCF!$E$22+DCF!$F$14/(1+$A9)^DCF!$F$22+DCF!$G$14/(1+$A9)^DCF!$G$22)+((DCF!$G$14*(1+F$5)/($A9-F$5))/(1+$A9)^5.5)-DCF!$B$39)/DCF!$B$42,0) -> 167.59468
A10: 12% | B10: =IFERROR(((DCF!$B$14/(1+$A10)^DCF!$B$22+DCF!$C$14/(1+$A10)^DCF!$C$22+DCF!$D$14/(1+$A10)^DCF!$D$22+DCF!$E$14/(1+$A10)^DCF!$E$22+DCF!$F$14/(1+$A10)^DCF!$F$22+DCF!$G$14/(1+$A10)^DCF!$G$22)+((DCF!$G$14*(1+B$5)/($A10-B$5))/(1+$A10)^5.5)-DCF!$B$39)/DCF!$B$42,0) -> 124.90392 | C10: =IFERROR(((DCF!$B$14/(1+$A10)^DCF!$B$22+DCF!$C$14/(1+$A10)^DCF!$C$22+DCF!$D$14/(1+$A10)^DCF!$D$22+DCF!$E$14/(1+$A10)^DCF!$E$22+DCF!$F$14/(1+$A10)^DCF!$F$22+DCF!$G$14/(1+$A10)^DCF!$G$22)+((DCF!$G$14*(1+C$5)/($A10-C$5))/(1+$A10)^5.5)-DCF!$B$39)/DCF!$B$42,0) -> 129.4226 | D10: =IFERROR(((DCF!$B$14/(1+$A10)^DCF!$B$22+DCF!$C$14/(1+$A10)^DCF!$C$22+DCF!$D$14/(1+$A10)^DCF!$D$22+DCF!$E$14/(1+$A10)^DCF!$E$22+DCF!$F$14/(1+$A10)^DCF!$F$22+DCF!$G$14/(1+$A10)^DCF!$G$22)+((DCF!$G$14*(1+D$5)/($A10-D$5))/(1+$A10)^5.5)-DCF!$B$39)/DCF!$B$42,0) -> 134.44335 | E10: =IFERROR(((DCF!$B$14/(1+$A10)^DCF!$B$22+DCF!$C$14/(1+$A10)^DCF!$C$22+DCF!$D$14/(1+$A10)^DCF!$D$22+DCF!$E$14/(1+$A10)^DCF!$E$22+DCF!$F$14/(1+$A10)^DCF!$F$22+DCF!$G$14/(1+$A10)^DCF!$G$22)+((DCF!$G$14*(1+E$5)/($A10-E$5))/(1+$A10)^5.5)-DCF!$B$39)/DCF!$B$42,0) -> 140.05477 | F10: =IFERROR(((DCF!$B$14/(1+$A10)^DCF!$B$22+DCF!$C$14/(1+$A10)^DCF!$C$22+DCF!$D$14/(1+$A10)^DCF!$D$22+DCF!$E$14/(1+$A10)^DCF!$E$22+DCF!$F$14/(1+$A10)^DCF!$F$22+DCF!$G$14/(1+$A10)^DCF!$G$22)+((DCF!$G$14*(1+F$5)/($A10-F$5))/(1+$A10)^5.5)-DCF!$B$39)/DCF!$B$42,0) -> 146.36763
A13: Table 2: EBITDA Year 5 ($M) | Revenue Growth (rows) vs EBITDA Margin (cols)
A14: Rev Gr ↓ Mgn → | B14: 0.2 | C14: 0.25 | D14: 0.3 | E14: 0.35 | F14: 0.4
A15: 0.02 | B15: ='Income Statement'!$G$10*(1+$A15)^5*B$14 -> 9.1895074e+10 | C15: ='Income Statement'!$G$10*(1+$A15)^5*C$14 -> 1.1486884e+11 | D15: ='Income Statement'!$G$10*(1+$A15)^5*D$14 -> 1.3784261e+11 | E15: ='Income Statement'!$G$10*(1+$A15)^5*E$14 -> 1.6081638e+11 | F15: ='Income Statement'!$G$10*(1+$A15)^5*F$14 -> 1.8379015e+11
A16: 0.03 | B16: ='Income Statement'!$G$10*(1+$A16)^5*B$14 -> 9.6488932e+10 | C16: ='Income Statement'!$G$10*(1+$A16)^5*C$14 -> 1.2061116e+11 | D16: ='Income Statement'!$G$10*(1+$A16)^5*D$14 -> 1.447334e+11 | E16: ='Income Statement'!$G$10*(1+$A16)^5*E$14 -> 1.6885563e+11 | F16: ='Income Statement'!$G$10*(1+$A16)^5*F$14 -> 1.9297786e+11
A17: 0.04 | B17: ='Income Statement'!$G$10*(1+$A17)^5*B$14 -> 1.012647e+11 | C17: ='Income Statement'!$G$10*(1+$A17)^5*C$14 -> 1.2658087e+11 | D17: ='Income Statement'!$G$10*(1+$A17)^5*D$14 -> 1.5189705e+11 | E17: ='Income Statement'!$G$10*(1+$A17)^5*E$14 -> 1.7721322e+11 | F17: ='Income Statement'!$G$10*(1+$A17)^5*F$14 -> 2.025294e+11
A18: 0.05 | B18: ='Income Statement'!$G$10*(1+$A18)^5*B$14 -> 1.0622772e+11 | C18: ='Income Statement'!$G$10*(1+$A18)^5*C$14 -> 1.3278465e+11 | D18: ='Income Statement'!$G$10*(1+$A18)^5*D$14 -> 1.5934158e+11 | E18: ='Income Statement'!$G$10*(1+$A18)^5*E$14 -> 1.8589851e+11 | F18: ='Income Statement'!$G$10*(1+$A18)^5*F$14 -> 2.1245544e+11
A19: 0.06 | B19: ='Income Statement'!$G$10*(1+$A19)^5*B$14 -> 1.1138346e+11 | C19: ='Income Statement'!$G$10*(1+$A19)^5*C$14 -> 1.3922932e+11 | D19: ='Income Statement'!$G$10*(1+$A19)^5*D$14 -> 1.6707519e+11 | E19: ='Income Statement'!$G$10*(1+$A19)^5*E$14 -> 1.9492105e+11 | F19: ='Income Statement'!$G$10*(1+$A19)^5*F$14 -> 2.2276692e+11
A20: 0.07 | B20: ='Income Statement'!$G$10*(1+$A20)^5*B$14 -> 1.1673747e+11 | C20: ='Income Statement'!$G$10*(1+$A20)^5*C$14 -> 1.4592183e+11 | D20: ='Income Statement'!$G$10*(1+$A20)^5*D$14 -> 1.751062e+11 | E20: ='Income Statement'!$G$10*(1+$A20)^5*E$14 -> 2.0429057e+11 | F20: ='Income Statement'!$G$10*(1+$A20)^5*F$14 -> 2.3347493e+11
A21: 0.08 | B21: ='Income Statement'!$G$10*(1+$A21)^5*B$14 -> 1.2229541e+11 | C21: ='Income Statement'!$G$10*(1+$A21)^5*C$14 -> 1.5286926e+11 | D21: ='Income Statement'!$G$10*(1+$A21)^5*D$14 -> 1.8344311e+11 | E21: ='Income Statement'!$G$10*(1+$A21)^5*E$14 -> 2.1401696e+11 | F21: ='Income Statement'!$G$10*(1+$A21)^5*F$14 -> 2.4459082e+11
A22: 0.09 | B22: ='Income Statement'!$G$10*(1+$A22)^5*B$14 -> 1.2806306e+11 | C22: ='Income Statement'!$G$10*(1+$A22)^5*C$14 -> 1.6007882e+11 | D22: ='Income Statement'!$G$10*(1+$A22)^5*D$14 -> 1.9209459e+11 | E22: ='Income Statement'!$G$10*(1+$A22)^5*E$14 -> 2.2411035e+11 | F22: ='Income Statement'!$G$10*(1+$A22)^5*F$14 -> 2.5612611e+11
A23: 0.1 | B23: ='Income Statement'!$G$10*(1+$A23)^5*B$14 -> 1.3404629e+11 | C23: ='Income Statement'!$G$10*(1+$A23)^5*C$14 -> 1.6755786e+11 | D23: ='Income Statement'!$G$10*(1+$A23)^5*D$14 -> 2.0106944e+11 | E23: ='Income Statement'!$G$10*(1+$A23)^5*E$14 -> 2.3458101e+11 | F23: ='Income Statement'!$G$10*(1+$A23)^5*F$14 -> 2.6809258e+11
A24: 0.11 | B24: ='Income Statement'!$G$10*(1+$A24)^5*B$14 -> 1.402511e+11 | C24: ='Income Statement'!$G$10*(1+$A24)^5*C$14 -> 1.7531387e+11 | D24: ='Income Statement'!$G$10*(1+$A24)^5*D$14 -> 2.1037665e+11 | E24: ='Income Statement'!$G$10*(1+$A24)^5*E$14 -> 2.4543942e+11 | F24: ='Income Statement'!$G$10*(1+$A24)^5*F$14 -> 2.8050219e+11
A25: 0.12 | B25: ='Income Statement'!$G$10*(1+$A25)^5*B$14 -> 1.4668358e+11 | C25: ='Income Statement'!$G$10*(1+$A25)^5*C$14 -> 1.8335447e+11 | D25: ='Income Statement'!$G$10*(1+$A25)^5*D$14 -> 2.2002536e+11 | E25: ='Income Statement'!$G$10*(1+$A25)^5*E$14 -> 2.5669626e+11 | F25: ='Income Statement'!$G$10*(1+$A25)^5*F$14 -> 2.9336715e+11

Sheet Scenario Analysis
A1: Scenario Analysis
A2: Change cell B2 to switch scenario
A4: Selected Scenario → | B4: Bear
A6: Driver | B6: Current | C6: Bull | D6: Normal | E6: Bear
A7: Product Revenue Growth (YoY %) | B7: ='Assumptions & Drivers'!E7 -> 0.04116107 | C7: 0.1 | D7: 0.07 | E7: 0.05
A8: Services Revenue Growth (YoY %) | B8: ='Assumptions & Drivers'!E8 -> 0.13506431 | C8: 0.1 | D8: 0.07 | E8: 0.05
A9: Effective Tax Rate (%) | B9: ='Assumptions & Drivers'!E27 -> 0.21 | C9: 0.21 | D9: 0.21 | E9: 0.21
A10: Annual Share Buyback ($mm) | B10: ='Assumptions & Drivers'!E32 -> 90000 | C10: 90000 | D10: 90000 | E10: 90000
A11: WACC (%) | B11: ='Assumptions & Drivers'!D45 -> 0.098242 | C11: 0.08 | D11: 0.088842 | E11: 0.098242
A12: Terminal Growth Rate (Gordon Growth) | B12: ='Assumptions & Drivers'!D53 -> 0.025 | C12: 0.035 | D12: 0.03 | E12: 0.025
A13: Exit EV/EBITDA Multiple | B13: ='Assumptions & Drivers'!D54 -> 15 | C13: 20 | D13: 15 | E13: 15
A16: ── SELECTED SCENARIO OUTPUTS ──
A17: KPI | B17: Current | C17: Selected | D17: Bull | E17: Normal | F17: Bear
A18: Revenue Y5 ($M) | B18: =DCF!G5 -> 5.8126957e+11 | C18: =INDEX(E18:F18,1,MATCH($B$4,$E$17:$F$17,0)) -> 5.3113861e+11 | D18: 6.7023145e+11 | E18: 5.8368733e+11 | F18: 5.3113861e+11
A19: EBITDA Y5 ($M) | B19: =DCF!G6 -> 2.2695727e+11 | C19: =INDEX(E19:F19,1,MATCH($B$4,$E$17:$F$17,0)) -> 1.8891169e+11 | D19: 2.3838327e+11 | E19: 2.0760186e+11 | F19: 1.8891169e+11
A20: EBITDA Margin Y5 | B20: ='Income Statement'!L57 -> 0.39045097 | C20: =INDEX(E20:F20,1,MATCH($B$4,$E$17:$F$17,0)) -> 0.35567306 | D20: 0.35567306 | E20: 0.35567306 | F20: 0.35567306
A21: Net Debt ($M) | B21: =DCF!B39 -> -33763000000 | C21: =INDEX(E21:F21,1,MATCH($B$4,$E$17:$F$17,0)) -> -33763000000 | D21: -33763000000 | E21: -33763000000 | F21: -33763000000
A22: Equity Value – GGM ($M) | B22: =DCF!B40 -> 2.5353252e+12 | C22: =INDEX(E22:F22,1,MATCH($B$4,$E$17:$F$17,0)) -> 1.8848393e+12 | D22: 3.6327738e+12 | E22: 2.4973807e+12 | F22: 1.8848393e+12
A23: Equity Value – Exit ($M) | B23: =DCF!B41 -> 2.6824569e+12 | C23: =INDEX(E23:F23,1,MATCH($B$4,$E$17:$F$17,0)) -> 2.2026406e+12 | D23: 3.6990745e+12 | E23: 2.4999195e+12 | F23: 2.2026406e+12
A24: Shares Outstanding | B24: =DCF!B42 -> 15004697000 | C24: =INDEX(E24:F24,1,MATCH($B$4,$E$17:$F$17,0)) -> 15004697000 | D24: 15004697000 | E24: 15004697000 | F24: 15004697000
A25: ⭐ Implied Share Price – Gordon Growth ($) | B25: =DCF!B43 -> 168.96877 | C25: =INDEX(E25:F25,1,MATCH($B$4,$E$17:$F$17,0)) -> 125.61662 | D25: 242.10911 | E25: 166.43993 | F25: 125.61662
A26: ⭐ Implied Share Price – Exit Multiple ($) | B26: =DCF!B44 -> 178.77448 | C26: =INDEX(E26:F26,1,MATCH($B$4,$E$17:$F$17,0)) -> 146.79674 | D26: 246.52777 | E26: 166.60913 | F26: 146.79674

Sheet Stress Testing
A1: Stress Testing | Shock scenarios on key risk factors
A2: Revenue shock is additive to each year's base growth | All $ in USD ($M)
A4: Scenario | B4: Rev Shock | C4: EBITDA Mgn | D4: Revenue Y3 | E4: EBITDA Y3 | F4: Net Debt | G4: Debt / EBITDA | H4: Debt Repay (yrs)
A5: Base Case | B5: 0 | C5: =[1]Assumptions!C12 -> 0.22 | D5: =[1]Assumptions!C5*(1+[1]Assumptions!C6+0)*(1+[1]Assumptions!C7+0)*(1+[1]Assumptions!C8+0) -> 1224.936 | E5: =D5*C5 -> 269.48592 | F5: =[1]Assumptions!C24*1 -> 200 | G5: =IFERROR(F5/E5,"-") -> 0.7421538 | H5: =IFERROR(F5/(E5*(1-[1]Assumptions!C22)),"-") -> 0.9895384
A6: Revenue –20% | B6: -0.2 | C6: =[1]Assumptions!C12 -> 0.22 | D6: =[1]Assumptions!C5*(1+[1]Assumptions!C6+-0.2)*(1+[1]Assumptions!C7+-0.2)*(1+[1]Assumptions!C8+-0.2) -> 658.416 | E6: =D6*C6 -> 144.85152 | F6: =[1]Assumptions!C24*1 -> 200 | G6: =IFERROR(F6/E6,"-") -> 1.3807242 | H6: =IFERROR(F6/(E6*(1-[1]Assumptions!C22)),"-") -> 1.8409656
A7: Revenue –40% | B7: -0.4 | C7: 0.18 | D7: =[1]Assumptions!C5*(1+[1]Assumptions!C6+-0.4)*(1+[1]Assumptions!C7+-0.4)*(1+[1]Assumptions!C8+-0.4) -> 300.696 | E7: =D7*C7 -> 54.12528 | F7: =[1]Assumptions!C24*1 -> 200 | G7: =IFERROR(F7/E7,"-") -> 3.695131 | H7: =IFERROR(F7/(E7*(1-[1]Assumptions!C22)),"-") -> 4.9268413
A8: Margin Compression | B8: 0 | C8: 0.14 | D8: =[1]Assumptions!C5*(1+[1]Assumptions!C6+0)*(1+[1]Assumptions!C7+0)*(1+[1]Assumptions!C8+0) -> 1224.936 | E8: =D8*C8 -> 171.49104 | F8: =[1]Assumptions!C24*1 -> 200 | G8: =IFERROR(F8/E8,"-") -> 1.1662417 | H8: =IFERROR(F8/(E8*(1-[1]Assumptions!C22)),"-") -> 1.5549889
A9: Rate Shock (+2%) | B9: 0 | C9: =[1]Assumptions!C12 -> 0.22 | D9: =[1]Assumptions!C5*(1+[1]Assumptions!C6+0)*(1+[1]Assumptions!C7+0)*(1+[1]Assumptions!C8+0) -> 1224.936 | E9: =D9*C9 -> 269.48592 | F9: =[1]Assumptions!C24*1 -> 200 | G9: =IFERROR(F9/E9,"-") -> 0.7421538 | H9: =IFERROR(F9/(E9*(1-[1]Assumptions!C22)),"-") -> 0.9895384
A10: Liquidity Squeeze | B10: 0 | C10: =[1]Assumptions!C12 -> 0.22 | D10: =[1]Assumptions!C5*(1+[1]Assumptions!C6+0)*(1+[1]Assumptions!C7+0)*(1+[1]Assumptions!C8+0) -> 1224.936 | E10: =D10*C10 -> 269.48592 | F10: =[1]Assumptions!C24*2 -> 400 | G10: =IFERROR(F10/E10,"-") -> 1.4843076 | H10: =IFERROR(F10/(E10*(1-[1]Assumptions!C22)),"-") -> 1.9790768
A11: Combined Stress | B11: -0.25 | C11: 0.15 | D11: =[1]Assumptions!C5*(1+[1]Assumptions!C6+-0.25)*(1+[1]Assumptions!C7+-0.25)*(1+[1]Assumptions!C8+-0.25) -> 551.286 | E11: =D11*C11 -> 82.6929 | F11: =[1]Assumptions!C24*1.5 -> 300 | G11: =IFERROR(F11/E11,"-") -> 3.627881 | H11: =IFERROR(F11/(E11*(1-[1]Assumptions!C22)),"-") -> 4.8371747
A13: Notes:
A14: • Only applicable to company's that have (+) Net Debt
A15: • Revenue Shock = additive adjustment to each year's base growth rate from Assumptions tab
A16: • EBITDA Margin: "-" = carries Assumptions Y3 margin; numeric = scenario override
A17: • Debt Repayment (yrs) = Net Debt ÷ (EBITDA × (1–Tax)) | Simplified liquidity proxy
A18: • Rate Shock row: manually increase "Pre-Tax Cost of Debt" in Assumptions by +2% to model impact
